Workbook
Name DoubleCount: 'Envizi mapping notes'!$A$23:$A$36

Sheet Summary
B2: Forecast Buffer | C2: 0.05
B4: Country | C4: Australia | H4: Country | I4: New Zealand
B6: Row Labels | C6: Count of Connection ID | D6: Sum of FY26 Budget | E6: Sum of FY27 Budget | F6: Sum of FY28 Budget | H6: Row Labels | I6: Count of Connection ID | J6: Sum of FY26 Budget | K6: Sum of FY27 Budget | L6: Sum of FY28 Budget
B7: Electricity | H7: Electricity
B8: AU Large Electricity | H8: NZ NTOU Electricity
B9: ACT | C9: 1 | D9: 250500 | E9: 194100 | F9: 192500 | H9: North Island | I9: 96 | J9: 894400 | K9: 1046200 | L9: 1046200
B10: NSW | C10: 36 | D10: 8697700 | E10: 7443200 | F10: 7402300 | H10: South Island | I10: 36 | J10: 367000 | K10: 405300 | L10: 405300
B11: NT | C11: 3 | D11: 718000 | E11: 822300 | F11: 822300 | H11: NZ NTOU Electricity Total | I11: 132 | J11: 1261400 | K11: 1451500 | L11: 1451500
B12: QLD | C12: 17 | D12: 4434000 | E12: 4031200 | F12: 4061800 | H12: NZ TOU Electricity
B13: SA | C13: 4 | D13: 556200 | E13: 452900 | F13: 454900 | H13: North Island | I13: 17 | J13: 2353000 | K13: 1928800 | L13: 1928800
B14: TAS | C14: 3 | D14: 402900 | E14: 321700 | F14: 321300 | H14: South Island | I14: 9 | J14: 705700 | K14: 631000 | L14: 631000
B15: VIC | C15: 10 | D15: 1082100 | E15: 1056600 | F15: 1061500 | H15: NZ TOU Electricity Total | I15: 26 | J15: 3058700 | K15: 2559800 | L15: 2559800
B16: WA | C16: 7 | D16: 2045700 | E16: 1937600 | F16: 1937600 | H16: Electricity Total | I16: 158 | J16: 4320100 | K16: 4011300 | L16: 4011300
B17: AU Large Electricity Total | C17: 81 | D17: 18187100 | E17: 16259600 | F17: 16254200 | H17: Natural Gas
B18: AU Small Energy | H18: NZ NTOU Natural Gas
B19: NSW | C19: 11 | D19: 198000 | E19: 150000 | F19: 150000 | H19: North Island | I19: 12 | J19: 17100 | K19: 17900 | L19: 17900
B20: QLD | C20: 5 | D20: 62400 | E20: 61500 | F20: 61500 | H20: NZ NTOU Natural Gas Total | I20: 12 | J20: 17100 | K20: 17900 | L20: 17900
B21: SA | C21: 10 | D21: 74600 | E21: 66500 | F21: 66500 | H21: NZ TOU Natural Gas
B22: VIC | C22: 24 | D22: 152500 | E22: 117100 | F22: 117100 | H22: North Island | I22: 8 | J22: 5325500 | K22: 4602800 | L22: 4602800
B23: AU Small Energy Total | C23: 50 | D23: 487500 | E23: 395100 | F23: 395100 | H23: NZ TOU Natural Gas Total | I23: 8 | J23: 5325500 | K23: 4602800 | L23: 4602800
B24: Electricity Total | C24: 131 | D24: 18674600 | E24: 16654700 | F24: 16649300 | H24: Natural Gas Total | I24: 20 | J24: 5342600 | K24: 4620700 | L24: 4620700
B25: Natural Gas | H25: Grand Total | I25: 178 | J25: 9662700 | K25: 8632000 | L25: 8632000
B26: AU Large Natural Gas
B27: ACT | C27: 1 | D27: 1015100 | E27: 982100 | F27: 975800
B28: NSW | C28: 4 | D28: 3310300 | E28: 3173000 | F28: 3188000
B29: SA | C29: 2 | D29: 2820800 | E29: 2750300 | F29: 2797600
B30: TAS | C30: 1 | D30: 283000 | E30: 283000 | F30: 283000
B31: VIC | C31: 3 | D31: 3976100 | E31: 3553100 | F31: 3559400
B32: WA | C32: 4 | D32: 985200 | E32: 959200 | F32: 959200
B33: AU Large Natural Gas Total | C33: 15 | D33: 12390500 | E33: 11700700 | F33: 11763000
B34: AU Small Energy
B35: NSW | C35: 11 | D35: 6500 | E35: 5500 | F35: 5500
B36: QLD | C36: 4 | D36: 67700 | E36: 69700 | F36: 69700
B37: SA | C37: 1 | D37: 22800 | E37: 26500 | F37: 26500
B38: VIC | C38: 1 | D38: 500 | E38: 500 | F38: 500
B39: AU Small Energy Total | C39: 17 | D39: 97500 | E39: 102200 | F39: 102200
B40: Natural Gas Total | C40: 32 | D40: 12488000 | E40: 11802900 | F40: 11865200
B41: Grand Total | C41: 163 | D41: 31162600 | E41: 28457600 | F41: 28514500

Sheet Site Register
A1: Downer Energy Portfolio – Consolidated Site Register
A2: Connection ID | B2: Commodity | C2: Country | D2: State / Region | E2: Portfolio Group | F2: Site Name | G2: Address | H2: Entity | I2: Business Unit | J2: Units | K2: Annual Consumption | L2: Retailer at Tender | M2: Contracted Retailer | N2: New Contract Start | O2: New Contract End | P2: Term | Q2: FY26 Budget | R2: FY27 Budget | S2: FY28 Budget | T2: Budget Status | U2: Notes | V2: Envizi Account Number | W2: Envizi Account Style | X2: Envizi Data Type | Y2: Envizi Supplier | Z2: Envizi Location | AA2: Envizi Location Ref | AB2: Account Status | AC2: Match Basis | AD2: Other Envizi accounts on this ID | AE2: Certificate / virtual meter account
A3: 5265773931 | B3: Natural Gas | C3: Australia | D3: ACT | E3: AU Large Natural Gas | G3: 7 Tralee Street, Hume ACT 2620 | H3: DOWNER EDI WORKS PTY LTD (ABN: 66 008 709 608) | I3: T&I | J3: GJ | K3: 30729.026 | L3: Origin | M3: Origin | N3: 46388 | O3: 47483 | P3: 36 months | Q3: {=IFERROR(ROUNDUP(_xlfn.XLOOKUP(A3,'Budget FY26-28'!A:A,'Budget FY26-28'!M:O)*(1+Summary!$C$2), -2), "")} | R3: 982100 | S3: 975800 | T3: Ready | V3: 50002801028_5265773931 | W3: Natural Gas - PDF Parsing | X3: Natural Gas [GJ] | Y3: Origin | Z3: Asphalt Prod - Hume (101) | AA3: 101 | AB3: Active | AC3: Connection ID is the account number suffix | AD3: 1963107867_5265773931; 50000353781_5265773931 | AE3: LGCS_7001184714 (at this location, different ID) - historical
A4: 5242077399 | B4: Natural Gas | C4: Australia | D4: NSW | E4: AU Large Natural Gas | G4: ICC Darling Drive, Darling Harbour NSW 2000 | H4: SPOTLESS FACILITY SERVICES PTY LTD (ABN: 83 072 293 880) | I4: SICS | J4: GJ | K4: 19847.411 | L4: ShellEnergyAU | M4: Shell | N4: 46023 | O4: 46752 | P4: 12 months | Q4: {=IFERROR(ROUNDUP(_xlfn.XLOOKUP(A4,'Budget FY26-28'!A:A,'Budget FY26-28'!M:O)*(1+Summary!$C$2), -2), "")} | R4: 580400 | S4: 589800 | T4: Ready | V4: 2100433_5242077399 | W4: Natural Gas - PDF Parsing | X4: Natural Gas [GJ] | Y4: ShellEnergyAU | Z4: PPP - SICEEP | AA4: 9077 | AB4: Active | AC4: Connection ID is the account number suffix | AD4: 50000102373_5242077399 | AE4: LGCS_4103927804 (at this location, different ID) - historical · LGCS_4103927806 (at this location, different ID) - historical · LGCS_4103927808 (at this location, different ID) - historical · LGCS_4103927809 (at this location, different ID) - historical
A5: 5247064745 | B5: Natural Gas | C5: Australia | D5: NSW | E5: AU Large Natural Gas | G5: 460 Main Road, Glendale NSW 2285 | H5: DOWNER EDI RAIL PTY LTD (ABN: 92 000 002 031) | I5: RAIL | J5: GJ | K5: 2500 | L5: Origin | M5: Origin | N5: 46388 | O5: 47483 | P5: 36 months | Q5: {=IFERROR(ROUNDUP(_xlfn.XLOOKUP(A5,'Budget FY26-28'!A:A,'Budget FY26-28'!M:O)*(1+Summary!$C$2), -2), "")} | R5: 64000 | S5: 65700 | T5: Ready | V5: 50002958793_5247064745 | W5: Natural Gas - PDF Parsing | X5: Natural Gas [GJ] | Y5: Origin | Z5: Cardiff - Rail | AA5: 3004 | AB5: Active | AC5: Connection ID is the account number suffix | AD5: 51632065_5247064745; Tenant 51632065_5247064745; 1109120_5247064745; Tenant 1109120_5247064745; 7733066771_5247064745; 9248380435_5247064745; Tenant 7733066771_5247064745; Tenant 9248380435_5247064745; A-DF77364D_5247064745; Tenant A-DF77364D_5247064745; Tenant Apportionment 50002958793_5247064745
A6: 5248353654 | B6: Natural Gas | C6: Australia | D6: NSW | E6: AU Large Natural Gas | G6: 9 Devon St, Rosehill NSW 2142 | H6: DOWNER EDI SERVICES PTY LTD (ABN: 71 137 732 042) | I6: T&I | J6: GJ | K6: 108015.37 | L6: ShellEnergyAU | M6: Shell | N6: 46023 | O6: 46752 | P6: 12 months | Q6: {=IFERROR(ROUNDUP(_xlfn.XLOOKUP(A6,'Budget FY26-28'!A:A,'Budget FY26-28'!M:O)*(1+Summary!$C$2), -2), "")} | R6: 2465100 | S6: 2532500 | T6: Ready | V6: 2100432_5248353654 | W6: Natural Gas - PDF Parsing | X6: Natural Gas [GJ] | Y6: ShellEnergyAU | Z6: Asphalt Prod - Rosehill (163) | AA6: 163 | AB6: Active | AC6: Connection ID is the account number suffix | AD6: 50002719045_5248353654 | AE6: LGCS_4311396021 (at this location, different ID) - historical · LGCS_4311396022 (at this location, different ID) - historical
A7: 5265761108 | B7: Natural Gas | C7: Australia | D7: NSW | E7: AU Large Natural Gas | G7: 5800 Kings Highway, Bungendore NSW 2621 | H7: SPOTLESS FACILITY SERVICES PTY LTD (ABN: 83 072 293 880) | I7: SICS | J7: GJ | K7: 1300 | L7: Origin | M7: Origin | N7: 46388 | O7: 46752 | P7: 12 months | Q7: {=IFERROR(ROUNDUP(_xlfn.XLOOKUP(A7,'Budget FY26-28'!A:A,'Budget FY26-28'!M:O)*(1+Summary!$C$2), -2), "")} | R7: 63500 | S7: 0 | T7: Ready | V7: 50002959329_5265761108 | W7: Natural Gas - PDF Parsing | X7: Natural Gas [GJ] | Y7: Origin | Z7: PPP - HQJOC (ACT) | AA7: 9092 | AB7: Active | AC7: Connection ID is the account number suffix | AD7: 701221629213_5265761108; A-D62CBEED_5265761108
A8: 5510072233 | B8: Natural Gas | C8: Australia | D8: SA | E8: AU Large Natural Gas | G8: 557 Grand Junction Road, Wingfield SA 5013 | H8: DOWNER EDI SERVICES PTY LTD (ABN: 71 137 732 042) | I8: T&I | J8: GJ | K8: 92565.36 | L8: ShellEnergyAU | M8: Shell | N8: 46023 | O8: 46752 | P8: 12 months | Q8: {=IFERROR(ROUNDUP(_xlfn.XLOOKUP(A8,'Budget FY26-28'!A:A,'Budget FY26-28'!M:O)*(1+Summary!$C$2), -2), "")} | R8: 2403600 | S8: 2449300 | T8: Ready | V8: 2100431_5510072233 | W8: Natural Gas - PDF Parsing | X8: Natural Gas [GJ] | Y8: ShellEnergyAU | Z8: Asphalt Prod - Wingfield (523) | AA8: 523 | AB8: Active | AC8: Connection ID is the account number suffix | AD8: 15005551610_5510072233 | AE8: LGCS_2002254877 (at this location, different ID) - historical
A9: 5510485000 | B9: Natural Gas | C9: Australia | D9: SA | E9: AU Large Natural Gas | G9: Wills Street, Largs Bay SA 5016 | H9: DOWNER EDI SERVICES PTY LTD (ABN: 71 137 732 042) | I9: T&I | J9: GJ | K9: 13214.104 | L9: ShellEnergyAU | M9: Shell | N9: 46023 | O9: 46752 | P9: 12 months | Q9: {=IFERROR(ROUNDUP(_xlfn.XLOOKUP(A9,'Budget FY26-28'!A:A,'Budget FY26-28'!M:O)*(1+Summary!$C$2), -2), "")} | R9: 346700 | S9: 348300 | T9: Ready | V9: 2100430_5510485000 | W9: Natural Gas - PDF Parsing | X9: Natural Gas [GJ] | Y9: ShellEnergyAU | Z9: Largs Bay | AA9: 163 | AB9: Active | AC9: Connection ID is the account number suffix | AD9: 15000948910_5510485000 | AE9: LGCS_SAAAAAB023 (at this location, different ID) - historical · LGCS_SAAAAAC481 (at this location, different ID) - historical
A10: 5762711908 | B10: Natural Gas | C10: Australia | D10: TAS | E10: AU Large Natural Gas | G10: 59 Remount Road, Mowbray TAS 7248 | H10: DOWNER EDI WORKS PTY LTD (ABN: 66 008 709 608) | I10: T&I | J10: GJ | K10: 15621.564 | L10: Solstice | M10: Solstice Energy | N10: 45658 | O10: 46387 | P10: Existing term to 31-Dec-2026 | Q10: {=IFERROR(ROUNDUP(_xlfn.XLOOKUP(A10,'Budget FY26-28'!A:A,'Budget FY26-28'!M:O)*(1+Summary!$C$2), -2), "")} | R10: 283000 | S10: 283000 | T10: FY26 secured | U10: No further term secured | V10: 2000120410_5762711908 | W10: Natural Gas - PDF Parsing | X10: Natural Gas [GJ] | Y10: SolsticeEnergy | Z10: Asphalt Prod - Mowbray (360) | AA10: 360 | AB10: Active | AC10: Connection ID is the account number suffix
A11: 5310000243 | B11: Natural Gas | C11: Australia | D11: VIC | E11: AU Large Natural Gas | G11: 18 Jersey Road, Bayswater VIC 3153 | H11: DOWNER EDI SERVICES PTY LTD (ABN: 71 137 732 042) | I11: T&I | J11: GJ | K11: 57783.717 | L11: ShellEnergyAU | M11: Shell | N11: 46023 | O11: 46752 | P11: 12 months | Q11: {=IFERROR(ROUNDUP(_xlfn.XLOOKUP(A11,'Budget FY26-28'!A:A,'Budget FY26-28'!M:O)*(1+Summary!$C$2), -2), "")} | R11: 1132200 | S11: 1134900 | T11: Ready | V11: 2100427_5310000243 | W11: Natural Gas - PDF Parsing | X11: Natural Gas [GJ] | Y11: ShellEnergyAU | Z11: Asphalt Prod - Bayswater (302) | AA11: 302 | AB11: Active | AC11: Connection ID is the account number suffix | AD11: 15000096411_5310000243 | AE11: LGCS_6305920528 (at this location, different ID) - historical
A12: 5320000943 | B12: Natural Gas | C12: Australia | D12: VIC | E12: AU Large Natural Gas | G12: Apollo Drive, Shepparton VIC 3630 | H12: DOWNER EDI SERVICES PTY LTD (ABN: 71 137 732 042) | I12: T&I | J12: GJ | K12: 23114.486 | L12: ShellEnergyAU | M12: Shell | N12: 46023 | O12: 46752 | P12: 12 months | Q12: {=IFERROR(ROUNDUP(_xlfn.XLOOKUP(A12,'Budget FY26-28'!A:A,'Budget FY26-28'!M:O)*(1+Summary!$C$2), -2), "")} | R12: 481500 | S12: 483200 | T12: Ready | V12: 2100428_5320000943 | W12: Natural Gas - PDF Parsing | X12: Natural Gas [GJ] | Y12: ShellEnergyAU | Z12: Asphalt Prod - Shepparton (308) | AA12: 308 | AB12: Active | AC12: Connection ID is the account number suffix | AD12: 15000093211_5320000943 | AE12: LGCS_VCCCSC0020 (at this location, different ID) - historical
A13: 5330662312 | B13: Natural Gas | C13: Australia | D13: VIC | E13: AU Large Natural Gas | G13: 125 Somerton Road, Somerton VIC 3062 | H13: DOWNER EDI SERVICES PTY LTD (ABN: 71 137 732 042) | I13: T&I | J13: GJ | K13: 103871.24 | L13: ShellEnergyAU | M13: Shell | N13: 46023 | O13: 46752 | P13: 12 months | Q13: {=IFERROR(ROUNDUP(_xlfn.XLOOKUP(A13,'Budget FY26-28'!A:A,'Budget FY26-28'!M:O)*(1+Summary!$C$2), -2), "")} | R13: 1939400 | S13: 1941300 | T13: Ready | V13: 2100429_5330662312 | W13: Natural Gas - PDF Parsing | X13: Natural Gas [GJ] | Y13: ShellEnergyAU | Z13: Asphalt Prod - Somerton (303) | AA13: L9.J.17032627 | AB13: Active | AC13: Connection ID is the account number suffix | AD13: 15005712110_5330662312 | AE13: LGCS_6001311036 (at this location, different ID) - historical
A14: 5600405263 | B14: Natural Gas | C14: Australia | D14: WA | E14: AU Large Natural Gas | G14: 73 Bickley Road, Beckenham WA 6107 | H14: DOWNER EDI SERVICES PTY LTD (ABN: 71 137 732 042) | I14: T&I | J14: GJ | K14: 590 | L14: Perth Energy | M14: Kleenheat | N14: 46023 | O14: 46752 | P14: To 31-Dec-2027 | Q14: {=IFERROR(ROUNDUP(_xlfn.XLOOKUP(A14,'Budget FY26-28'!A:A,'Budget FY26-28'!M:O)*(1+Summary!$C$2), -2), "")} | R14: 12000 | S14: 12000 | T14: Ready | V14: 3228711_5600405263 | W14: Natural Gas - PDF Parsing | X14: Natural Gas [GJ] | Y14: Kleenheat | Z14: Cannington Emulsion Plant | AA14: 39 | AB14: Active | AC14: Connection ID is the account number suffix | AD14: 129001507_5600405263; 805045016_5600405263; 3176624_5600405263; 605461_5600405263; 608258_5600405263
A15: 5600436929 | B15: Natural Gas | C15: Australia | D15: WA | E15: AU Large Natural Gas | G15: 95 Cockram Road, Martin WA 6110 | H15: DOWNER EDI SERVICES PTY LTD (ABN: 71 137 732 042) | I15: T&I | J15: GJ | K15: 23242.137 | L15: Perth Energy | M15: Kleenheat | N15: 46023 | O15: 46752 | P15: To 31-Dec-2027 | Q15: {=IFERROR(ROUNDUP(_xlfn.XLOOKUP(A15,'Budget FY26-28'!A:A,'Budget FY26-28'!M:O)*(1+Summary!$C$2), -2), "")} | R15: 326700 | S15: 326700 | T15: Ready | V15: 3176624_5600436929 | W15: Natural Gas - PDF Parsing | X15: Natural Gas [GJ] | Y15: Kleenheat | Z15: Asphalt Prod - Gosnells (621) | AA15: 621 | AB15: Active | AC15: Connection ID is the account number suffix | AD15: 11804846_5600436929; 80005968_5600436929; 606714_5600436929
A16: 5600604830 | B16: Natural Gas | C16: Australia | D16: WA | E16: AU Large Natural Gas | G16: Unit 1, 5 Mounts Bay Road, Perth WA 6000 | H16: SPOTLESS FACILITY SERVICES PTY LTD (ABN: 83 072 293 880) | I16: SICS | J16: GJ | K16: 9471.6073 | L16: Perth Energy | M16: Kleenheat | N16: 46023 | O16: 46752 | P16: To 31-Dec-2027 | Q16: {=IFERROR(ROUNDUP(_xlfn.XLOOKUP(A16,'Budget FY26-28'!A:A,'Budget FY26-28'!M:O)*(1+Summary!$C$2), -2), "")} | R16: 156500 | S16: 156500 | T16: Ready | V16: 3176620_5600604830 | W16: Natural Gas - PDF Parsing | X16: Natural Gas [GJ] | Y16: Kleenheat | Z16: LSE - Perth Convention & Exhibition Centre (WA) | AA16: 9068 | AB16: Active | AC16: Connection ID is the account number suffix | AD16: 11804879_5600604830; 80012725_5600604830; 606716_5600604830
A17: 5600945901 | B17: Natural Gas | C17: Australia | D17: WA | E17: AU Large Natural Gas | G17: Lot 106 Corner Hoyle & Conway Road, Hope Valley WA 6165 | H17: DOWNER EDI SERVICES PTY LTD (ABN: 71 137 732 042) | I17: T&I | J17: GJ | K17: 34066.928 | L17: Perth Energy | M17: Kleenheat | N17: 46023 | O17: 46752 | P17: To 31-Dec-2027 | Q17: {=IFERROR(ROUNDUP(_xlfn.XLOOKUP(A17,'Budget FY26-28'!A:A,'Budget FY26-28'!M:O)*(1+Summary!$C$2), -2), "")} | R17: 464000 | S17: 464000 | T17: Ready | V17: 3228713_5600945901 | W17: Natural Gas - PDF Parsing | X17: Natural Gas [GJ] | Y17: Kleenheat | Z17: Asphalt Prod - Hope Valley (628) | AA17: 628 | AB17: Active | AC17: Connection ID is the account number suffix | AD17: 11804853_5600945901; 80010413_5600945901; 3176624_5600945901; 606715_5600945901
A18: 3053253239 | B18: Electricity | C18: Australia | D18: QLD | E18: AU Large Electricity | F18: Torbanlea | G18: TRAIN FACILTY BRUCE HWY TORBANLEA 35 QLD 4662 | H18: DOWNER EDI SERVICES PTY LTD (ABN: 71 137 732 042) | I18: RAIL | J18: kWh | K18: 6208798 | L18: CS Energy | M18: Engie | N18: 46204 | O18: 46934 | P18: 24 months | Q18: {=IFERROR(ROUNDUP(_xlfn.XLOOKUP(A18,'Budget FY26-28'!A:A,'Budget FY26-28'!M:O)*(1+Summary!$C$2), -2), "")} | R18: 1165400 | S18: 1174900 | T18: Ready | V18: 900018201_3053253239 | W18: Electricity Small Market | X18: Electricity [kWh] | Y18: EngieAU | Z18: Torbanlea - QTMP | AB18: Active | AC18: Connection ID is the account number suffix | AD18: 1003571_3053253239; 5000021_3053253239 | AE18: 900018201_3053253239_CERTS (to create)
A19: 6305885252 | B19: Electricity | C19: Australia | D19: VIC | E19: AU Large Electricity | G19: 81 MCMILLAN STREET LUCKNOW VIC 3875 LUCKNOW VIC | H19: DOWNER EDI SERVICES PTY LTD (ABN: 71 137 732 042) | J19: kWh | K19: 201844 | L19: Origin | M19: Engie | N19: 46204 | O19: 46934 | P19: 24 months | Q19: {=IFERROR(ROUNDUP(_xlfn.XLOOKUP(A19,'Budget FY26-28'!A:A,'Budget FY26-28'!M:O)*(1+Summary!$C$2), -2), "")} | R19: 57800 | S19: 58100 | T19: Ready | V19: 900018218_6305885252 | W19: Electricity Small Market | X19: Electricity [kWh] | Y19: EngieAU | Z19: Gippsland Asphalt - Bairnsdale | AA19: 103.1 | AB19: Active | AC19: Connection ID is the account number suffix | AD19: 900018218_6305885252_CERTS; 50002976775_6305885252 | AE19: 900018218_6305885252_CERTS (live)
A20: 4001050448 | B20: Electricity | C20: Australia | D20: NSW | E20: AU Small Energy | F20: Roads - Forbes | G20: SAM STREET FORBES NSW 2871 | H20: DOWNER EDI WORKS PTY LTD (ABN: 66 008 709 608) | I20: ROAD SERVICES | J20: kWh | K20: 28354 | L20: Origin | M20: Origin | N20: 46204 | O20: 46934 | P20: 24 months | Q20: {=IFERROR(ROUNDUP(_xlfn.XLOOKUP(A20,'Budget FY26-28'!A:A,'Budget FY26-28'!M:O)*(1+Summary!$C$2), -2), "")} | R20: 9400 | S20: 9400 | T20: Ready | V20: A-5F3C0784_4001050448 | W20: Electricity Small Market | X20: Electricity [kWh] | Y20: Origin | Z20: Forbes | AA20: 116 | AB20: Active | AC20: Connection ID is the account number suffix | AD20: 200021563685_4001050448
A21: 4001128707 | B21: Electricity | C21: Australia | D21: NSW | E21: AU Small Energy | F21: Roads - Westdale (Tamworth) | G21: 15 ARMSTRONG STREET WESTDALE NSW 2340 | H21: DOWNER EDI WORKS PTY LTD (ABN: 66 008 709 608) | I21: ROAD SERVICES | J21: kWh | K21: 0 | L21: Origin | M21: Origin | N21: 46204 | O21: 46934 | P21: 24 months | Q21: {=IFERROR(ROUNDUP(_xlfn.XLOOKUP(A21,'Budget FY26-28'!A:A,'Budget FY26-28'!M:O)*(1+Summary!$C$2), -2), "")} | R21: 0 | S21: 0 | T21: Review required | U21: No consumption reported | V21: A-2A4343BB_4001128707 | W21: Electricity Small Market | X21: Electricity [kWh] | Y21: Origin | Z21: Tamworth | AA21: 170937 | AB21: Active | AC21: Connection ID is the account number suffix | AD21: 200021563628_4001128707 | AE21: LGCS_4001158058 (at this location, different ID) - historical
A22: 4001174306 | B22: Electricity | C22: Australia | D22: NSW | E22: AU Small Energy | F22: Roads - Westdale (Tamworth) | G22: 23 ARMSTRONG STREET WESTDALE NSW 2340 | H22: DOWNER EDI WORKS PTY LTD (ABN: 66 008 709 608) | I22: ROAD SERVICES | J22: kWh | K22: 254401 | L22: Origin | M22: Origin | N22: 46204 | O22: 46934 | P22: 24 months | Q22: {=IFERROR(ROUNDUP(_xlfn.XLOOKUP(A22,'Budget FY26-28'!A:A,'Budget FY26-28'!M:O)*(1+Summary!$C$2), -2), "")} | R22: 74700 | S22: 74700 | T22: Ready | V22: A-0B2330E0_4001174306 | W22: Electricity Small Market | X22: Electricity [kWh] | Y22: Origin | Z22: Tamworth | AA22: 170937 | AB22: Active | AC22: Connection ID is the account number suffix | AE22: LGCS_4001158058 (at this location, different ID) - historical
A23: 4001231357 | B23: Electricity | C23: Australia | D23: NSW | E23: AU Small Energy | F23: Surfacing Lismore | G23: 64 Lancaster Drive Goonellabah NSW 2480 | H23: DOWNER EDI WORKS PTY LTD (ABN: 66 008 709 608) | I23: Roads | J23: kWh | K23: 30776 | L23: Origin | M23: Origin | N23: 46204 | O23: 46934 | P23: 24 months | Q23: {=IFERROR(ROUNDUP(_xlfn.XLOOKUP(A23,'Budget FY26-28'!A:A,'Budget FY26-28'!M:O)*(1+Summary!$C$2), -2), "")} | R23: 13200 | S23: 13200 | T23: Ready | V23: A-12B8B627_4001231357 | W23: Electricity Small Market | X23: Electricity [kWh] | Y23: Origin | Z23: RPQ NSW Lismore Depot | AA23: 170426 | AB23: Active | AC23: Connection ID is the account number suffix
A24: 4001277522 | B24: Electricity | C24: Australia | D24: NSW | E24: AU Small Energy | F24: RPQ South Grafton | G24: Lot 42 Tyson St, , South Grafton NSW 2460 | H24: RPQ PTY LTD (ABN: 53 010 760 826) | I24: RPQ | J24: kWh | K24: 9299 | L24: Origin | M24: Origin | N24: 46204 | O24: 46934 | P24: 24 months | Q24: {=IFERROR(ROUNDUP(_xlfn.XLOOKUP(A24,'Budget FY26-28'!A:A,'Budget FY26-28'!M:O)*(1+Summary!$C$2), -2), "")} | R24: 3800 | S24: 3800 | T24: Ready | V24: A-480CA3BE_4001277522 | W24: Electricity Small Market | X24: Electricity [kWh] | Y24: Origin | Z24: RPQ NSW South Grafton | AA24: L9.J.171215 | AB24: Active | AC24: Connection ID is the account number suffix | AD24: A-B500CC5F_4001277522
A25: 4103512903 | B25: Electricity | C25: Australia | D25: NSW | E25: AU Small Energy | F25: Rail Hornsby | G25: 29 Leighton Place Hornsby NSW 2077 | H25: DOWNER EDI RAIL PTY LTD (ABN: 92 000 002 031) | I25: Rail | J25: kWh | K25: 15039 | L25: AGL | M25: Origin | N25: 46204 | O25: 46934 | P25: 24 months | Q25: {=IFERROR(ROUNDUP(_xlfn.XLOOKUP(A25,'Budget FY26-28'!A:A,'Budget FY26-28'!M:O)*(1+Summary!$C$2), -2), "")} | R25: 4100 | S25: 4100 | T25: Ready | V25: 7093364037_4103512903 | W25: Electricity Small Market | X25: Electricity [kWh] | Y25: AGL | Z25: WTP Mobile Tech Hornsby | AA25: 3025 | AB25: Active | AC25: Connection ID is the account number suffix
A26: 4104037195 | B26: Electricity | C26: Australia | D26: NSW | E26: AU Small Energy | F26: Whole of Government -Riverwood | G26: 5-7 Littleton St Riverwood NSW 2190 | H26: SPOTLESS FACILITY SERVICES PTY LTD (ABN: 83 072 293 880) | I26: Spotless | J26: kWh | K26: 2938 | L26: Origin | M26: Origin | N26: 46204 | O26: 46934 | P26: 24 months | Q26: {=IFERROR(ROUNDUP(_xlfn.XLOOKUP(A26,'Budget FY26-28'!A:A,'Budget FY26-28'!M:O)*(1+Summary!$C$2), -2), "")} | R26: 1500 | S26: 1500 | T26: Ready | V26: A-EE80EEC5_4104037195 | W26: Electricity Small Market | X26: Electricity [kWh] | Y26: Origin | Z26: Spotless FM - Riverwood office | AB26: Active | AC26: Connection ID is the account number suffix | AD26: A-67BE8F15_4104037195
A27: 4204234430 | B27: Electricity | C27: Australia | D27: NSW | E27: AU Small Energy | F27: Roads - Narrandera | G27: 1 DRISCOLL DRIVE NARRANDERA NSW 2700 | H27: DOWNER EDI WORKS PTY LTD (ABN: 66 008 709 608) | I27: ROAD SERVICES | J27: kWh | K27: 16709 | L27: Origin | M27: Origin | N27: 46204 | O27: 46934 | P27: 24 months | Q27: {=IFERROR(ROUNDUP(_xlfn.XLOOKUP(A27,'Budget FY26-28'!A:A,'Budget FY26-28'!M:O)*(1+Summary!$C$2), -2), "")} | R27: 6600 | S27: 6600 | T27: Ready | V27: A-39C3EA08_4204234430 | W27: Electricity Small Market | X27: Electricity [kWh] | Y27: Origin | Z27: Asphalt Prod - Narrandera (113) | AA27: 113 | AB27: Active | AC27: Connection ID is the account number suffix | AD27: 5868854420_4204234430; 200021563602_4204234430
A28: 4310027807 | B28: Electricity | C28: Australia | D28: NSW | E28: AU Small Energy | F28: Skilltech - Rydalmere | G28: U S 16 SOUTH ST RYDALMERE NSW 2116 | H28: SKILLTECH CONSULTING SERVICES PTY. LTD. (ABN: 14 007 162 647) | I28: Spotless | J28: kWh | K28: 65379 | L28: EnergyAustralia | M28: Origin | N28: 46204 | O28: 46934 | P28: 24 months | Q28: {=IFERROR(ROUNDUP(_xlfn.XLOOKUP(A28,'Budget FY26-28'!A:A,'Budget FY26-28'!M:O)*(1+Summary!$C$2), -2), "")} | R28: 16800 | S28: 16800 | T28: Ready | V28: 4735468390_4310027807 | W28: Electricity Small Market | X28: Electricity [kWh] | Y28: EnergyAustralia | Z28: Skilltech - Rydalmere | AA28: L9.S.13000871 | AB28: Active | AC28: Connection ID is the account number suffix | AD28: 200012634040_4310027807
A29: 4311422527 | B29: Electricity | C29: Australia | D29: NSW | E29: AU Small Energy | F29: 5 Edney Lane | G29: Unit 1, 5 Edney Lane Spring Hill, NSW 2500 | H29: DOWNER EDI SERVICES PTY LTD (ABN: 71 137 732 042) | I29: Downer EDI Services Pty | J29: kWh | K29: 33060 | L29: Origin | M29: Origin | N29: 46204 | O29: 46934 | P29: 24 months | Q29: {=IFERROR(ROUNDUP(_xlfn.XLOOKUP(A29,'Budget FY26-28'!A:A,'Budget FY26-28'!M:O)*(1+Summary!$C$2), -2), "")} | R29: 8900 | S29: 8900 | T29: Ready | V29: A-1C180A27_4311422527 | W29: Electricity Small Market | X29: Electricity [kWh] | Y29: Origin | Z29: LAHC NSW - Springhill | AA29: L9.S.3174.45002371 | AB29: Active | AC29: Connection ID is the account number suffix
A30: 4407159044 | B30: Electricity | C30: Australia | D30: NSW | E30: AU Small Energy | F30: RPQ -Chinderah - NSW Spray Seal | G30: 24A Ozone St Chinderah NSW 2487 | H30: RPQ PTY LTD (ABN: 53 010 760 826) | I30: ROAD SERVICES | J30: kWh | K30: 33872 | L30: Origin | M30: Origin | N30: 46204 | O30: 46934 | P30: 24 months | Q30: {=IFERROR(ROUNDUP(_xlfn.XLOOKUP(A30,'Budget FY26-28'!A:A,'Budget FY26-28'!M:O)*(1+Summary!$C$2), -2), "")} | R30: 11000 | S30: 11000 | T30: Ready | V30: A-7098FD44_4407159044 | W30: Electricity Small Market | X30: Electricity [kWh] | Y30: Origin | Z30: RPQ NSW Chinderah | AA30: L9.J.171210 | AB30: Active | AC30: Connection ID is the account number suffix | AD30: 200051085393_4407159044; A-4005C5DE_4407159044 | AE30: LGCS_4407159054 (at this location, different ID) - historical
A31: 3038502933 | B31: Electricity | C31: Australia | D31: QLD | E31: AU Small Energy | F31: Engineering Power Gladstone | G31: 7 ROOKSBY ST GLADSTONE CENTRAL QLD 4680 | H31: DOWNER EDI ENGINEERING POWER PTY LTD (ABN: 53 000 983 700) | J31: kWh | K31: 38380 | L31: Ergon | M31: Origin | N31: 46204 | O31: 46934 | P31: 24 months | Q31: {=IFERROR(ROUNDUP(_xlfn.XLOOKUP(A31,'Budget FY26-28'!A:A,'Budget FY26-28'!M:O)*(1+Summary!$C$2), -2), "")} | R31: 11800 | S31: 11800 | T31: Ready | V31: A-18650A37_3038502933 | W31: Electricity Small Market | X31: Electricity [kWh] | Y31: Ergon | Z31: Rooksby St, Gladstone | AA31: ASV-363.376.302.420 | AB31: Active | AC31: Connection ID is the account number suffix | AD31: 43183239_3038502933
A32: 3039040879 | B32: Electricity | C32: Australia | D32: QLD | E32: AU Small Energy | F32: Engineering Power - Gladstone | G32: LOT 145 ROOKSBY ST GLADSTONE CENTRAL QLD 4680 | H32: DOWNER EDI ENGINEERING POWER PTY LTD (ABN: 53 000 983 700) | I32: ENGINEERING POWER | J32: kWh | K32: 70195 | L32: Ergon | M32: Origin | N32: 46204 | O32: 46934 | P32: 24 months | Q32: {=IFERROR(ROUNDUP(_xlfn.XLOOKUP(A32,'Budget FY26-28'!A:A,'Budget FY26-28'!M:O)*(1+Summary!$C$2), -2), "")} | R32: 20900 | S32: 20900 | T32: Ready | V32: A-3B52C8FB_3039040879 | W32: Electricity Small Market | X32: Electricity [kWh] | Y32: Ergon | Z32: Rooksby St, Gladstone | AA32: ASV-363.376.302.420 | AB32: Active | AC32: Connection ID is the account number suffix | AD32: 41144911_3039040879
A33: 3041781236 | B33: Electricity | C33: Australia | D33: QLD | E33: AU Small Energy | F33: Rail - Maryborough | G33: 3 Ellena Street MARYBOROUGH QLD 4650 | H33: DOWNER EDI RAIL PTY LTD (ABN: 92 000 002 031) | I33: ROLLING STOCK | J33: kWh | K33: 53331 | L33: Ergon | M33: Origin | N33: 46204 | O33: 46934 | P33: 24 months | Q33: {=IFERROR(ROUNDUP(_xlfn.XLOOKUP(A33,'Budget FY26-28'!A:A,'Budget FY26-28'!M:O)*(1+Summary!$C$2), -2), "")} | R33: 16100 | S33: 16100 | T33: Ready | V33: A-011B63B4_3041781236 | W33: Electricity Small Market | X33: Electricity [kWh] | Y33: Ergon | Z33: Maryborough | AA33: 3011 | AB33: Active | AC33: Connection ID is the account number suffix | AD33: 7101034937_3041781236; 7029136236_3041781236 | AE33: LGCS_QGGG000010 (at this location, different ID) - historical · LGCS_QGGG000320 (at this location, different ID) - historical
A34: QB07736452 | B34: Electricity | C34: Australia | D34: QLD | E34: AU Small Energy | F34: Utilities - Kunda Park | G34: 32 PAGE STREET KUNDA PARK QLD 4556 | H34: DOWNER EDI SERVICES PTY LTD (ABN: 71 137 732 042) | I34: Utilities | J34: kWh | K34: 24596 | L34: AGL | M34: Origin | N34: 46204 | O34: 46934 | P34: 24 months | Q34: {=IFERROR(ROUNDUP(_xlfn.XLOOKUP(A34,'Budget FY26-28'!A:A,'Budget FY26-28'!M:O)*(1+Summary!$C$2), -2), "")} | R34: 8100 | S34: 8100 | T34: Ready | V34: 7099513421_QB07736452 | W34: Electricity Small Market | X34: Electricity [kWh] | Y34: AGL | Z34: Kunda Park | AA34: 10920046 | AB34: Active | AC34: Connection ID is the account number suffix | AD34: 400030619011_QB07736452
A35: QB13869604 | B35: Electricity | C35: Australia | D35: QLD | E35: AU Small Energy | F35: UAM Office - Molendinar | G35: Unit 2, 24 Export Drive Molendinar QLD 4214 | H35: Utilities Asset Management Pty Ltd (ABN: TBC) | I35: SPOTLESS | J35: kWh | K35: 16289 | L35: AGL | M35: Origin | N35: 46204 | O35: 46934 | P35: 24 months | Q35: {=IFERROR(ROUNDUP(_xlfn.XLOOKUP(A35,'Budget FY26-28'!A:A,'Budget FY26-28'!M:O)*(1+Summary!$C$2), -2), "")} | R35: 4600 | S35: 4600 | T35: Ready | V35: 7101031974_QB13869604 | W35: Electricity Small Market | X35: Electricity [kWh] | Y35: AGL | Z35: AE Smith - Molendinar | AA35: 9126 | AB35: Active | AC35: Connection ID is the account number suffix | AD35: 7051765779_QB13869604
A36: 2001130961 | B36: Electricity | C36: Australia | D36: SA | E36: AU Small Energy | F36: Utilities - Gepps Cross | G36: 535 PROSPECT ROAD GEPPS CROSS SA 5094 | H36: DOWNER EDI SERVICES PTY LTD (ABN: 71 137 732 042) | I36: Utilities | J36: kWh | K36: 22458 | L36: AGL | M36: Origin | N36: 46204 | O36: 46934 | P36: 24 months | Q36: {=IFERROR(ROUNDUP(_xlfn.XLOOKUP(A36,'Budget FY26-28'!A:A,'Budget FY26-28'!M:O)*(1+Summary!$C$2), -2), "")} | R36: 9200 | S36: 9200 | T36: Ready | V36: 7099171253_2001130961 | W36: Electricity Small Market | X36: Electricity [kWh] | Y36: AGL | Z36: Gepps Cross | AB36: Active | AC36: Connection ID is the account number suffix | AD36: 8404807400_2001130961; 500012733985_2001130961; 500014182603_2001130961
A37: 2001160686 | B37: Electricity | C37: Australia | D37: SA | E37: AU Small Energy | F37: Roads Workshop Wingfield | G37: 553-557 GRAND JUNCTION ROAD WINGFIELD SA 5013 | H37: DOWNER EDI SERVICES PTY LTD (ABN: 71 137 732 042) | I37: ROAD SERVICES | J37: kWh | K37: 36782 | L37: AGL | M37: Origin | N37: 46204 | O37: 46934 | P37: 24 months | Q37: {=IFERROR(ROUNDUP(_xlfn.XLOOKUP(A37,'Budget FY26-28'!A:A,'Budget FY26-28'!M:O)*(1+Summary!$C$2), -2), "")} | R37: 14000 | S37: 14000 | T37: Ready | V37: 7099172129_2001160686 | W37: Electricity Small Market | X37: Electricity [kWh] | Y37: AGL | Z37: Asphalt Prod - Wingfield (523) | AA37: 523 | AB37: Active | AC37: Connection ID is the account number suffix | AD37: 500006951122_2001160686 | AE37: LGCS_2002254877 (at this location, different ID) - historical
A38: 2001223248 | B38: Electricity | C38: Australia | D38: SA | E38: AU Small Energy | F38: 326 Kidman Park, SA | G38: 326 GRANGE RD KIDMAN PARK SA | H38: DOWNER UTILITIES AUSTRALIA PTY LTD (ABN: 65 075 194 857) | I38: E&U | J38: kWh | K38: 5840 | L38: AGL | M38: Origin | N38: 46204 | O38: 46934 | P38: 24 months | Q38: {=IFERROR(ROUNDUP(_xlfn.XLOOKUP(A38,'Budget FY26-28'!A:A,'Budget FY26-28'!M:O)*(1+Summary!$C$2), -2), "")} | R38: 2900 | S38: 2900 | T38: Ready | V38: Not found | AC38: No Envizi account ends in this Connection ID
A39: 2001341166 | B39: Electricity | C39: Australia | D39: SA | E39: AU Small Energy | F39: DM Roads -Sturt Depot | G39: Lot 100 / 78 Sturt Rd Bedford Park SA 5042 | H39: DOWNER EDI WORKS PTY LTD (ABN: 66 008 709 608) | I39: ROAD SERVICES | J39: kWh | K39: 3902 | L39: AGL | M39: Origin | N39: 46204 | O39: 46934 | P39: 24 months | Q39: {=IFERROR(ROUNDUP(_xlfn.XLOOKUP(A39,'Budget FY26-28'!A:A,'Budget FY26-28'!M:O)*(1+Summary!$C$2), -2), "")} | R39: 2000 | S39: 2000 | T39: Ready | V39: 7099171261_2001341166 | W39: Electricity Small Market | X39: Electricity [kWh] | Y39: AGL | Z39: Sturt | AA39: 17021267 | AB39: Active | AC39: Connection ID is the account number suffix | AD39: 4304586748_2001341166; 500015155756_2001341166
A40: 2001341167 | B40: Electricity | C40: Australia | D40: SA | E40: AU Small Energy | F40: DM Roads- Sturt Depot | G40: 331 Sturt Rd Bedford Park SA 5042 | H40: DOWNER EDI WORKS PTY LTD (ABN: 66 008 709 608) | I40: ROAD SERVICES | J40: kWh | K40: 21166 | L40: AGL | M40: Origin | N40: 46204 | O40: 46934 | P40: 24 months | Q40: {=IFERROR(ROUNDUP(_xlfn.XLOOKUP(A40,'Budget FY26-28'!A:A,'Budget FY26-28'!M:O)*(1+Summary!$C$2), -2), "")} | R40: 8000 | S40: 8000 | T40: Ready | V40: 7099172137_2001341167 | W40: Electricity Small Market | X40: Electricity [kWh] | Y40: AGL | Z40: Sturt | AA40: 17021267 | AB40: Active | AC40: Connection ID is the account number suffix | AD40: 4938159759_2001341167; 5372802078_2001341167; 500016287640_2001341167
A41: 2001515449 | B41: Electricity | C41: Australia | D41: SA | E41: AU Small Energy | F41: Roads - Port Lincoln | G41: 9 DUBLIN STREET PORT LINCOLN SA 5606 | H41: DOWNER EDI WORKS PTY LTD (ABN: 66 008 709 608) | I41: ROAD SERVICES | J41: kWh | K41: 10660 | L41: AGL | M41: Origin | N41: 46204 | O41: 46934 | P41: 24 months | Q41: {=IFERROR(ROUNDUP(_xlfn.XLOOKUP(A41,'Budget FY26-28'!A:A,'Budget FY26-28'!M:O)*(1+Summary!$C$2), -2), "")} | R41: 4400 | S41: 4400 | T41: Ready | V41: 7099171741_2001515449 | W41: Electricity Small Market | X41: Electricity [kWh] | Y41: AGL | Z41: Port Lincoln | AA41: 17021037 | AB41: Active | AC41: Connection ID is the account number suffix | AD41: 500006757354_2001515449
A42: 2001600008 | B42: Electricity | C42: Australia | D42: SA | E42: AU Small Energy | F42: Roads - Ceduna | G42: 8 EYRE HIGHWAY CEDUNA SA 5690 | H42: DOWNER EDI WORKS PTY LTD (ABN: 66 008 709 608) | I42: ROAD SERVICES | J42: kWh | K42: 3495 | L42: AGL | M42: Origin | N42: 46204 | O42: 46934 | P42: 24 months | Q42: {=IFERROR(ROUNDUP(_xlfn.XLOOKUP(A42,'Budget FY26-28'!A:A,'Budget FY26-28'!M:O)*(1+Summary!$C$2), -2), "")} | R42: 1800 | S42: 1800 | T42: Ready | V42: 7099171733_2001600008 | W42: Electricity Small Market | X42: Electricity [kWh] | Y42: AGL | Z42: Ceduna | AB42: Active | AC42: Connection ID is the account number suffix | AD42: LGCS_2001600008; 1679016133_2001600008; 500012057260_2001600008 | AE42: LGCS_2001600008 - historical
A43: 2001676115 | B43: Electricity | C43: Australia | D43: SA | E43: AU Small Energy | F43: Roads - Port Pirie | G43: 5 COPINGER ROAD SOLOMONTOWN SA 5540 | H43: DOWNER EDI WORKS PTY LTD (ABN: 66 008 709 608) | I43: ROAD SERVICES | J43: kWh | K43: 28791 | L43: AGL | M43: Origin | N43: 46204 | O43: 46934 | P43: 24 months | Q43: {=IFERROR(ROUNDUP(_xlfn.XLOOKUP(A43,'Budget FY26-28'!A:A,'Budget FY26-28'!M:O)*(1+Summary!$C$2), -2), "")} | R43: 10800 | S43: 10800 | T43: Ready | V43: 7099169596_2001676115 | W43: Electricity Small Market | X43: Electricity [kWh] | Y43: AGL | Z43: Port Pirie | AA43: 235 | AB43: Active | AC43: Connection ID is the account number suffix | AD43: 5479471765_2001676115; 500006757396_2001676115
A44: 2002190876 | B44: Electricity | C44: Australia | D44: SA | E44: AU Small Energy | F44: Roads - Port Augusta | G44: VICTORIA PARADE PORT AUGUSTA SA 5700 | H44: DOWNER EDI WORKS PTY LTD (ABN: 66 008 709 608) | I44: ROAD SERVICES | J44: kWh | K44: 29818 | L44: AGL | M44: Origin | N44: 46204 | O44: 46934 | P44: 24 months | Q44: {=IFERROR(ROUNDUP(_xlfn.XLOOKUP(A44,'Budget FY26-28'!A:A,'Budget FY26-28'!M:O)*(1+Summary!$C$2), -2), "")} | R44: 11100 | S44: 11100 | T44: Ready | V44: 7099171246_2002190876 | W44: Electricity Small Market | X44: Electricity [kWh] | Y44: AGL | Z44: Port Augusta-Works | AA44: 230 | AB44: Active | AC44: Connection ID is the account number suffix | AD44: 8359881814_2002190876; 500006757347_2002190876
A45: 2002601115 | B45: Electricity | C45: Australia | D45: SA | E45: AU Small Energy | F45: North South Corridor Site Office - SA | G45: BTS 21 SIR DONALD BRADMAN DR MILE END SOUTH SA | H45: DOWNER EDI WORKS PTY LTD (ABN: 66 008 709 608) | I45: 24170357 | J45: kWh | K45: 4380 | L45: AGL | M45: Origin | N45: 46204 | O45: 46934 | P45: 24 months | Q45: {=IFERROR(ROUNDUP(_xlfn.XLOOKUP(A45,'Budget FY26-28'!A:A,'Budget FY26-28'!M:O)*(1+Summary!$C$2), -2), "")} | R45: 2300 | S45: 2300 | T45: Ready | V45: Not found | AC45: No Envizi account ends in this Connection ID
A46: 6001295311 | B46: Electricity | C46: Australia | D46: VIC | E46: AU Small Energy | F46: Water Pipelines - Campbellfield | G46: 41 FORDSON ROAD CAMPBELLFIELD VIC 3061 | H46: DOWNER EDI WORKS PTY LTD (ABN: 66 008 709 608) | I46: ROAD SERVICES | J46: kWh | K46: 22391 | L46: AGL | M46: Origin | N46: 46204 | O46: 46934 | P46: 24 months | Q46: {=IFERROR(ROUNDUP(_xlfn.XLOOKUP(A46,'Budget FY26-28'!A:A,'Budget FY26-28'!M:O)*(1+Summary!$C$2), -2), "")} | R46: 5500 | S46: 5500 | T46: Ready | V46: 7099172855_6001295311 | W46: Electricity Small Market | X46: Electricity [kWh] | Y46: AGL | Z46: GWW - Campbellfield Depot | AB46: Active | AC46: Connection ID is the account number suffix | AD46: 9956624348_6001295311; 300022519718_6001295311
A47: 6001399332 | B47: Electricity | C47: Australia | D47: VIC | E47: AU Small Energy | F47: Spotless - Melb Street sweeping | G47: FY 2 41-45 HOBSONS RD KENSINGTON KENSINGTON VIC 3031 | H47: SPOTLESS FACILITY SERVICES PTY LTD (ABN: 83 072 293 880) | I47: SPOTLESS | J47: kWh | K47: 58945 | L47: AGL | M47: Origin | N47: 46204 | O47: 46934 | P47: 24 months | Q47: {=IFERROR(ROUNDUP(_xlfn.XLOOKUP(A47,'Budget FY26-28'!A:A,'Budget FY26-28'!M:O)*(1+Summary!$C$2), -2), "")} | R47: 14300 | S47: 14300 | T47: Ready | V47: 7099172947_6001399332 | W47: Electricity Small Market | X47: Electricity [kWh] | Y47: AGL | Z47: Kensington - Hobsons Rd | AA47: 9045 | AB47: Active | AC47: Connection ID is the account number suffix | AD47: 3791453447_6001399332; 300020368936_6001399332
A48: 6103034554 | B48: Electricity | C48: Australia | D48: VIC | E48: AU Small Energy | F48: Corporate - 567 Collins St | G48: 567 COLLINS STREET MELBOURNE VIC 3000 | H48: DOWNER EDI SERVICES PTY LTD (ABN: 71 137 732 042) | I48: CORPORATE | J48: kWh | K48: 30794 | L48: AGL | M48: Origin | N48: 46204 | O48: 46934 | P48: 24 months | Q48: {=IFERROR(ROUNDUP(_xlfn.XLOOKUP(A48,'Budget FY26-28'!A:A,'Budget FY26-28'!M:O)*(1+Summary!$C$2), -2), "")} | R48: 6800 | S48: 6800 | T48: Ready | V48: 7099171295_6103034554 | W48: Electricity Small Market | X48: Electricity [kWh] | Y48: AGL | Z48: 567 Collins St - Level 5 | AA48: 1014 | AB48: Active | AC48: Connection ID is the account number suffix | AD48: 5663254940_6103034554; 300032638565_6103034554
A49: 6103034564 | B49: Electricity | C49: Australia | D49: VIC | E49: AU Small Energy | F49: Corporate - 567 Collins St LEV 10 | G49: 567 COLLINS STREET MELBOURNE VIC 3000 | H49: DOWNER EDI SERVICES PTY LTD (ABN: 71 137 732 042) | I49: CORPORATE | J49: kWh | K49: 37745 | L49: AGL | M49: Origin | N49: 46204 | O49: 46934 | P49: 24 months | Q49: {=IFERROR(ROUNDUP(_xlfn.XLOOKUP(A49,'Budget FY26-28'!A:A,'Budget FY26-28'!M:O)*(1+Summary!$C$2), -2), "")} | R49: 8100 | S49: 8100 | T49: Ready | V49: 7099172145_6103034564 | W49: Electricity Small Market | X49: Electricity [kWh] | Y49: AGL | Z49: 567 Collins St - Level 10 | AA49: 1005 | AB49: Active | AC49: Connection ID is the account number suffix | AD49: 3797111232_6103034564; 300032527586_6103034564
A50: 6103034565 | B50: Electricity | C50: Australia | D50: VIC | E50: AU Small Energy | F50: Corporate - 567 Collins St LEV 10 | G50: 567 COLLINS STREET MELBOURNE VIC 3000 | H50: DOWNER EDI SERVICES PTY LTD (ABN: 71 137 732 042) | I50: CORPORATE | J50: kWh | K50: 56975 | L50: AGL | M50: Origin | N50: 46204 | O50: 46934 | P50: 24 months | Q50: {=IFERROR(ROUNDUP(_xlfn.XLOOKUP(A50,'Budget FY26-28'!A:A,'Budget FY26-28'!M:O)*(1+Summary!$C$2), -2), "")} | R50: 12000 | S50: 12000 | T50: Ready | V50: 7099173143_6103034565 | W50: Electricity Small Market | X50: Electricity [kWh] | Y50: AGL | Z50: 567 Collins St - Level 10 | AA50: 1005 | AB50: Active | AC50: Connection ID is the account number suffix | AD50: 1514766741_6103034565; 300032528477_6103034565
A51: 6103066712 | B51: Electricity | C51: Australia | D51: VIC | E51: AU Small Energy | F51: Spotless Abbotsford site Rehab | G51: 12 - 18 VICTORIA CRES ABBOTSFORD VIC 3067 | H51: SPOTLESS FACILITY SERVICES PTY LTD (ABN: 83 072 293 880) | I51: SPOTLESS | J51: kWh | K51: 376 | L51: AGL | M51: Origin | N51: 46204 | O51: 46934 | P51: 24 months | Q51: {=IFERROR(ROUNDUP(_xlfn.XLOOKUP(A51,'Budget FY26-28'!A:A,'Budget FY26-28'!M:O)*(1+Summary!$C$2), -2), "")} | R51: 700 | S51: 700 | T51: Ready | V51: 7099172186_6103066712 | W51: Electricity Small Market | X51: Electricity [kWh] | Y51: AGL | Z51: Remediation Site_Laundry - Abbotsford (VIC) | AA51: 9053 | AB51: Active | AC51: Connection ID is the account number suffix | AD51: 3582693223_6103066712; 300043704836_6103066712
A52: 6203155353 | B52: Electricity | C52: Australia | D52: VIC | E52: AU Small Energy | F52: Utilities - Geelong | G52: 31 Leather Street Geelong East VIC 3219 | H52: DOWNER UTILITIES AUSTRALIA PTY LTD (ABN: 65 075 194 857) | I52: Utilities | J52: kWh | K52: 27942 | L52: AGL | M52: Origin | N52: 46204 | O52: 46934 | P52: 24 months | Q52: {=IFERROR(ROUNDUP(_xlfn.XLOOKUP(A52,'Budget FY26-28'!A:A,'Budget FY26-28'!M:O)*(1+Summary!$C$2), -2), "")} | R52: 6800 | S52: 6800 | T52: Ready | V52: 7099173051_6203155353 | W52: Electricity Small Market | X52: Electricity [kWh] | Y52: AGL | Z52: Ausnet_Gas_Geelong East | AA52: AGGE | AB52: Active | AC52: Connection ID is the account number suffix | AD52: 7068967442_6203155353
A53: 6203245874 | B53: Electricity | C53: Australia | D53: VIC | E53: AU Small Energy | F53: Utilities - Wendouree | G53: 352 DOWLING STREET WENDOUREE VIC 3355 | H53: DOWNER UTILITIES AUSTRALIA PTY LTD (ABN: 65 075 194 857) | I53: Utilities | J53: kWh | K53: 11909 | L53: AGL | M53: Origin | N53: 46204 | O53: 46934 | P53: 24 months | Q53: {=IFERROR(ROUNDUP(_xlfn.XLOOKUP(A53,'Budget FY26-28'!A:A,'Budget FY26-28'!M:O)*(1+Summary!$C$2), -2), "")} | R53: 3200 | S53: 3200 | T53: Ready | V53: 7099172913_6203245874 | W53: Electricity Small Market | X53: Electricity [kWh] | Y53: AGL | Z53: Ausnet_Gas_Wendouree | AA53: AGWD | AB53: Active | AC53: Connection ID is the account number suffix | AD53: 1476119418_6203245874; 300001848187_6203245874
A54: 6203409239 | B54: Electricity | C54: Australia | D54: VIC | E54: AU Small Energy | F54: Roads Shepparton | G54: 12-28 Apollo Dve Shepparton VIC 3630 | H54: DOWNER EDI WORKS PTY LTD (ABN: 66 008 709 608) | I54: Roads | J54: kWh | K54: 3824 | L54: AGL | M54: Origin | N54: 46204 | O54: 46934 | P54: 24 months | Q54: {=IFERROR(ROUNDUP(_xlfn.XLOOKUP(A54,'Budget FY26-28'!A:A,'Budget FY26-28'!M:O)*(1+Summary!$C$2), -2), "")} | R54: 1500 | S54: 1500 | T54: Ready | V54: 7104945063_6203409239 | W54: Electricity Small Market | X54: Electricity [kWh] | Y54: AGL | Z54: Asphalt Prod - Shepparton (308) | AA54: 308 | AB54: Active | AC54: Connection ID is the account number suffix | AE54: LGCS_VCCCSC0020 (at this location, different ID) - historical
A55: 6203409240 | B55: Electricity | C55: Australia | D55: VIC | E55: AU Small Energy | F55: Roads Shepparton 3 | G55: 12-28 Apollo Dve Shepparton VIC 3630 | H55: DOWNER EDI WORKS PTY LTD (ABN: 66 008 709 608) | I55: Roads | J55: kWh | K55: 21695 | L55: AGL | M55: Origin | N55: 46204 | O55: 46934 | P55: 24 months | Q55: {=IFERROR(ROUNDUP(_xlfn.XLOOKUP(A55,'Budget FY26-28'!A:A,'Budget FY26-28'!M:O)*(1+Summary!$C$2), -2), "")} | R55: 5400 | S55: 5400 | T55: Ready | V55: 7103814690_6203409240 | W55: Electricity Small Market | X55: Electricity [kWh] | Y55: AGL | Z55: Asphalt Prod - Shepparton (308) | AA55: 308 | AB55: Active | AC55: Connection ID is the account number suffix | AE55: LGCS_VCCCSC0020 (at this location, different ID) - historical
A56: 6203424291 | B56: Electricity | C56: Australia | D56: VIC | E56: AU Small Energy | F56: Utilities - Bendigo | G56: 116-118 HOLMES ROAD NORTH BENDIGO VIC 3550 | H56: DOWNER UTILITIES AUSTRALIA PTY LTD (ABN: 65 075 194 857) | I56: Utilities | J56: kWh | K56: 5946 | L56: AGL | M56: Origin | N56: 46204 | O56: 46934 | P56: 24 months | Q56: {=IFERROR(ROUNDUP(_xlfn.XLOOKUP(A56,'Budget FY26-28'!A:A,'Budget FY26-28'!M:O)*(1+Summary!$C$2), -2), "")} | R56: 1900 | S56: 1900 | T56: Ready | V56: 7099172897_6203424291 | W56: Electricity Small Market | X56: Electricity [kWh] | Y56: AGL | Z56: Ausnet_Gas_North Bendigo | AA56: AGNB | AB56: Active | AC56: Connection ID is the account number suffix | AD56: 2443004782_6203424291; 300001232820_6203424291
A57: 6203424292 | B57: Electricity | C57: Australia | D57: VIC | E57: AU Small Energy | F57: Utilities - Bendigo | G57: 116-118 HOLMES ROAD NORTH BENDIGO VIC 3550 | H57: DOWNER UTILITIES AUSTRALIA PTY LTD (ABN: 65 075 194 857) | I57: Utilities | J57: kWh | K57: 8591 | L57: AGL | M57: Origin | N57: 46204 | O57: 46934 | P57: 24 months | Q57: {=IFERROR(ROUNDUP(_xlfn.XLOOKUP(A57,'Budget FY26-28'!A:A,'Budget FY26-28'!M:O)*(1+Summary!$C$2), -2), "")} | R57: 2500 | S57: 2500 | T57: Ready | V57: 7099173044_6203424292 | W57: Electricity Small Market | X57: Electricity [kWh] | Y57: AGL | Z57: Ausnet_Gas_North Bendigo | AA57: AGNB | AB57: Active | AC57: Connection ID is the account number suffix | AD57: 6270817761_6203424292; 300001232770_6203424292
A58: 6203606598 | B58: Electricity | C58: Australia | D58: VIC | E58: AU Small Energy | F58: Shepparton DM Roads Workshop | G58: 12-28 Apollo Drive Shepparton VIC 3630 | H58: DOWNER EDI WORKS PTY LTD (ABN: 66 008 709 608) | I58: Roads | J58: kWh | K58: 33744 | L58: AGL | M58: Origin | N58: 46204 | O58: 46934 | P58: 24 months | Q58: {=IFERROR(ROUNDUP(_xlfn.XLOOKUP(A58,'Budget FY26-28'!A:A,'Budget FY26-28'!M:O)*(1+Summary!$C$2), -2), "")} | R58: 8700 | S58: 8700 | T58: Ready | V58: 7103814674_6203606598 | W58: Electricity Small Market | X58: Electricity [kWh] | Y58: AGL | Z58: Asphalt Prod - Shepparton (308) | AA58: 308 | AB58: Active | AC58: Connection ID is the account number suffix | AE58: LGCS_VCCCSC0020 (at this location, different ID) - historical
A59: 6203613570 | B59: Electricity | C59: Australia | D59: VIC | E59: AU Small Energy | F59: Ausnet Gas Portland | G59: 102 Browning St Portland VIC 3305 | H59: DOWNER UTILITIES AUSTRALIA PTY LTD (ABN: 65 075 194 857) | I59: Utilities | J59: kWh | K59: 2010 | L59: Origin | M59: Origin | N59: 46204 | O59: 46934 | P59: 24 months | Q59: {=IFERROR(ROUNDUP(_xlfn.XLOOKUP(A59,'Budget FY26-28'!A:A,'Budget FY26-28'!M:O)*(1+Summary!$C$2), -2), "")} | R59: 1100 | S59: 1100 | T59: Ready | V59: A-4BD00928_6203613570 | W59: Electricity Small Market | X59: Electricity [kWh] | Y59: Origin | Z59: Ausnet_Gas_Portland - Browning | AA59: AGPLB | AB59: Active | AC59: Connection ID is the account number suffix
A60: 6203616394 | B60: Electricity | C60: Australia | D60: VIC | E60: AU Small Energy | F60: Utilities - Warrambool | G60: 13 DICKSON STREET WARRNAMBOOL VIC 3280 | H60: DOWNER UTILITIES AUSTRALIA PTY LTD (ABN: 65 075 194 857) | I60: Utilities | J60: kWh | K60: 4760 | L60: AGL | M60: Origin | N60: 46204 | O60: 46934 | P60: 24 months | Q60: {=IFERROR(ROUNDUP(_xlfn.XLOOKUP(A60,'Budget FY26-28'!A:A,'Budget FY26-28'!M:O)*(1+Summary!$C$2), -2), "")} | R60: 1700 | S60: 1700 | T60: Ready | V60: 7099172954_6203616394 | W60: Electricity Small Market | X60: Electricity [kWh] | Y60: AGL | Z60: Ausnet_Gas_Warrnambool | AA60: AGWB | AB60: Active | AC60: Connection ID is the account number suffix | AD60: 7510340718_6203616394; 300032541280_6203616394
A61: 6203723433 | B61: Electricity | C61: Australia | D61: VIC | E61: AU Small Energy | F61: Utilities - Colac | G61: 49 ROSSMOYNE ROAD COLAC WEST VIC 3250 | H61: DOWNER UTILITIES AUSTRALIA PTY LTD (ABN: 65 075 194 857) | I61: Utilities | J61: kWh | K61: 1966 | L61: AGL | M61: Origin | N61: 46204 | O61: 46934 | P61: 24 months | Q61: {=IFERROR(ROUNDUP(_xlfn.XLOOKUP(A61,'Budget FY26-28'!A:A,'Budget FY26-28'!M:O)*(1+Summary!$C$2), -2), "")} | R61: 1100 | S61: 1100 | T61: Ready | V61: 7099171279_6203723433 | W61: Electricity Small Market | X61: Electricity [kWh] | Y61: AGL | Z61: Ausnet_Gas_Colac West | AA61: AGCW | AB61: Active | AC61: Connection ID is the account number suffix | AD61: 300023859196_6203723433
A62: 6203834591 | B62: Electricity | C62: Australia | D62: VIC | E62: AU Small Energy | F62: DM Roads -Melton | G62: 90 High Street Melton VIC 3337 | H62: DOWNER EDI WORKS PTY LTD (ABN: 66 008 709 608) | I62: DM Roads | J62: kWh | K62: 14148 | L62: AGL | M62: Origin | N62: 46204 | O62: 46934 | P62: 24 months | Q62: {=IFERROR(ROUNDUP(_xlfn.XLOOKUP(A62,'Budget FY26-28'!A:A,'Budget FY26-28'!M:O)*(1+Summary!$C$2), -2), "")} | R62: 3900 | S62: 3900 | T62: Ready | V62: 7099510799_6203834591 | W62: Electricity Small Market | X62: Electricity [kWh] | Y62: AGL | Z62: City of Melton Roads and Drainage Asset Maintenanc | AA62: L9.J.170232 | AB62: Active | AC62: Connection ID is the account number suffix | AD62: LGCS_6203834591; 7099172939_6203834591; 1868971_6203834591 | AE62: LGCS_6203834591 - historical
A63: 6203842158 | B63: Electricity | C63: Australia | D63: VIC | E63: AU Small Energy | F63: Utilities - Horsham | G63: 10 BALLINGER STREET HORSHAM VIC 3400 | H63: DOWNER UTILITIES AUSTRALIA PTY LTD (ABN: 65 075 194 857) | I63: Utilities | J63: kWh | K63: 6286 | L63: AGL | M63: Origin | N63: 46204 | O63: 46934 | P63: 24 months | Q63: {=IFERROR(ROUNDUP(_xlfn.XLOOKUP(A63,'Budget FY26-28'!A:A,'Budget FY26-28'!M:O)*(1+Summary!$C$2), -2), "")} | R63: 2100 | S63: 2100 | T63: Ready | V63: 7099173036_6203842158 | W63: Electricity Small Market | X63: Electricity [kWh] | Y63: AGL | Z63: Horsham - Ballinger St | AA63: 2027 | AB63: Active | AC63: Connection ID is the account number suffix | AD63: 0620269716_6203842158; 300038025023_6203842158; 300039184647_6203842158
A64: 6305487004 | B64: Electricity | C64: Australia | D64: VIC | E64: AU Small Energy | F64: Property Lease - Broadford | G64: 10 CAMERON PDE BROADFORD VIC | H64: DOWNER EDI WORKS PTY LTD (ABN: 66 008 709 608) | I64: DM Roads | J64: kWh | K64: 11315 | L64: AGL | M64: Origin | N64: 46204 | O64: 46934 | P64: 24 months | Q64: {=IFERROR(ROUNDUP(_xlfn.XLOOKUP(A64,'Budget FY26-28'!A:A,'Budget FY26-28'!M:O)*(1+Summary!$C$2), -2), "")} | R64: 3300 | S64: 3300 | T64: Ready | V64: 7120528919_6305487004 | W64: Electricity Small Market | X64: Electricity [kWh] | Y64: AGL | Z64: VIC, Broadford (10 Cameron Parade) | AA64: DOWN0738 | AB64: Active | AC64: Connection ID is the account number suffix
A65: 6305812613 | B65: Electricity | C65: Australia | D65: VIC | E65: AU Small Energy | F65: Roads - Wangaratta | G65: 51 BUCKLER ROAD NORTH WANGARATTA VIC 3677 | H65: DOWNER EDI WORKS PTY LTD (ABN: 66 008 709 608) | I65: ROAD SERVICES | J65: kWh | K65: 33004 | L65: AGL | M65: Origin | N65: 46204 | O65: 46934 | P65: 24 months | Q65: {=IFERROR(ROUNDUP(_xlfn.XLOOKUP(A65,'Budget FY26-28'!A:A,'Budget FY26-28'!M:O)*(1+Summary!$C$2), -2), "")} | R65: 8700 | S65: 8700 | T65: Ready | V65: 7099172194_6305812613 | W65: Electricity Small Market | X65: Electricity [kWh] | Y65: AGL | Z65: Wangaratta | AA65: 17081070 | AB65: Active | AC65: Connection ID is the account number suffix | AD65: LGCS_6305812613; 4173353522_6305812613; 300019223902_6305812613 | AE65: LGCS_6305812613 - historical
A66: 6305983844 | B66: Electricity | C66: Australia | D66: VIC | E66: AU Small Energy | F66: Fowlers Asphalt - Bairnsdale | G66: 15 Rovan Pl Bairnsdale VIC 3875 | H66: FOWLERS ASPHALTING PTY. LIMITED (ABN: 86 007 406 386) | I66: ROAD SERVICES | J66: kWh | K66: 18825 | L66: AGL | M66: Origin | N66: 46204 | O66: 46934 | P66: 24 months | Q66: {=IFERROR(ROUNDUP(_xlfn.XLOOKUP(A66,'Budget FY26-28'!A:A,'Budget FY26-28'!M:O)*(1+Summary!$C$2), -2), "")} | R66: 5200 | S66: 5200 | T66: Ready | V66: 7099547411_6305983844 | W66: Electricity Small Market | X66: Electricity [kWh] | Y66: AGL | Z66: Tarmac Line Marking, Bairnsdale Depot | AA66: L9.J.17030829 | AB66: Active | AC66: Connection ID is the account number suffix | AD66: LGCS_6305983844; 0441568333_6305983844; 2288973295_6305983844 | AE66: LGCS_6305983844 - historical
A67: 6407387461 | B67: Electricity | C67: Australia | D67: VIC | E67: AU Small Energy | F67: Spotless UAM - Manufacturing Plant | G67: 2 MURRA STREET BENTLEIGH EAST VIC 3165 | H67: Utilities Asset Management Pty Ltd (ABN: TBC) | I67: SPOTLESS | J67: kWh | K67: 25187 | L67: AGL | M67: Origin | N67: 46204 | O67: 46934 | P67: 24 months | Q67: {=IFERROR(ROUNDUP(_xlfn.XLOOKUP(A67,'Budget FY26-28'!A:A,'Budget FY26-28'!M:O)*(1+Summary!$C$2), -2), "")} | R67: 5900 | S67: 5900 | T67: Ready | V67: 7099172889_6407387461 | W67: Electricity Small Market | X67: Electricity [kWh] | Y67: AGL | Z67: UAM - Bentleigh East | AA67: 9117 | AB67: Active | AC67: Connection ID is the account number suffix | AD67: 21295365_6407387461; 6373106072_6407387461; 300040431722_6407387461
A68: 6407695648 | B68: Electricity | C68: Australia | D68: VIC | E68: AU Small Energy | F68: Spotless - Skilltech | G68: Factory U2/ 200 WELLINGTON ROAD MULGRAVE VIC 3170 | H68: SKILLTECH CONSULTING SERVICES PTY. LTD. (ABN: 14 007 162 647) | I68: SPOTLESS | J68: kWh | K68: 13969 | L68: AGL | M68: Origin | N68: 46204 | O68: 46934 | P68: 24 months | Q68: {=IFERROR(ROUNDUP(_xlfn.XLOOKUP(A68,'Budget FY26-28'!A:A,'Budget FY26-28'!M:O)*(1+Summary!$C$2), -2), "")} | R68: 3400 | S68: 3400 | T68: Ready | V68: 7099173127_6407695648 | W68: Electricity Small Market | X68: Electricity [kWh] | Y68: AGL | Z68: Mulgrave - Wellington Rd, Clayton | AA68: 9118 | AB68: Active | AC68: Connection ID is the account number suffix | AD68: 41086067_6407695648; 0825998030_6407695648; 825998030_6407695648; 300040507539_6407695648; 300042684575_6407695648 | AE68: LGCS_6407695655 (at this location, different ID) - historical
A69: 6408293833 | B69: Electricity | C69: Australia | D69: VIC | E69: AU Small Energy | F69: Downer Utilites Substations | G69: 71 NAXOS WAY KEYSBOROUGH VIC | H69: DOWNER UTILITIES AUSTRALIA PTY LTD (ABN: 65 075 194 857) | I69: 241908 | J69: kWh | K69: 13140 | L69: AGL | M69: Origin | N69: 46204 | O69: 46934 | P69: 24 months | Q69: {=IFERROR(ROUNDUP(_xlfn.XLOOKUP(A69,'Budget FY26-28'!A:A,'Budget FY26-28'!M:O)*(1+Summary!$C$2), -2), "")} | R69: 3300 | S69: 3300 | T69: Ready | V69: 7111412230_6408293833 | W69: Electricity Small Market | X69: Electricity [kWh] | Y69: AGL | Z69: VIC, Keysborough (7 Naxos Way) | AA69: DOWN0767 | AB69: Active | AC69: Connection ID is the account number suffix
A70: 5240431343 | B70: Natural Gas | C70: Australia | D70: NSW | E70: AU Small Energy | F70: NSW Schools 2 -Kelso | G70: 88 BOYD ST KELSO NSW | H70: SPOTLESS FACILITY SERVICES PTY LTD (ABN: 83 072 293 880) | I70: Spotless | J70: MJ | K70: 1000 | L70: AGL | M70: Origin | N70: 46204 | O70: 46934 | P70: 24 months | Q70: {=IFERROR(ROUNDUP(_xlfn.XLOOKUP(A70,'Budget FY26-28'!A:A,'Budget FY26-28'!M:O)*(1+Summary!$C$2), -2), "")} | R70: 500 | S70: 500 | T70: Ready | V70: 2931201705_5240431343 | W70: Natural Gas - PDF Parsing | X70: Natural Gas [GJ] | Y70: EnergyAustralia | Z70: PPP - NSW Schools 2 (Kelso HS) | AA70: 9002 | AB70: Active | AC70: Connection ID is the account number suffix | AD70: 49123946_5240431343; 7113513159_5240431343; 200051509731_5240431343; A-C086B337_5240431343
A71: 5243917108 | B71: Natural Gas | C71: Australia | D71: NSW | E71: AU Small Energy | F71: NSW Schools 2 - Kariong | G71: 10 FESTIVAL DR KARIONG NSW | H71: SPOTLESS FACILITY SERVICES PTY LTD (ABN: 83 072 293 880) | I71: SPOTLESS | J71: MJ | K71: 1000 | L71: AGL | M71: Origin | N71: 46204 | O71: 46934 | P71: 24 months | Q71: {=IFERROR(ROUNDUP(_xlfn.XLOOKUP(A71,'Budget FY26-28'!A:A,'Budget FY26-28'!M:O)*(1+Summary!$C$2), -2), "")} | R71: 500 | S71: 500 | T71: Ready | V71: 6562861000_5243917108 | W71: Natural Gas - PDF Parsing | X71: Natural Gas [GJ] | Y71: EnergyAustralia | Z71: PPP - NSW Schools 2 (Kariong) | AA71: 9001 | AB71: Active | AC71: Connection ID is the account number suffix | AD71: 7113515329_5243917108
A72: 5246209066 | B72: Natural Gas | C72: Australia | D72: NSW | E72: AU Small Energy | F72: Spotless NSW Schools 2 - Elderslie PS | G72: 170 LODGES ST ELDERSLIE NSW | H72: SPOTLESS FACILITY SERVICES PTY LTD (ABN: 83 072 293 880) | I72: SPOTLESS | J72: MJ | K72: 1000 | L72: AGL | M72: Origin | N72: 46204 | O72: 46934 | P72: 24 months | Q72: {=IFERROR(ROUNDUP(_xlfn.XLOOKUP(A72,'Budget FY26-28'!A:A,'Budget FY26-28'!M:O)*(1+Summary!$C$2), -2), "")} | R72: 500 | S72: 500 | T72: Ready | V72: 1198751876_5246209066 | W72: Natural Gas - PDF Parsing | X72: Natural Gas [GJ] | Y72: EnergyAustralia | Z72: PPP - NSW Schools 2 (Elderslie PS) | AA72: 9009 | AB72: Active | AC72: Connection ID is the account number suffix | AD72: 68470632_5246209066; 7113513167_5246209066
A73: 5247058378 | B73: Natural Gas | C73: Australia | D73: NSW | E73: AU Small Energy | F73: NSW Schools 2 -Ashtonfield | G73: 1 NORFOLK ST ASHTONFIELD NSW | H73: SPOTLESS FACILITY SERVICES PTY LTD (ABN: 83 072 293 880) | I73: SPOTLESS | J73: MJ | K73: 1000 | L73: AGL | M73: Origin | N73: 46204 | O73: 46934 | P73: 24 months | Q73: {=IFERROR(ROUNDUP(_xlfn.XLOOKUP(A73,'Budget FY26-28'!A:A,'Budget FY26-28'!M:O)*(1+Summary!$C$2), -2), "")} | R73: 500 | S73: 500 | T73: Ready | V73: 3267093640_5247058378 | W73: Natural Gas - PDF Parsing | X73: Natural Gas [GJ] | Y73: EnergyAustralia | Z73: PPP - NSW Schools 2 (Ashtonfield PS) | AA73: 9008 | AB73: Active | AC73: Connection ID is the account number suffix | AD73: 7113513001_5247058378
A74: 5247063334 | B74: Natural Gas | C74: Australia | D74: NSW | E74: AU Small Energy | F74: Spotless NSW Schools 2 - Halinda HS | G74: LUXFORD RD WHALAN NSW | H74: SPOTLESS FACILITY SERVICES PTY LTD (ABN: 83 072 293 880) | I74: SPOTLESS | J74: MJ | K74: 1000 | L74: AGL | M74: Origin | N74: 46204 | O74: 46934 | P74: 24 months | Q74: {=IFERROR(ROUNDUP(_xlfn.XLOOKUP(A74,'Budget FY26-28'!A:A,'Budget FY26-28'!M:O)*(1+Summary!$C$2), -2), "")} | R74: 500 | S74: 500 | T74: Ready | V74: 7113511591_5247063334 | W74: Natural Gas - PDF Parsing | X74: Natural Gas [GJ] | Y74: AGL | Z74: PPP - NSW Schools 2 (Halinda SSP) | AA74: 9010 | AB74: Active | AC74: Connection ID is the account number suffix | AD74: 67506824_5247063334; 6241516621_5247063334
A75: 5247072812 | B75: Natural Gas | C75: Australia | D75: NSW | E75: AU Small Energy | F75: NSW Schools 2 - Ropes Crossing | G75: LOT 17 PULLEY DR ROPES CROSSING NSW | H75: SPOTLESS FACILITY SERVICES PTY LTD (ABN: 83 072 293 880) | I75: SPOTLESS | J75: MJ | K75: 1000 | L75: AGL | M75: Origin | N75: 46204 | O75: 46934 | P75: 24 months | Q75: {=IFERROR(ROUNDUP(_xlfn.XLOOKUP(A75,'Budget FY26-28'!A:A,'Budget FY26-28'!M:O)*(1+Summary!$C$2), -2), "")} | R75: 500 | S75: 500 | T75: Ready | V75: 7113511617_5247072812 | W75: Natural Gas - PDF Parsing | X75: Natural Gas [GJ] | Y75: AGL | Z75: PPP - NSW Schools 2 (Ropes Crossing PS) | AA75: 9004 | AB75: Active | AC75: Connection ID is the account number suffix | AD75: 53431185_5247072812; 8404243246_5247072812
A76: 5247072833 | B76: Natural Gas | C76: Australia | D76: NSW | E76: AU Small Energy | F76: NSW Schools John Palmer PS | G76: 85 THE PONDS BVD THE PONDS NSW | H76: SPOTLESS FACILITY SERVICES PTY LTD (ABN: 83 072 293 880) | I76: SPOTLESS | J76: MJ | K76: 1000 | L76: AGL | M76: Origin | N76: 46204 | O76: 46934 | P76: 24 months | Q76: {=IFERROR(ROUNDUP(_xlfn.XLOOKUP(A76,'Budget FY26-28'!A:A,'Budget FY26-28'!M:O)*(1+Summary!$C$2), -2), "")} | R76: 500 | S76: 500 | T76: Ready | V76: 7113515337_5247072833 | W76: Natural Gas - PDF Parsing | X76: Natural Gas [GJ] | Y76: AGL | Z76: PPP - NSW Schools 2 (John Palmer PS) | AA76: 9011 | AB76: Active | AC76: Connection ID is the account number suffix | AD76: 7028171853_5247072833; 7604232900_5247072833
A77: 5247074005 | B77: Natural Gas | C77: Australia | D77: NSW | E77: AU Small Energy | F77: NSW Schools 2 - Tullimbar | G77: EDEN PL TULLIMBAR NSW | H77: SPOTLESS FACILITY SERVICES PTY LTD (ABN: 83 072 293 880) | I77: SPOTLESS | J77: MJ | K77: 1000 | L77: AGL | M77: Origin | N77: 46204 | O77: 46934 | P77: 24 months | Q77: {=IFERROR(ROUNDUP(_xlfn.XLOOKUP(A77,'Budget FY26-28'!A:A,'Budget FY26-28'!M:O)*(1+Summary!$C$2), -2), "")} | R77: 500 | S77: 500 | T77: Ready | V77: 2819748120_5247074005 | W77: Natural Gas - PDF Parsing | X77: Natural Gas [GJ] | Y77: EnergyAustralia | Z77: PPP - NSW Schools 2 (Tulimbar PS) | AA77: 9006 | AB77: Active | AC77: Connection ID is the account number suffix | AD77: 70219068_5247074005; 7113511609_5247074005
A78: 5247082981 | B78: Natural Gas | C78: Australia | D78: NSW | E78: AU Small Energy | F78: NSW Schools 2 - Warnervale | G78: 179-201 WARNERVALE RD HAMLYN TERRACE NSW | H78: SPOTLESS FACILITY SERVICES PTY LTD (ABN: 83 072 293 880) | I78: SPOTLESS | J78: MJ | K78: 1000 | L78: AGL | M78: Origin | N78: 46204 | O78: 46934 | P78: 24 months | Q78: {=IFERROR(ROUNDUP(_xlfn.XLOOKUP(A78,'Budget FY26-28'!A:A,'Budget FY26-28'!M:O)*(1+Summary!$C$2), -2), "")} | R78: 500 | S78: 500 | T78: Ready | V78: 7113513019_5247082981 | W78: Natural Gas - PDF Parsing | X78: Natural Gas [GJ] | Y78: AGL | Z78: PPP - NSW Schools 2 (Warnervale PS) | AA78: 9007 | AB78: Active | AC78: Connection ID is the account number suffix | AD78: 68470632_5247082981; 8271041165_5247082981
A79: 5247083098 | B79: Natural Gas | C79: Australia | D79: NSW | E79: AU Small Energy | F79: NSW Schools 2 -Rouse Hill | G79: 240 WITHERS RD KELLYVILLE NSW | H79: SPOTLESS FACILITY SERVICES PTY LTD (ABN: 83 072 293 880) | I79: SPOTLESS | J79: MJ | K79: 1000 | L79: AGL | M79: Origin | N79: 46204 | O79: 46934 | P79: 24 months | Q79: {=IFERROR(ROUNDUP(_xlfn.XLOOKUP(A79,'Budget FY26-28'!A:A,'Budget FY26-28'!M:O)*(1+Summary!$C$2), -2), "")} | R79: 500 | S79: 500 | T79: Ready | V79: 7113510379_5247083098 | W79: Natural Gas - PDF Parsing | X79: Natural Gas [GJ] | Y79: AGL | Z79: PPP - NSW Schools 2 (Rouse Hill HS) | AA79: 9005 | AB79: Active | AC79: Connection ID is the account number suffix | AD79: 50410646_5247083098; 8861165395_5247083098
A80: 5270000035 | B80: Natural Gas | C80: Australia | D80: NSW | E80: AU Small Energy | F80: Roads - Tamworth | G80: 18 ARMSTRONG STREET WESTDALE NSW 2340 | H80: DOWNER EDI WORKS PTY LTD (ABN: 66 008 709 608) | I80: Road Services | J80: MJ | K80: 0 | L80: Origin | M80: Origin | N80: 46204 | O80: 46934 | P80: 24 months | Q80: {=IFERROR(ROUNDUP(_xlfn.XLOOKUP(A80,'Budget FY26-28'!A:A,'Budget FY26-28'!M:O)*(1+Summary!$C$2), -2), "")} | R80: 500 | S80: 500 | T80: Ready | V80: A-A7CEE9F0_5270000035 | W80: Natural Gas - PDF Parsing | X80: Natural Gas [GJ] | Y80: Origin | Z80: Tamworth | AA80: 170937 | AB80: Active | AC80: Connection ID is the account number suffix | AD80: 1109123_5270000035; 15003902611_5270000035 | AE80: LGCS_4001158058 (at this location, different ID) - historical
A81: 5410075384 | B81: Natural Gas | C81: Australia | D81: QLD | E81: AU Small Energy | F81: Mineral Tech - Carrara | G81: 11 ELYSIUM ROAD CARRARA QLD 4211 | H81: MINERAL TECHNOLOGIES PTY LTD (ABN: 52 105 309 260) | I81: Mineral Tech | J81: MJ | K81: 27439 | L81: Origin | M81: Origin | N81: 46204 | O81: 46934 | P81: 24 months | Q81: {=IFERROR(ROUNDUP(_xlfn.XLOOKUP(A81,'Budget FY26-28'!A:A,'Budget FY26-28'!M:O)*(1+Summary!$C$2), -2), "")} | R81: 1700 | S81: 1700 | T81: Ready | V81: A-C4B69989_5410075384 | W81: Natural Gas - PDF Parsing | X81: Natural Gas [GJ] | Y81: Origin | Z81: MT-Carrara | AA81: MT-39510068 | AB81: Active | AC81: Connection ID is the account number suffix | AD81: 71432793_5410075384; 400033605199_5410075384; A-E7991C4D_5410075384 | AE81: LGCS_QB06081428 (at this location, different ID) - historical · LGCS_QB06082220 (at this location, different ID) - historical
A82: 5410078053 | B82: Natural Gas | C82: Australia | D82: QLD | E82: AU Small Energy | F82: SPOTLESS SOUTHBANK TAFE | G82: 16 GLEBELG STREET SOUTH BRISBANE QLD 4101 | H82: SPOTLESS FACILITY SERVICES PTY LTD (ABN: 83 072 293 880) | I82: SPOTLESS | J82: MJ | K82: 153318 | L82: Origin | M82: Origin | N82: 46204 | O82: 46934 | P82: 24 months | Q82: {=IFERROR(ROUNDUP(_xlfn.XLOOKUP(A82,'Budget FY26-28'!A:A,'Budget FY26-28'!M:O)*(1+Summary!$C$2), -2), "")} | R82: 7000 | S82: 7000 | T82: Ready | V82: A-0818208A_5410078053 | W82: Natural Gas - PDF Parsing | X82: Natural Gas [GJ] | Y82: Origin | Z82: PPP - Southbank TAFE (QLD) | AA82: 9108 | AB82: Active | AC82: Connection ID is the account number suffix | AD82: 70928841_5410078053; A-8AB66196_5410078053
A83: 5410086500 | B83: Natural Gas | C83: Australia | D83: QLD | E83: AU Small Energy | F83: SPOTLESS SOUTHBANK TAFE | G83: BUILDING D 0 COLCHESTER STREET SOUTH BRISBANE QLD 4101 | H83: SPOTLESS FACILITY SERVICES PTY LTD (ABN: 83 072 293 880) | I83: SPOTLESS | J83: MJ | K83: 504905 | L83: Origin | M83: Origin | N83: 46204 | O83: 46934 | P83: 24 months | Q83: {=IFERROR(ROUNDUP(_xlfn.XLOOKUP(A83,'Budget FY26-28'!A:A,'Budget FY26-28'!M:O)*(1+Summary!$C$2), -2), "")} | R83: 19700 | S83: 19700 | T83: Ready | V83: A-87825F48_5410086500 | W83: Natural Gas - PDF Parsing | X83: Natural Gas [GJ] | Y83: Origin | Z83: PPP - Southbank TAFE (QLD) | AA83: 9108 | AB83: Active | AC83: Connection ID is the account number suffix | AD83: 70485982_5410086500; 400033605165_5410086500; A-5C73568F_5410086500
A84: 5420000032 | B84: Natural Gas | C84: Australia | D84: QLD | E84: AU Small Energy | F84: Rail - Maryborough | G84: 23 Bowen Street Maryborough QLD 4650 | H84: DOWNER EDI RAIL PTY LTD (ABN: 92 000 002 031) | I84: ROLLING STOCK | J84: MJ | K84: 888078 | L84: Origin | M84: Origin | N84: 46204 | O84: 46934 | P84: 24 months | Q84: {=IFERROR(ROUNDUP(_xlfn.XLOOKUP(A84,'Budget FY26-28'!A:A,'Budget FY26-28'!M:O)*(1+Summary!$C$2), -2), "")} | R84: 41300 | S84: 41300 | T84: Ready | V84: A-0870F40E_5420000032 | W84: Natural Gas - PDF Parsing | X84: Natural Gas [GJ] | Y84: Origin | Z84: Maryborough | AA84: 3011 | AB84: Active | AC84: Connection ID is the account number suffix | AD84: 15001100210_5420000032 | AE84: LGCS_QGGG000010 (at this location, different ID) - historical · LGCS_QGGG000320 (at this location, different ID) - historical
A85: 5510484999 | B85: Natural Gas | C85: Australia | D85: SA | E85: AU Small Energy | F85: Roads - Largs Bay | G85: 188 Jetty Road Largs Bay SA 5016 | H85: DOWNER EDI WORKS PTY LTD (ABN: 66 008 709 608) | I85: ROAD SERVICES | J85: MJ | K85: 766606 | L85: EnergyAustralia | M85: Origin | N85: 46204 | O85: 46934 | P85: 24 months | Q85: {=IFERROR(ROUNDUP(_xlfn.XLOOKUP(A85,'Budget FY26-28'!A:A,'Budget FY26-28'!M:O)*(1+Summary!$C$2), -2), "")} | R85: 26500 | S85: 26500 | T85: Ready | V85: 1262946362_5510484999 | W85: Natural Gas - PDF Parsing | X85: Natural Gas [GJ] | Y85: EnergyAustralia | Z85: Largs Bay | AA85: 163 | AB85: Active | AC85: Connection ID is the account number suffix | AD85: 15000050510_5510484999; 50002669746_5510484999 | AE85: LGCS_SAAAAAB023 (at this location, different ID) - historical · LGCS_SAAAAAC481 (at this location, different ID) - historical
A86: 5321918308 | B86: Natural Gas | C86: Australia | D86: VIC | E86: AU Small Energy | F86: Fowlers Asphalting Trafalgar (Contour Road) | G86: 100 Contour Road Trafalgar VIC 3824 | H86: FOWLERS ASPHALTING PTY. LIMITED (ABN: 86 007 406 386) | I86: ROAD SERVICES | J86: MJ | K86: 0 | L86: Origin | M86: Origin | N86: 46204 | O86: 46934 | P86: 24 months | Q86: {=IFERROR(ROUNDUP(_xlfn.XLOOKUP(A86,'Budget FY26-28'!A:A,'Budget FY26-28'!M:O)*(1+Summary!$C$2), -2), "")} | R86: 500 | S86: 500 | T86: Ready | V86: A-25171392_5321918308 | W86: Natural Gas - PDF Parsing | X86: Natural Gas [GJ] | Y86: Origin | Z86: Fowlers Asphalting, Trafalgar Depot | AB86: Active | AC86: Connection ID is the account number suffix | AD86: 300007860145_5321918308; 300046364232_5321918308 | AE86: LGCS_6305110585 (at this location, different ID) - historical
A87: 7001184714 | B87: Electricity | C87: Australia | D87: ACT | E87: AU Large Electricity | F87: Roads - Hume | G87: 36 Sawmill Circuit | H87: DOWNER EDI SERVICES PTY LTD (ABN: 71 137 732 042) | I87: T&I | J87: kWh | K87: 928827.68 | L87: Origin | M87: Origin | N87: 46204 | O87: 46934 | P87: 24 months | Q87: {=IFERROR(ROUNDUP(_xlfn.XLOOKUP(A87,'Budget FY26-28'!A:A,'Budget FY26-28'!M:O)*(1+Summary!$C$2), -2), "")} | R87: 194100 | S87: 192500 | T87: Ready | V87: 50002618040_7001184714 | W87: Electricity Large Market | X87: Electricity [kWh] | Y87: Origin | Z87: Asphalt Prod - Hume (101) | AA87: 101 | AB87: Active | AC87: Connection ID is the account number suffix | AD87: 50002618040_7001184714_CERTS; LGCS_7001184714; 385317_7001184714 | AE87: 50002618040_7001184714_CERTS (live) · LGCS_7001184714 - historical
A88: 4001127731 | B88: Electricity | C88: Australia | D88: NSW | E88: AU Large Electricity | F88: Roads - Jerramadra (Mogo) | G88: 55 Princes Highway | H88: DOWNER EDI WORKS PTY LTD (ABN: 66 008 709 608) | I88: T&I | J88: kWh | K88: 44278.31 | L88: Origin | M88: Origin | N88: 46204 | O88: 46934 | P88: 24 months | Q88: {=IFERROR(ROUNDUP(_xlfn.XLOOKUP(A88,'Budget FY26-28'!A:A,'Budget FY26-28'!M:O)*(1+Summary!$C$2), -2), "")} | R88: 22100 | S88: 22100 | T88: Ready | V88: 50002769514_4001127731 | W88: Electricity Small Market | X88: Electricity [kWh] | Y88: Origin | Z88: Asphalt Prod - Mogo (154) | AA88: 154 | AB88: Active | AC88: Connection ID is the account number suffix | AD88: LGCS_4001127731; 9863438916_4001127731; 200021562893_4001127731 | AE88: 50002769514_4001127731_CERTS (to create) · LGCS_4001127731 - historical · LGCS_4204072845 (at this location, different ID) - historical
A89: 4001158058 | B89: Electricity | C89: Australia | D89: NSW | E89: AU Large Electricity | F89: Roads - Tamworth | G89: 15 Armstrong Street | H89: DOWNER EDI SERVICES PTY LTD (ABN: 71 137 732 042) | I89: T&I | J89: kWh | K89: 0 | L89: Origin | M89: Origin | N89: 46204 | O89: 46934 | P89: 24 months | Q89: {=IFERROR(ROUNDUP(_xlfn.XLOOKUP(A89,'Budget FY26-28'!A:A,'Budget FY26-28'!M:O)*(1+Summary!$C$2), -2), "")} | R89: 0 | S89: 0 | T89: Review required | U89: No consumption reported | V89: 50002617983_4001158058 | W89: Electricity Large Market | X89: Electricity [kWh] | Y89: Origin | Z89: Tamworth | AA89: 170937 | AB89: Active | AC89: Connection ID is the account number suffix | AD89: 50002617983_4001158058_CERTS; LGCS_4001158058; 385299_4001158058 | AE89: 50002617983_4001158058_CERTS (live) · LGCS_4001158058 - historical
A90: 4001198085 | B90: Electricity | C90: Australia | D90: NSW | E90: AU Large Electricity | F90: NSW Schools 2 - Kelso HS | G90: 88 Boyd St | H90: SPOTLESS FACILITY SERVICES PTY LTD (ABN: 83 072 293 880) | I90: SICS | J90: kWh | K90: 399092.86 | L90: Origin | M90: Origin | N90: 46204 | O90: 46934 | P90: 24 months | Q90: {=IFERROR(ROUNDUP(_xlfn.XLOOKUP(A90,'Budget FY26-28'!A:A,'Budget FY26-28'!M:O)*(1+Summary!$C$2), -2), "")} | R90: 119700 | S90: 118900 | T90: Ready | V90: 50002617982_4001198085 | W90: Electricity Large Market | X90: Electricity [kWh] | Y90: Origin | Z90: PPP - NSW Schools 2 (Kelso HS) | AA90: 9002 | AB90: Active | AC90: Connection ID is the account number suffix | AD90: 50002617982_4001198085_CERTS; 385274_4001198085 | AE90: 50002617982_4001198085_CERTS (live)
A91: 4001200751 | B91: Electricity | C91: Australia | D91: NSW | E91: AU Large Electricity | F91: Defence - HQJOC | G91: 5835 Kings Hwy | H91: SPOTLESS FACILITY SERVICES PTY LTD (ABN: 83 072 293 880) | I91: SICS | J91: kWh | K91: 10268532 | L91: Origin | M91: Origin | N91: 46204 | O91: 46934 | P91: 24 months | Q91: {=IFERROR(ROUNDUP(_xlfn.XLOOKUP(A91,'Budget FY26-28'!A:A,'Budget FY26-28'!M:O)*(1+Summary!$C$2), -2), "")} | R91: 1916900 | S91: 1906600 | T91: Ready | V91: 50002617969_4001200751 | W91: Electricity Large Market | X91: Electricity [kWh] | Y91: Origin | Z91: PPP - HQJOC (ACT) | AA91: 9092 | AB91: Active | AC91: Connection ID is the account number suffix | AD91: 50002617969_4001200751_CERTS; 385289_4001200751 | AE91: 50002617969_4001200751_CERTS (live)
A92: 4001287259 | B92: Electricity | C92: Australia | D92: NSW | E92: AU Large Electricity | F92: RPQ SPRAYSEAL | G92: Lot 12 122 Gwydir St | H92: RPQ PTY LTD (ABN: 53 010 760 826) | I92: T&I | J92: kWh | K92: 171810.51 | L92: Origin | M92: Origin | N92: 46204 | O92: 46934 | P92: 24 months | Q92: {=IFERROR(ROUNDUP(_xlfn.XLOOKUP(A92,'Budget FY26-28'!A:A,'Budget FY26-28'!M:O)*(1+Summary!$C$2), -2), "")} | R92: 41600 | S92: 41500 | T92: Ready | V92: 50002617997_4001287259 | W92: Electricity Large Market | X92: Electricity [kWh] | Y92: Origin | Z92: RPQ NSW Moree | AA92: L9.J.171220 | AB92: Active | AC92: Connection ID is the account number suffix | AD92: 50002617997_4001287259_CERTS; LGCS_4001287259; LGCS_4001287259; 200034933644_4001287259 | AE92: 50002617997_4001287259_CERTS (live) · LGCS_4001287259 - historical
A93: 4103689689 | B93: Electricity | C93: Australia | D93: NSW | E93: AU Large Electricity | F93: NSW Schools 2- Ashtonfield | G93: 4642 Norfolk Street | H93: SPOTLESS FACILITY SERVICES PTY LTD (ABN: 83 072 293 880) | I93: SICS | J93: kWh | K93: 143552.12 | L93: Origin | M93: Origin | N93: 46204 | O93: 46934 | P93: 24 months | Q93: {=IFERROR(ROUNDUP(_xlfn.XLOOKUP(A93,'Budget FY26-28'!A:A,'Budget FY26-28'!M:O)*(1+Summary!$C$2), -2), "")} | R93: 36800 | S93: 36600 | T93: Ready | V93: 50002716068_4103689689 | W93: Electricity Large Market | X93: Electricity [kWh] | Y93: Origin | Z93: PPP - NSW Schools 2 (Ashtonfield PS) | AA93: 9008 | AB93: Active | AC93: Connection ID is the account number suffix | AD93: 50002716068_4103689689_CERTS | AE93: 50002716068_4103689689_CERTS (live)
A94: 4103705443 | B94: Electricity | C94: Australia | D94: NSW | E94: AU Large Electricity | F94: NSW Schools 2- Warnervale PS | G94: Warnervale Rd | H94: SPOTLESS FACILITY SERVICES PTY LTD (ABN: 83 072 293 880) | I94: SICS | J94: kWh | K94: 106397.96 | L94: Origin | M94: Origin | N94: 46204 | O94: 46934 | P94: 24 months | Q94: {=IFERROR(ROUNDUP(_xlfn.XLOOKUP(A94,'Budget FY26-28'!A:A,'Budget FY26-28'!M:O)*(1+Summary!$C$2), -2), "")} | R94: 26900 | S94: 26700 | T94: Ready | V94: 50002617995_4103705443 | W94: Electricity Large Market | X94: Electricity [kWh] | Y94: Origin | Z94: PPP - NSW Schools 2 (Warnervale PS) | AA94: 9007 | AB94: Active | AC94: Connection ID is the account number suffix | AD94: 50002617995_4103705443_CERTS; 3229870000_4103705443 | AE94: 50002617995_4103705443_CERTS (live)
A95: 4103711576 | B95: Electricity | C95: Australia | D95: NSW | E95: AU Large Electricity | F95: Rail - Auburn | G95: Manchester Road | H95: DOWNER EDI SERVICES PTY LTD (ABN: 71 137 732 042) | I95: RAIL | J95: kWh | K95: 2405011.6 | L95: Origin | M95: Origin | N95: 46204 | O95: 46934 | P95: 24 months | Q95: {=IFERROR(ROUNDUP(_xlfn.XLOOKUP(A95,'Budget FY26-28'!A:A,'Budget FY26-28'!M:O)*(1+Summary!$C$2), -2), "")} | R95: 409100 | S95: 406500 | T95: Ready | V95: 50002617965_4103711576 | W95: Electricity Large Market | X95: Electricity [kWh] | Y95: Origin | Z95: Auburn | AA95: 3002 | AB95: Active | AC95: Connection ID is the account number suffix | AD95: 50002617965_4103711576_CERTS; LGCS_4103711576; 385297_4103711576 | AE95: 50002617965_4103711576_CERTS (live) · LGCS_4103711576 - historical · LGCS_4103713125 (at this location, different ID) - historical
A96: 4103713125 | B96: Electricity | C96: Australia | D96: NSW | E96: AU Large Electricity | F96: Rail - Auburn | G96: Manchester Road | H96: DOWNER EDI SERVICES PTY LTD (ABN: 71 137 732 042) | I96: RAIL | J96: kWh | K96: 1251891.6 | L96: Origin | M96: Origin | N96: 46204 | O96: 46934 | P96: 24 months | Q96: {=IFERROR(ROUNDUP(_xlfn.XLOOKUP(A96,'Budget FY26-28'!A:A,'Budget FY26-28'!M:O)*(1+Summary!$C$2), -2), "")} | R96: 257800 | S96: 256500 | T96: Ready | V96: 50002617957_4103713125 | W96: Electricity Large Market | X96: Electricity [kWh] | Y96: Origin | Z96: Auburn | AA96: 3002 | AB96: Active | AC96: Connection ID is the account number suffix | AD96: 50002617957_4103713125_CERTS; LGCS_4103713125; 385287_4103713125 | AE96: 50002617957_4103713125_CERTS (live) · LGCS_4103711576 (at this location, different ID) - historical · LGCS_4103713125 - historical
A97: 4103737079 | B97: Electricity | C97: Australia | D97: NSW | E97: AU Large Electricity | F97: Corporate Office - North Ryde | G97: Floor 2 - Trinity Bus Campus Bldg A, 39 Delphi Road | H97: DOWNER EDI SERVICES PTY LTD (ABN: 71 137 732 042) | I97: CORPORATE | J97: kWh | K97: 19241.4 | L97: Origin | M97: Origin | N97: 46204 | O97: 46934 | P97: 24 months | Q97: {=IFERROR(ROUNDUP(_xlfn.XLOOKUP(A97,'Budget FY26-28'!A:A,'Budget FY26-28'!M:O)*(1+Summary!$C$2), -2), "")} | R97: 10800 | S97: 10800 | T97: Ready | V97: 50002617973_4103737079 | W97: Electricity Large Market | X97: Electricity [kWh] | Y97: Origin | Z97: North Ryde T1 - Level 1 | AA97: 1006 | AB97: Active | AC97: Connection ID is the account number suffix | AD97: 50002617973_4103737079_CERTS; LGCS_4103737079; 385314_4103737079 | AE97: 50002617973_4103737079_CERTS (live) · LGCS_4103737079 - historical · LGCS_4103737729 (at this location, different ID) - historical
A98: 4103737729 | B98: Electricity | C98: Australia | D98: NSW | E98: AU Large Electricity | F98: Corporate Office - North Ryde | G98: Floor 1 - Trinity Bus Campus Bldg A, 39 Delphi Road | H98: DOWNER EDI SERVICES PTY LTD (ABN: 71 137 732 042) | I98: CORPORATE | J98: kWh | K98: 13618.63 | L98: Origin | M98: Origin | N98: 46204 | O98: 46934 | P98: 24 months | Q98: {=IFERROR(ROUNDUP(_xlfn.XLOOKUP(A98,'Budget FY26-28'!A:A,'Budget FY26-28'!M:O)*(1+Summary!$C$2), -2), "")} | R98: 3900 | S98: 3900 | T98: Ready | V98: 50002617971_4103737729 | W98: Electricity Large Market | X98: Electricity [kWh] | Y98: Origin | Z98: North Ryde T1 - Level 1 | AA98: 1006 | AB98: Active | AC98: Connection ID is the account number suffix | AD98: 50002617971_4103737729_CERTS; LGCS_4103737729; 385282_4103737729 | AE98: 50002617971_4103737729_CERTS (live) · LGCS_4103737079 (at this location, different ID) - historical · LGCS_4103737729 - historical
A99: 4103742938 | B99: Electricity | C99: Australia | D99: NSW | E99: AU Large Electricity | F99: Corporate Office - North Ryde | G99: Triniti 1, Level 3, 39 Delhi Road (Trinity Business Campus) | H99: DOWNER EDI SERVICES PTY LTD (ABN: 71 137 732 042) | I99: CORPORATE | J99: kWh | K99: 105623.45 | L99: Origin | M99: Origin | N99: 46204 | O99: 46934 | P99: 24 months | Q99: {=IFERROR(ROUNDUP(_xlfn.XLOOKUP(A99,'Budget FY26-28'!A:A,'Budget FY26-28'!M:O)*(1+Summary!$C$2), -2), "")} | R99: 50300 | S99: 50100 | T99: Ready | V99: 50002617975_4103742938 | W99: Electricity Large Market | X99: Electricity [kWh] | Y99: Origin | Z99: North Ryde T1 - Level 3 | AA99: 1007 | AB99: Active | AC99: Connection ID is the account number suffix | AD99: 50002617975_4103742938_CERTS; LGCS_4103742938; 385300_4103742938 | AE99: 50002617975_4103742938_CERTS (live) · LGCS_4103742938 - historical · LGCS_4103742939 (at this location, different ID) - historical
A100: 4103742939 | B100: Electricity | C100: Australia | D100: NSW | E100: AU Large Electricity | F100: Corporate Office - North Ryde | G100: Trinity Business Campus Bld A Level 3 Tenant Server Room Tenacy Fl 3, 39 Delhi Road | H100: DOWNER EDI SERVICES PTY LTD (ABN: 71 137 732 042) | I100: CORPORATE | J100: kWh | K100: 81857.8 | L100: Origin | M100: Origin | N100: 46204 | O100: 46934 | P100: 24 months | Q100: {=IFERROR(ROUNDUP(_xlfn.XLOOKUP(A100,'Budget FY26-28'!A:A,'Budget FY26-28'!M:O)*(1+Summary!$C$2), -2), "")} | R100: 38800 | S100: 38800 | T100: Ready | V100: 50002617966_4103742939 | W100: Electricity Large Market | X100: Electricity [kWh] | Y100: Origin | Z100: North Ryde T1 - Level 3 | AA100: 1007 | AB100: Active | AC100: Connection ID is the account number suffix | AD100: 50002617966_4103742939_CERTS; LGCS_4103742939; 385315_4103742939 | AE100: 50002617966_4103742939_CERTS (live) · LGCS_4103742938 (at this location, different ID) - historical · LGCS_4103742939 - historical
...

Sheet Budget FY26-28
A1: FY26–FY28 Budget
A2: Connection ID | B2: Country | C2: Commodity | D2: State / Region | E2: Portfolio Group | F2: Units | G2: Annual Consumption | H2: Contract Start | I2: Contract End | J2: Currency | K2: Annual Input (current term) | L2: Renewal / FY28 Input | M2: FY26 Budget | N2: FY27 Budget | O2: FY28 Budget | P2: Budget Status | Q2: Notes
A3: 5265773931 | B3: {=_xlfn.XLOOKUP(A3,'Site Register'!A:A,'Site Register'!B:E)} | C3: Australia | D3: ACT | E3: AU Large Natural Gas | F3: GJ | G3: 30729.026 | H3: 46388 | I3: 47483 | J3: AUD | K3: ='Rate Inputs'!E134 | L3: ='Rate Inputs'!F134 | M3: =IF(OR($P3="Ready",$P3="FY26 provisional",$P3="FY26 secured"),IF($H3<=DATE(2025,7,1),ROUNDUP($K3,-2),IF('Rate Inputs'!$J134="","",ROUNDUP(IF($H3>DATE(2026,6,30),'Rate Inputs'!$J134,'Rate Inputs'!$J134*($H3-DATE(2025,7,1))/365+$K3*(DATE(2026,6,30)-$H3+1)/365),-2))),"") | N3: =IF($P3="Ready",ROUNDUP(IFERROR($K3,0),-2),IF(OR($P3="FY26 provisional",$P3="FY26 secured"),"",0)) | O3: =IF($P3="Ready",IF('Rate Inputs'!$F134="","",ROUNDUP(IFERROR($L3,0),-2)),IF(OR($P3="FY26 provisional",$P3="FY26 secured"),"",0)) | P3: Ready
A4: 5242077399 | B4: {=_xlfn.XLOOKUP(A4,'Site Register'!A:A,'Site Register'!B:E)} | C4: Australia | D4: NSW | E4: AU Large Natural Gas | F4: GJ | G4: 19847.411 | H4: 46023 | I4: 46752 | J4: AUD | K4: ='Rate Inputs'!E136 | L4: ='Rate Inputs'!F136 | M4: =IF(OR($P4="Ready",$P4="FY26 provisional",$P4="FY26 secured"),IF($H4<=DATE(2025,7,1),ROUNDUP($K4,-2),IF('Rate Inputs'!$J136="","",ROUNDUP(IF($H4>DATE(2026,6,30),'Rate Inputs'!$J136,'Rate Inputs'!$J136*($H4-DATE(2025,7,1))/365+$K4*(DATE(2026,6,30)-$H4+1)/365),-2))),"") | N4: =IF($P4="Ready",ROUNDUP(IFERROR($K4,0),-2),IF(OR($P4="FY26 provisional",$P4="FY26 secured"),"",0)) | O4: =IF($P4="Ready",IF('Rate Inputs'!$F136="","",ROUNDUP(IFERROR($L4,0),-2)),IF(OR($P4="FY26 provisional",$P4="FY26 secured"),"",0)) | P4: Ready
A5: 5247064745 | B5: {=_xlfn.XLOOKUP(A5,'Site Register'!A:A,'Site Register'!B:E)} | C5: Australia | D5: NSW | E5: AU Large Natural Gas | F5: GJ | G5: 2500 | H5: 46388 | I5: 47483 | J5: AUD | K5: ='Rate Inputs'!E141 | L5: ='Rate Inputs'!F141 | M5: =IF(OR($P5="Ready",$P5="FY26 provisional",$P5="FY26 secured"),IF($H5<=DATE(2025,7,1),ROUNDUP($K5,-2),IF('Rate Inputs'!$J141="","",ROUNDUP(IF($H5>DATE(2026,6,30),'Rate Inputs'!$J141,'Rate Inputs'!$J141*($H5-DATE(2025,7,1))/365+$K5*(DATE(2026,6,30)-$H5+1)/365),-2))),"") | N5: =IF($P5="Ready",ROUNDUP(IFERROR($K5,0),-2),IF(OR($P5="FY26 provisional",$P5="FY26 secured"),"",0)) | O5: =IF($P5="Ready",IF('Rate Inputs'!$F141="","",ROUNDUP(IFERROR($L5,0),-2)),IF(OR($P5="FY26 provisional",$P5="FY26 secured"),"",0)) | P5: Ready
A6: 5248353654 | B6: {=_xlfn.XLOOKUP(A6,'Site Register'!A:A,'Site Register'!B:E)} | C6: Australia | D6: NSW | E6: AU Large Natural Gas | F6: GJ | G6: 108015.37 | H6: 46023 | I6: 46752 | J6: AUD | K6: ='Rate Inputs'!E147 | L6: ='Rate Inputs'!F147 | M6: =IF(OR($P6="Ready",$P6="FY26 provisional",$P6="FY26 secured"),IF($H6<=DATE(2025,7,1),ROUNDUP($K6,-2),IF('Rate Inputs'!$J147="","",ROUNDUP(IF($H6>DATE(2026,6,30),'Rate Inputs'!$J147,'Rate Inputs'!$J147*($H6-DATE(2025,7,1))/365+$K6*(DATE(2026,6,30)-$H6+1)/365),-2))),"") | N6: =IF($P6="Ready",ROUNDUP(IFERROR($K6,0),-2),IF(OR($P6="FY26 provisional",$P6="FY26 secured"),"",0)) | O6: =IF($P6="Ready",IF('Rate Inputs'!$F147="","",ROUNDUP(IFERROR($L6,0),-2)),IF(OR($P6="FY26 provisional",$P6="FY26 secured"),"",0)) | P6: Ready
A7: 5265761108 | B7: {=_xlfn.XLOOKUP(A7,'Site Register'!A:A,'Site Register'!B:E)} | C7: Australia | D7: NSW | E7: AU Large Natural Gas | F7: GJ | G7: 1300 | H7: 46388 | I7: 46752 | J7: AUD | K7: ='Rate Inputs'!E148 | L7: ='Rate Inputs'!F148 | M7: =IF(OR($P7="Ready",$P7="FY26 provisional",$P7="FY26 secured"),IF($H7<=DATE(2025,7,1),ROUNDUP($K7,-2),IF('Rate Inputs'!$J148="","",ROUNDUP(IF($H7>DATE(2026,6,30),'Rate Inputs'!$J148,'Rate Inputs'!$J148*($H7-DATE(2025,7,1))/365+$K7*(DATE(2026,6,30)-$H7+1)/365),-2))),"") | N7: =IF($P7="Ready",ROUNDUP(IFERROR($K7,0),-2),IF(OR($P7="FY26 provisional",$P7="FY26 secured"),"",0)) | O7: =IF($P7="Ready",IF('Rate Inputs'!$F148="","",ROUNDUP(IFERROR($L7,0),-2)),IF(OR($P7="FY26 provisional",$P7="FY26 secured"),"",0)) | P7: Ready
A8: 5510072233 | B8: {=_xlfn.XLOOKUP(A8,'Site Register'!A:A,'Site Register'!B:E)} | C8: Australia | D8: SA | E8: AU Large Natural Gas | F8: GJ | G8: 92565.36 | H8: 46023 | I8: 46752 | J8: AUD | K8: ='Rate Inputs'!E154 | L8: ='Rate Inputs'!F154 | M8: =IF(OR($P8="Ready",$P8="FY26 provisional",$P8="FY26 secured"),IF($H8<=DATE(2025,7,1),ROUNDUP($K8,-2),IF('Rate Inputs'!$J154="","",ROUNDUP(IF($H8>DATE(2026,6,30),'Rate Inputs'!$J154,'Rate Inputs'!$J154*($H8-DATE(2025,7,1))/365+$K8*(DATE(2026,6,30)-$H8+1)/365),-2))),"") | N8: =IF($P8="Ready",ROUNDUP(IFERROR($K8,0),-2),IF(OR($P8="FY26 provisional",$P8="FY26 secured"),"",0)) | O8: =IF($P8="Ready",IF('Rate Inputs'!$F154="","",ROUNDUP(IFERROR($L8,0),-2)),IF(OR($P8="FY26 provisional",$P8="FY26 secured"),"",0)) | P8: Ready
A9: 5510485000 | B9: {=_xlfn.XLOOKUP(A9,'Site Register'!A:A,'Site Register'!B:E)} | C9: Australia | D9: SA | E9: AU Large Natural Gas | F9: GJ | G9: 13214.104 | H9: 46023 | I9: 46752 | J9: AUD | K9: ='Rate Inputs'!E156 | L9: ='Rate Inputs'!F156 | M9: =IF(OR($P9="Ready",$P9="FY26 provisional",$P9="FY26 secured"),IF($H9<=DATE(2025,7,1),ROUNDUP($K9,-2),IF('Rate Inputs'!$J156="","",ROUNDUP(IF($H9>DATE(2026,6,30),'Rate Inputs'!$J156,'Rate Inputs'!$J156*($H9-DATE(2025,7,1))/365+$K9*(DATE(2026,6,30)-$H9+1)/365),-2))),"") | N9: =IF($P9="Ready",ROUNDUP(IFERROR($K9,0),-2),IF(OR($P9="FY26 provisional",$P9="FY26 secured"),"",0)) | O9: =IF($P9="Ready",IF('Rate Inputs'!$F156="","",ROUNDUP(IFERROR($L9,0),-2)),IF(OR($P9="FY26 provisional",$P9="FY26 secured"),"",0)) | P9: Ready
A10: 5762711908 | B10: {=_xlfn.XLOOKUP(A10,'Site Register'!A:A,'Site Register'!B:E)} | C10: Australia | D10: TAS | E10: AU Large Natural Gas | F10: GJ | G10: 15621.564 | H10: 45658 | I10: 46387 | J10: AUD | K10: ='Rate Inputs'!E157 | L10: =K10 | M10: =IF(OR($P10="Ready",$P10="FY26 provisional",$P10="FY26 secured"),IF($H10<=DATE(2025,7,1),ROUNDUP($K10,-2),IF('Rate Inputs'!$J157="","",ROUNDUP(IF($H10>DATE(2026,6,30),'Rate Inputs'!$J157,'Rate Inputs'!$J157*($H10-DATE(2025,7,1))/365+$K10*(DATE(2026,6,30)-$H10+1)/365),-2))),"") | N10: =IF($P10="Ready",ROUNDUP(IFERROR($K10,0),-2),IF(OR($P10="FY26 provisional",$P10="FY26 secured"),"",0)) | O10: =N10 | P10: Ready | Q10: Estimated FY27/FY28 based on FY26 contract
A11: 5310000243 | B11: {=_xlfn.XLOOKUP(A11,'Site Register'!A:A,'Site Register'!B:E)} | C11: Australia | D11: VIC | E11: AU Large Natural Gas | F11: GJ | G11: 57783.717 | H11: 46023 | I11: 46752 | J11: AUD | K11: ='Rate Inputs'!E158 | L11: ='Rate Inputs'!F158 | M11: =IF(OR($P11="Ready",$P11="FY26 provisional",$P11="FY26 secured"),IF($H11<=DATE(2025,7,1),ROUNDUP($K11,-2),IF('Rate Inputs'!$J158="","",ROUNDUP(IF($H11>DATE(2026,6,30),'Rate Inputs'!$J158,'Rate Inputs'!$J158*($H11-DATE(2025,7,1))/365+$K11*(DATE(2026,6,30)-$H11+1)/365),-2))),"") | N11: =IF($P11="Ready",ROUNDUP(IFERROR($K11,0),-2),IF(OR($P11="FY26 provisional",$P11="FY26 secured"),"",0)) | O11: =IF($P11="Ready",IF('Rate Inputs'!$F158="","",ROUNDUP(IFERROR($L11,0),-2)),IF(OR($P11="FY26 provisional",$P11="FY26 secured"),"",0)) | P11: Ready
A12: 5320000943 | B12: {=_xlfn.XLOOKUP(A12,'Site Register'!A:A,'Site Register'!B:E)} | C12: Australia | D12: VIC | E12: AU Large Natural Gas | F12: GJ | G12: 23114.486 | H12: 46023 | I12: 46752 | J12: AUD | K12: ='Rate Inputs'!E159 | L12: ='Rate Inputs'!F159 | M12: =IF(OR($P12="Ready",$P12="FY26 provisional",$P12="FY26 secured"),IF($H12<=DATE(2025,7,1),ROUNDUP($K12,-2),IF('Rate Inputs'!$J159="","",ROUNDUP(IF($H12>DATE(2026,6,30),'Rate Inputs'!$J159,'Rate Inputs'!$J159*($H12-DATE(2025,7,1))/365+$K12*(DATE(2026,6,30)-$H12+1)/365),-2))),"") | N12: =IF($P12="Ready",ROUNDUP(IFERROR($K12,0),-2),IF(OR($P12="FY26 provisional",$P12="FY26 secured"),"",0)) | O12: =IF($P12="Ready",IF('Rate Inputs'!$F159="","",ROUNDUP(IFERROR($L12,0),-2)),IF(OR($P12="FY26 provisional",$P12="FY26 secured"),"",0)) | P12: Ready
A13: 5330662312 | B13: {=_xlfn.XLOOKUP(A13,'Site Register'!A:A,'Site Register'!B:E)} | C13: Australia | D13: VIC | E13: AU Large Natural Gas | F13: GJ | G13: 103871.24 | H13: 46023 | I13: 46752 | J13: AUD | K13: ='Rate Inputs'!E161 | L13: ='Rate Inputs'!F161 | M13: =IF(OR($P13="Ready",$P13="FY26 provisional",$P13="FY26 secured"),IF($H13<=DATE(2025,7,1),ROUNDUP($K13,-2),IF('Rate Inputs'!$J161="","",ROUNDUP(IF($H13>DATE(2026,6,30),'Rate Inputs'!$J161,'Rate Inputs'!$J161*($H13-DATE(2025,7,1))/365+$K13*(DATE(2026,6,30)-$H13+1)/365),-2))),"") | N13: =IF($P13="Ready",ROUNDUP(IFERROR($K13,0),-2),IF(OR($P13="FY26 provisional",$P13="FY26 secured"),"",0)) | O13: =IF($P13="Ready",IF('Rate Inputs'!$F161="","",ROUNDUP(IFERROR($L13,0),-2)),IF(OR($P13="FY26 provisional",$P13="FY26 secured"),"",0)) | P13: Ready
A14: 5600405263 | B14: {=_xlfn.XLOOKUP(A14,'Site Register'!A:A,'Site Register'!B:E)} | C14: Australia | D14: WA | E14: AU Large Natural Gas | F14: GJ | G14: 590 | H14: 46023 | I14: 46752 | J14: AUD | K14: ='Rate Inputs'!E162 | L14: ='Rate Inputs'!F162 | M14: =IF(OR($P14="Ready",$P14="FY26 provisional",$P14="FY26 secured"),IF($H14<=DATE(2025,7,1),ROUNDUP($K14,-2),IF('Rate Inputs'!$J162="","",ROUNDUP(IF($H14>DATE(2026,6,30),'Rate Inputs'!$J162,'Rate Inputs'!$J162*($H14-DATE(2025,7,1))/365+$K14*(DATE(2026,6,30)-$H14+1)/365),-2))),"") | N14: =IF($P14="Ready",ROUNDUP(IFERROR($K14,0),-2),IF(OR($P14="FY26 provisional",$P14="FY26 secured"),"",0)) | O14: =N14 | P14: Ready | Q14: Estimated FY28 based on FY27 contract
A15: 5600436929 | B15: {=_xlfn.XLOOKUP(A15,'Site Register'!A:A,'Site Register'!B:E)} | C15: Australia | D15: WA | E15: AU Large Natural Gas | F15: GJ | G15: 23242.137 | H15: 46023 | I15: 46752 | J15: AUD | K15: ='Rate Inputs'!E163 | L15: ='Rate Inputs'!F163 | M15: =IF(OR($P15="Ready",$P15="FY26 provisional",$P15="FY26 secured"),IF($H15<=DATE(2025,7,1),ROUNDUP($K15,-2),IF('Rate Inputs'!$J163="","",ROUNDUP(IF($H15>DATE(2026,6,30),'Rate Inputs'!$J163,'Rate Inputs'!$J163*($H15-DATE(2025,7,1))/365+$K15*(DATE(2026,6,30)-$H15+1)/365),-2))),"") | N15: =IF($P15="Ready",ROUNDUP(IFERROR($K15,0),-2),IF(OR($P15="FY26 provisional",$P15="FY26 secured"),"",0)) | O15: =N15 | P15: Ready | Q15: Estimated FY28 based on FY27 contract
A16: 5600604830 | B16: {=_xlfn.XLOOKUP(A16,'Site Register'!A:A,'Site Register'!B:E)} | C16: Australia | D16: WA | E16: AU Large Natural Gas | F16: GJ | G16: 9471.6073 | H16: 46023 | I16: 46752 | J16: AUD | K16: ='Rate Inputs'!E164 | L16: ='Rate Inputs'!F164 | M16: =IF(OR($P16="Ready",$P16="FY26 provisional",$P16="FY26 secured"),IF($H16<=DATE(2025,7,1),ROUNDUP($K16,-2),IF('Rate Inputs'!$J164="","",ROUNDUP(IF($H16>DATE(2026,6,30),'Rate Inputs'!$J164,'Rate Inputs'!$J164*($H16-DATE(2025,7,1))/365+$K16*(DATE(2026,6,30)-$H16+1)/365),-2))),"") | N16: =IF($P16="Ready",ROUNDUP(IFERROR($K16,0),-2),IF(OR($P16="FY26 provisional",$P16="FY26 secured"),"",0)) | O16: =N16 | P16: Ready | Q16: Estimated FY28 based on FY27 contract
A17: 5600945901 | B17: {=_xlfn.XLOOKUP(A17,'Site Register'!A:A,'Site Register'!B:E)} | C17: Australia | D17: WA | E17: AU Large Natural Gas | F17: GJ | G17: 34066.928 | H17: 46023 | I17: 46752 | J17: AUD | K17: ='Rate Inputs'!E165 | L17: ='Rate Inputs'!F165 | M17: =IF(OR($P17="Ready",$P17="FY26 provisional",$P17="FY26 secured"),IF($H17<=DATE(2025,7,1),ROUNDUP($K17,-2),IF('Rate Inputs'!$J165="","",ROUNDUP(IF($H17>DATE(2026,6,30),'Rate Inputs'!$J165,'Rate Inputs'!$J165*($H17-DATE(2025,7,1))/365+$K17*(DATE(2026,6,30)-$H17+1)/365),-2))),"") | N17: =IF($P17="Ready",ROUNDUP(IFERROR($K17,0),-2),IF(OR($P17="FY26 provisional",$P17="FY26 secured"),"",0)) | O17: =N17 | P17: Ready | Q17: Estimated FY28 based on FY27 contract
A18: 3053253239 | B18: {=_xlfn.XLOOKUP(A18,'Site Register'!A:A,'Site Register'!B:E)} | C18: Australia | D18: QLD | E18: AU Large Electricity | F18: kWh | G18: 6208798 | H18: 46204 | I18: 46934 | J18: AUD | K18: ='Rate Inputs'!E59 | L18: ='Rate Inputs'!F59 | M18: =IF(OR($P18="Ready",$P18="FY26 provisional",$P18="FY26 secured"),IF($H18<=DATE(2025,7,1),ROUNDUP($K18,-2),IF('Rate Inputs'!$J59="","",ROUNDUP(IF($H18>DATE(2026,6,30),'Rate Inputs'!$J59,'Rate Inputs'!$J59*($H18-DATE(2025,7,1))/365+$K18*(DATE(2026,6,30)-$H18+1)/365),-2))),"") | N18: =IF($P18="Ready",ROUNDUP(IFERROR($K18,0),-2),IF(OR($P18="FY26 provisional",$P18="FY26 secured"),"",0)) | O18: =IF($P18="Ready",IF('Rate Inputs'!$F59="","",ROUNDUP(IFERROR($L18,0),-2)),IF(OR($P18="FY26 provisional",$P18="FY26 secured"),"",0)) | P18: Ready
A19: 6305885252 | B19: {=_xlfn.XLOOKUP(A19,'Site Register'!A:A,'Site Register'!B:E)} | C19: Australia | D19: VIC | E19: AU Large Electricity | F19: kWh | G19: 201844 | H19: 46204 | I19: 46934 | J19: AUD | K19: ='Rate Inputs'!E116 | L19: ='Rate Inputs'!F116 | M19: =IF(OR($P19="Ready",$P19="FY26 provisional",$P19="FY26 secured"),IF($H19<=DATE(2025,7,1),ROUNDUP($K19,-2),IF('Rate Inputs'!$J116="","",ROUNDUP(IF($H19>DATE(2026,6,30),'Rate Inputs'!$J116,'Rate Inputs'!$J116*($H19-DATE(2025,7,1))/365+$K19*(DATE(2026,6,30)-$H19+1)/365),-2))),"") | N19: =IF($P19="Ready",ROUNDUP(IFERROR($K19,0),-2),IF(OR($P19="FY26 provisional",$P19="FY26 secured"),"",0)) | O19: =IF($P19="Ready",IF('Rate Inputs'!$F116="","",ROUNDUP(IFERROR($L19,0),-2)),IF(OR($P19="FY26 provisional",$P19="FY26 secured"),"",0)) | P19: Ready
A20: 4001050448 | B20: {=_xlfn.XLOOKUP(A20,'Site Register'!A:A,'Site Register'!B:E)} | C20: Australia | D20: NSW | E20: AU Small Energy | F20: kWh | G20: 28354 | H20: 46204 | I20: 46934 | J20: AUD | K20: ='Rate Inputs'!E4 | L20: ='Rate Inputs'!F4 | M20: =IF(OR($P20="Ready",$P20="FY26 provisional",$P20="FY26 secured"),IF($H20<=DATE(2025,7,1),ROUNDUP($K20,-2),IF('Rate Inputs'!$J4="","",ROUNDUP(IF($H20>DATE(2026,6,30),'Rate Inputs'!$J4,'Rate Inputs'!$J4*($H20-DATE(2025,7,1))/365+$K20*(DATE(2026,6,30)-$H20+1)/365),-2))),"") | N20: =IF($P20="Ready",ROUNDUP(IFERROR($K20,0),-2),IF(OR($P20="FY26 provisional",$P20="FY26 secured"),"",0)) | O20: =IF($P20="Ready",IF('Rate Inputs'!$F4="","",ROUNDUP(IFERROR($L20,0),-2)),IF(OR($P20="FY26 provisional",$P20="FY26 secured"),"",0)) | P20: Ready
A21: 4001128707 | B21: {=_xlfn.XLOOKUP(A21,'Site Register'!A:A,'Site Register'!B:E)} | C21: Australia | D21: NSW | E21: AU Small Energy | F21: kWh | G21: 0 | H21: 46204 | I21: 46934 | J21: AUD | K21: ='Rate Inputs'!E6 | L21: ='Rate Inputs'!F6 | M21: =IF(OR($P21="Ready",$P21="FY26 provisional",$P21="FY26 secured"),IF($H21<=DATE(2025,7,1),ROUNDUP($K21,-2),IF('Rate Inputs'!$J6="","",ROUNDUP(IF($H21>DATE(2026,6,30),'Rate Inputs'!$J6,'Rate Inputs'!$J6*($H21-DATE(2025,7,1))/365+$K21*(DATE(2026,6,30)-$H21+1)/365),-2))),"") | N21: =IF($P21="Ready",ROUNDUP(IFERROR($K21,0),-2),IF(OR($P21="FY26 provisional",$P21="FY26 secured"),"",0)) | O21: =IF($P21="Ready",IF('Rate Inputs'!$F6="","",ROUNDUP(IFERROR($L21,0),-2)),IF(OR($P21="FY26 provisional",$P21="FY26 secured"),"",0)) | P21: Review required
A22: 4001174306 | B22: {=_xlfn.XLOOKUP(A22,'Site Register'!A:A,'Site Register'!B:E)} | C22: Australia | D22: NSW | E22: AU Small Energy | F22: kWh | G22: 254401 | H22: 46204 | I22: 46934 | J22: AUD | K22: ='Rate Inputs'!E8 | L22: ='Rate Inputs'!F8 | M22: =IF(OR($P22="Ready",$P22="FY26 provisional",$P22="FY26 secured"),IF($H22<=DATE(2025,7,1),ROUNDUP($K22,-2),IF('Rate Inputs'!$J8="","",ROUNDUP(IF($H22>DATE(2026,6,30),'Rate Inputs'!$J8,'Rate Inputs'!$J8*($H22-DATE(2025,7,1))/365+$K22*(DATE(2026,6,30)-$H22+1)/365),-2))),"") | N22: =IF($P22="Ready",ROUNDUP(IFERROR($K22,0),-2),IF(OR($P22="FY26 provisional",$P22="FY26 secured"),"",0)) | O22: =IF($P22="Ready",IF('Rate Inputs'!$F8="","",ROUNDUP(IFERROR($L22,0),-2)),IF(OR($P22="FY26 provisional",$P22="FY26 secured"),"",0)) | P22: Ready
A23: 4001231357 | B23: {=_xlfn.XLOOKUP(A23,'Site Register'!A:A,'Site Register'!B:E)} | C23: Australia | D23: NSW | E23: AU Small Energy | F23: kWh | G23: 30776 | H23: 46204 | I23: 46934 | J23: AUD | K23: ='Rate Inputs'!E11 | L23: ='Rate Inputs'!F11 | M23: =IF(OR($P23="Ready",$P23="FY26 provisional",$P23="FY26 secured"),IF($H23<=DATE(2025,7,1),ROUNDUP($K23,-2),IF('Rate Inputs'!$J11="","",ROUNDUP(IF($H23>DATE(2026,6,30),'Rate Inputs'!$J11,'Rate Inputs'!$J11*($H23-DATE(2025,7,1))/365+$K23*(DATE(2026,6,30)-$H23+1)/365),-2))),"") | N23: =IF($P23="Ready",ROUNDUP(IFERROR($K23,0),-2),IF(OR($P23="FY26 provisional",$P23="FY26 secured"),"",0)) | O23: =IF($P23="Ready",IF('Rate Inputs'!$F11="","",ROUNDUP(IFERROR($L23,0),-2)),IF(OR($P23="FY26 provisional",$P23="FY26 secured"),"",0)) | P23: Ready
A24: 4001277522 | B24: {=_xlfn.XLOOKUP(A24,'Site Register'!A:A,'Site Register'!B:E)} | C24: Australia | D24: NSW | E24: AU Small Energy | F24: kWh | G24: 9299 | H24: 46204 | I24: 46934 | J24: AUD | K24: ='Rate Inputs'!E12 | L24: ='Rate Inputs'!F12 | M24: =IF(OR($P24="Ready",$P24="FY26 provisional",$P24="FY26 secured"),IF($H24<=DATE(2025,7,1),ROUNDUP($K24,-2),IF('Rate Inputs'!$J12="","",ROUNDUP(IF($H24>DATE(2026,6,30),'Rate Inputs'!$J12,'Rate Inputs'!$J12*($H24-DATE(2025,7,1))/365+$K24*(DATE(2026,6,30)-$H24+1)/365),-2))),"") | N24: =IF($P24="Ready",ROUNDUP(IFERROR($K24,0),-2),IF(OR($P24="FY26 provisional",$P24="FY26 secured"),"",0)) | O24: =IF($P24="Ready",IF('Rate Inputs'!$F12="","",ROUNDUP(IFERROR($L24,0),-2)),IF(OR($P24="FY26 provisional",$P24="FY26 secured"),"",0)) | P24: Ready
A25: 4103512903 | B25: {=_xlfn.XLOOKUP(A25,'Site Register'!A:A,'Site Register'!B:E)} | C25: Australia | D25: NSW | E25: AU Small Energy | F25: kWh | G25: 15039 | H25: 46204 | I25: 46934 | J25: AUD | K25: ='Rate Inputs'!E14 | L25: ='Rate Inputs'!F14 | M25: =IF(OR($P25="Ready",$P25="FY26 provisional",$P25="FY26 secured"),IF($H25<=DATE(2025,7,1),ROUNDUP($K25,-2),IF('Rate Inputs'!$J14="","",ROUNDUP(IF($H25>DATE(2026,6,30),'Rate Inputs'!$J14,'Rate Inputs'!$J14*($H25-DATE(2025,7,1))/365+$K25*(DATE(2026,6,30)-$H25+1)/365),-2))),"") | N25: =IF($P25="Ready",ROUNDUP(IFERROR($K25,0),-2),IF(OR($P25="FY26 provisional",$P25="FY26 secured"),"",0)) | O25: =IF($P25="Ready",IF('Rate Inputs'!$F14="","",ROUNDUP(IFERROR($L25,0),-2)),IF(OR($P25="FY26 provisional",$P25="FY26 secured"),"",0)) | P25: Ready
A26: 4104037195 | B26: {=_xlfn.XLOOKUP(A26,'Site Register'!A:A,'Site Register'!B:E)} | C26: Australia | D26: NSW | E26: AU Small Energy | F26: kWh | G26: 2938 | H26: 46204 | I26: 46934 | J26: AUD | K26: ='Rate Inputs'!E33 | L26: ='Rate Inputs'!F33 | M26: =IF(OR($P26="Ready",$P26="FY26 provisional",$P26="FY26 secured"),IF($H26<=DATE(2025,7,1),ROUNDUP($K26,-2),IF('Rate Inputs'!$J33="","",ROUNDUP(IF($H26>DATE(2026,6,30),'Rate Inputs'!$J33,'Rate Inputs'!$J33*($H26-DATE(2025,7,1))/365+$K26*(DATE(2026,6,30)-$H26+1)/365),-2))),"") | N26: =IF($P26="Ready",ROUNDUP(IFERROR($K26,0),-2),IF(OR($P26="FY26 provisional",$P26="FY26 secured"),"",0)) | O26: =IF($P26="Ready",IF('Rate Inputs'!$F33="","",ROUNDUP(IFERROR($L26,0),-2)),IF(OR($P26="FY26 provisional",$P26="FY26 secured"),"",0)) | P26: Ready
A27: 4204234430 | B27: {=_xlfn.XLOOKUP(A27,'Site Register'!A:A,'Site Register'!B:E)} | C27: Australia | D27: NSW | E27: AU Small Energy | F27: kWh | G27: 16709 | H27: 46204 | I27: 46934 | J27: AUD | K27: ='Rate Inputs'!E35 | L27: ='Rate Inputs'!F35 | M27: =IF(OR($P27="Ready",$P27="FY26 provisional",$P27="FY26 secured"),IF($H27<=DATE(2025,7,1),ROUNDUP($K27,-2),IF('Rate Inputs'!$J35="","",ROUNDUP(IF($H27>DATE(2026,6,30),'Rate Inputs'!$J35,'Rate Inputs'!$J35*($H27-DATE(2025,7,1))/365+$K27*(DATE(2026,6,30)-$H27+1)/365),-2))),"") | N27: =IF($P27="Ready",ROUNDUP(IFERROR($K27,0),-2),IF(OR($P27="FY26 provisional",$P27="FY26 secured"),"",0)) | O27: =IF($P27="Ready",IF('Rate Inputs'!$F35="","",ROUNDUP(IFERROR($L27,0),-2)),IF(OR($P27="FY26 provisional",$P27="FY26 secured"),"",0)) | P27: Ready
A28: 4310027807 | B28: {=_xlfn.XLOOKUP(A28,'Site Register'!A:A,'Site Register'!B:E)} | C28: Australia | D28: NSW | E28: AU Small Energy | F28: kWh | G28: 65379 | H28: 46204 | I28: 46934 | J28: AUD | K28: ='Rate Inputs'!E36 | L28: ='Rate Inputs'!F36 | M28: =IF(OR($P28="Ready",$P28="FY26 provisional",$P28="FY26 secured"),IF($H28<=DATE(2025,7,1),ROUNDUP($K28,-2),IF('Rate Inputs'!$J36="","",ROUNDUP(IF($H28>DATE(2026,6,30),'Rate Inputs'!$J36,'Rate Inputs'!$J36*($H28-DATE(2025,7,1))/365+$K28*(DATE(2026,6,30)-$H28+1)/365),-2))),"") | N28: =IF($P28="Ready",ROUNDUP(IFERROR($K28,0),-2),IF(OR($P28="FY26 provisional",$P28="FY26 secured"),"",0)) | O28: =IF($P28="Ready",IF('Rate Inputs'!$F36="","",ROUNDUP(IFERROR($L28,0),-2)),IF(OR($P28="FY26 provisional",$P28="FY26 secured"),"",0)) | P28: Ready
A29: 4311422527 | B29: {=_xlfn.XLOOKUP(A29,'Site Register'!A:A,'Site Register'!B:E)} | C29: Australia | D29: NSW | E29: AU Small Energy | F29: kWh | G29: 33060 | H29: 46204 | I29: 46934 | J29: AUD | K29: ='Rate Inputs'!E47 | L29: ='Rate Inputs'!F47 | M29: =IF(OR($P29="Ready",$P29="FY26 provisional",$P29="FY26 secured"),IF($H29<=DATE(2025,7,1),ROUNDUP($K29,-2),IF('Rate Inputs'!$J47="","",ROUNDUP(IF($H29>DATE(2026,6,30),'Rate Inputs'!$J47,'Rate Inputs'!$J47*($H29-DATE(2025,7,1))/365+$K29*(DATE(2026,6,30)-$H29+1)/365),-2))),"") | N29: =IF($P29="Ready",ROUNDUP(IFERROR($K29,0),-2),IF(OR($P29="FY26 provisional",$P29="FY26 secured"),"",0)) | O29: =IF($P29="Ready",IF('Rate Inputs'!$F47="","",ROUNDUP(IFERROR($L29,0),-2)),IF(OR($P29="FY26 provisional",$P29="FY26 secured"),"",0)) | P29: Ready
A30: 4407159044 | B30: {=_xlfn.XLOOKUP(A30,'Site Register'!A:A,'Site Register'!B:E)} | C30: Australia | D30: NSW | E30: AU Small Energy | F30: kWh | G30: 33872 | H30: 46204 | I30: 46934 | J30: AUD | K30: ='Rate Inputs'!E48 | L30: ='Rate Inputs'!F48 | M30: =IF(OR($P30="Ready",$P30="FY26 provisional",$P30="FY26 secured"),IF($H30<=DATE(2025,7,1),ROUNDUP($K30,-2),IF('Rate Inputs'!$J48="","",ROUNDUP(IF($H30>DATE(2026,6,30),'Rate Inputs'!$J48,'Rate Inputs'!$J48*($H30-DATE(2025,7,1))/365+$K30*(DATE(2026,6,30)-$H30+1)/365),-2))),"") | N30: =IF($P30="Ready",ROUNDUP(IFERROR($K30,0),-2),IF(OR($P30="FY26 provisional",$P30="FY26 secured"),"",0)) | O30: =IF($P30="Ready",IF('Rate Inputs'!$F48="","",ROUNDUP(IFERROR($L30,0),-2)),IF(OR($P30="FY26 provisional",$P30="FY26 secured"),"",0)) | P30: Ready
A31: 3038502933 | B31: {=_xlfn.XLOOKUP(A31,'Site Register'!A:A,'Site Register'!B:E)} | C31: Australia | D31: QLD | E31: AU Small Energy | F31: kWh | G31: 38380 | H31: 46204 | I31: 46934 | J31: AUD | K31: ='Rate Inputs'!E55 | L31: ='Rate Inputs'!F55 | M31: =IF(OR($P31="Ready",$P31="FY26 provisional",$P31="FY26 secured"),IF($H31<=DATE(2025,7,1),ROUNDUP($K31,-2),IF('Rate Inputs'!$J55="","",ROUNDUP(IF($H31>DATE(2026,6,30),'Rate Inputs'!$J55,'Rate Inputs'!$J55*($H31-DATE(2025,7,1))/365+$K31*(DATE(2026,6,30)-$H31+1)/365),-2))),"") | N31: =IF($P31="Ready",ROUNDUP(IFERROR($K31,0),-2),IF(OR($P31="FY26 provisional",$P31="FY26 secured"),"",0)) | O31: =IF($P31="Ready",IF('Rate Inputs'!$F55="","",ROUNDUP(IFERROR($L31,0),-2)),IF(OR($P31="FY26 provisional",$P31="FY26 secured"),"",0)) | P31: Ready
A32: 3039040879 | B32: {=_xlfn.XLOOKUP(A32,'Site Register'!A:A,'Site Register'!B:E)} | C32: Australia | D32: QLD | E32: AU Small Energy | F32: kWh | G32: 70195 | H32: 46204 | I32: 46934 | J32: AUD | K32: ='Rate Inputs'!E56 | L32: ='Rate Inputs'!F56 | M32: =IF(OR($P32="Ready",$P32="FY26 provisional",$P32="FY26 secured"),IF($H32<=DATE(2025,7,1),ROUNDUP($K32,-2),IF('Rate Inputs'!$J56="","",ROUNDUP(IF($H32>DATE(2026,6,30),'Rate Inputs'!$J56,'Rate Inputs'!$J56*($H32-DATE(2025,7,1))/365+$K32*(DATE(2026,6,30)-$H32+1)/365),-2))),"") | N32: =IF($P32="Ready",ROUNDUP(IFERROR($K32,0),-2),IF(OR($P32="FY26 provisional",$P32="FY26 secured"),"",0)) | O32: =IF($P32="Ready",IF('Rate Inputs'!$F56="","",ROUNDUP(IFERROR($L32,0),-2)),IF(OR($P32="FY26 provisional",$P32="FY26 secured"),"",0)) | P32: Ready
A33: 3041781236 | B33: {=_xlfn.XLOOKUP(A33,'Site Register'!A:A,'Site Register'!B:E)} | C33: Australia | D33: QLD | E33: AU Small Energy | F33: kWh | G33: 53331 | H33: 46204 | I33: 46934 | J33: AUD | K33: ='Rate Inputs'!E57 | L33: ='Rate Inputs'!F57 | M33: =IF(OR($P33="Ready",$P33="FY26 provisional",$P33="FY26 secured"),IF($H33<=DATE(2025,7,1),ROUNDUP($K33,-2),IF('Rate Inputs'!$J57="","",ROUNDUP(IF($H33>DATE(2026,6,30),'Rate Inputs'!$J57,'Rate Inputs'!$J57*($H33-DATE(2025,7,1))/365+$K33*(DATE(2026,6,30)-$H33+1)/365),-2))),"") | N33: =IF($P33="Ready",ROUNDUP(IFERROR($K33,0),-2),IF(OR($P33="FY26 provisional",$P33="FY26 secured"),"",0)) | O33: =IF($P33="Ready",IF('Rate Inputs'!$F57="","",ROUNDUP(IFERROR($L33,0),-2)),IF(OR($P33="FY26 provisional",$P33="FY26 secured"),"",0)) | P33: Ready
A34: QB07736452 | B34: {=_xlfn.XLOOKUP(A34,'Site Register'!A:A,'Site Register'!B:E)} | C34: Australia | D34: QLD | E34: AU Small Energy | F34: kWh | G34: 24596 | H34: 46204 | I34: 46934 | J34: AUD | K34: ='Rate Inputs'!E72 | L34: ='Rate Inputs'!F72 | M34: =IF(OR($P34="Ready",$P34="FY26 provisional",$P34="FY26 secured"),IF($H34<=DATE(2025,7,1),ROUNDUP($K34,-2),IF('Rate Inputs'!$J72="","",ROUNDUP(IF($H34>DATE(2026,6,30),'Rate Inputs'!$J72,'Rate Inputs'!$J72*($H34-DATE(2025,7,1))/365+$K34*(DATE(2026,6,30)-$H34+1)/365),-2))),"") | N34: =IF($P34="Ready",ROUNDUP(IFERROR($K34,0),-2),IF(OR($P34="FY26 provisional",$P34="FY26 secured"),"",0)) | O34: =IF($P34="Ready",IF('Rate Inputs'!$F72="","",ROUNDUP(IFERROR($L34,0),-2)),IF(OR($P34="FY26 provisional",$P34="FY26 secured"),"",0)) | P34: Ready
A35: QB13869604 | B35: {=_xlfn.XLOOKUP(A35,'Site Register'!A:A,'Site Register'!B:E)} | C35: Australia | D35: QLD | E35: AU Small Energy | F35: kWh | G35: 16289 | H35: 46204 | I35: 46934 | J35: AUD | K35: ='Rate Inputs'!E73 | L35: ='Rate Inputs'!F73 | M35: =IF(OR($P35="Ready",$P35="FY26 provisional",$P35="FY26 secured"),IF($H35<=DATE(2025,7,1),ROUNDUP($K35,-2),IF('Rate Inputs'!$J73="","",ROUNDUP(IF($H35>DATE(2026,6,30),'Rate Inputs'!$J73,'Rate Inputs'!$J73*($H35-DATE(2025,7,1))/365+$K35*(DATE(2026,6,30)-$H35+1)/365),-2))),"") | N35: =IF($P35="Ready",ROUNDUP(IFERROR($K35,0),-2),IF(OR($P35="FY26 provisional",$P35="FY26 secured"),"",0)) | O35: =IF($P35="Ready",IF('Rate Inputs'!$F73="","",ROUNDUP(IFERROR($L35,0),-2)),IF(OR($P35="FY26 provisional",$P35="FY26 secured"),"",0)) | P35: Ready
A36: 2001130961 | B36: {=_xlfn.XLOOKUP(A36,'Site Register'!A:A,'Site Register'!B:E)} | C36: Australia | D36: SA | E36: AU Small Energy | F36: kWh | G36: 22458 | H36: 46204 | I36: 46934 | J36: AUD | K36: ='Rate Inputs'!E76 | L36: ='Rate Inputs'!F76 | M36: =IF(OR($P36="Ready",$P36="FY26 provisional",$P36="FY26 secured"),IF($H36<=DATE(2025,7,1),ROUNDUP($K36,-2),IF('Rate Inputs'!$J76="","",ROUNDUP(IF($H36>DATE(2026,6,30),'Rate Inputs'!$J76,'Rate Inputs'!$J76*($H36-DATE(2025,7,1))/365+$K36*(DATE(2026,6,30)-$H36+1)/365),-2))),"") | N36: =IF($P36="Ready",ROUNDUP(IFERROR($K36,0),-2),IF(OR($P36="FY26 provisional",$P36="FY26 secured"),"",0)) | O36: =IF($P36="Ready",IF('Rate Inputs'!$F76="","",ROUNDUP(IFERROR($L36,0),-2)),IF(OR($P36="FY26 provisional",$P36="FY26 secured"),"",0)) | P36: Ready
A37: 2001160686 | B37: {=_xlfn.XLOOKUP(A37,'Site Register'!A:A,'Site Register'!B:E)} | C37: Australia | D37: SA | E37: AU Small Energy | F37: kWh | G37: 36782 | H37: 46204 | I37: 46934 | J37: AUD | K37: ='Rate Inputs'!E77 | L37: ='Rate Inputs'!F77 | M37: =IF(OR($P37="Ready",$P37="FY26 provisional",$P37="FY26 secured"),IF($H37<=DATE(2025,7,1),ROUNDUP($K37,-2),IF('Rate Inputs'!$J77="","",ROUNDUP(IF($H37>DATE(2026,6,30),'Rate Inputs'!$J77,'Rate Inputs'!$J77*($H37-DATE(2025,7,1))/365+$K37*(DATE(2026,6,30)-$H37+1)/365),-2))),"") | N37: =IF($P37="Ready",ROUNDUP(IFERROR($K37,0),-2),IF(OR($P37="FY26 provisional",$P37="FY26 secured"),"",0)) | O37: =IF($P37="Ready",IF('Rate Inputs'!$F77="","",ROUNDUP(IFERROR($L37,0),-2)),IF(OR($P37="FY26 provisional",$P37="FY26 secured"),"",0)) | P37: Ready
A38: 2001223248 | B38: {=_xlfn.XLOOKUP(A38,'Site Register'!A:A,'Site Register'!B:E)} | C38: Australia | D38: SA | E38: AU Small Energy | F38: kWh | G38: 5840 | H38: 46204 | I38: 46934 | J38: AUD | K38: ='Rate Inputs'!E79 | L38: ='Rate Inputs'!F79 | M38: =IF(OR($P38="Ready",$P38="FY26 provisional",$P38="FY26 secured"),IF($H38<=DATE(2025,7,1),ROUNDUP($K38,-2),IF('Rate Inputs'!$J79="","",ROUNDUP(IF($H38>DATE(2026,6,30),'Rate Inputs'!$J79,'Rate Inputs'!$J79*($H38-DATE(2025,7,1))/365+$K38*(DATE(2026,6,30)-$H38+1)/365),-2))),"") | N38: =IF($P38="Ready",ROUNDUP(IFERROR($K38,0),-2),IF(OR($P38="FY26 provisional",$P38="FY26 secured"),"",0)) | O38: =IF($P38="Ready",IF('Rate Inputs'!$F79="","",ROUNDUP(IFERROR($L38,0),-2)),IF(OR($P38="FY26 provisional",$P38="FY26 secured"),"",0)) | P38: Ready
A39: 2001341166 | B39: {=_xlfn.XLOOKUP(A39,'Site Register'!A:A,'Site Register'!B:E)} | C39: Australia | D39: SA | E39: AU Small Energy | F39: kWh | G39: 3902 | H39: 46204 | I39: 46934 | J39: AUD | K39: ='Rate Inputs'!E80 | L39: ='Rate Inputs'!F80 | M39: =IF(OR($P39="Ready",$P39="FY26 provisional",$P39="FY26 secured"),IF($H39<=DATE(2025,7,1),ROUNDUP($K39,-2),IF('Rate Inputs'!$J80="","",ROUNDUP(IF($H39>DATE(2026,6,30),'Rate Inputs'!$J80,'Rate Inputs'!$J80*($H39-DATE(2025,7,1))/365+$K39*(DATE(2026,6,30)-$H39+1)/365),-2))),"") | N39: =IF($P39="Ready",ROUNDUP(IFERROR($K39,0),-2),IF(OR($P39="FY26 provisional",$P39="FY26 secured"),"",0)) | O39: =IF($P39="Ready",IF('Rate Inputs'!$F80="","",ROUNDUP(IFERROR($L39,0),-2)),IF(OR($P39="FY26 provisional",$P39="FY26 secured"),"",0)) | P39: Ready
A40: 2001341167 | B40: {=_xlfn.XLOOKUP(A40,'Site Register'!A:A,'Site Register'!B:E)} | C40: Australia | D40: SA | E40: AU Small Energy | F40: kWh | G40: 21166 | H40: 46204 | I40: 46934 | J40: AUD | K40: ='Rate Inputs'!E81 | L40: ='Rate Inputs'!F81 | M40: =IF(OR($P40="Ready",$P40="FY26 provisional",$P40="FY26 secured"),IF($H40<=DATE(2025,7,1),ROUNDUP($K40,-2),IF('Rate Inputs'!$J81="","",ROUNDUP(IF($H40>DATE(2026,6,30),'Rate Inputs'!$J81,'Rate Inputs'!$J81*($H40-DATE(2025,7,1))/365+$K40*(DATE(2026,6,30)-$H40+1)/365),-2))),"") | N40: =IF($P40="Ready",ROUNDUP(IFERROR($K40,0),-2),IF(OR($P40="FY26 provisional",$P40="FY26 secured"),"",0)) | O40: =IF($P40="Ready",IF('Rate Inputs'!$F81="","",ROUNDUP(IFERROR($L40,0),-2)),IF(OR($P40="FY26 provisional",$P40="FY26 secured"),"",0)) | P40: Ready
A41: 2001515449 | B41: {=_xlfn.XLOOKUP(A41,'Site Register'!A:A,'Site Register'!B:E)} | C41: Australia | D41: SA | E41: AU Small Energy | F41: kWh | G41: 10660 | H41: 46204 | I41: 46934 | J41: AUD | K41: ='Rate Inputs'!E82 | L41: ='Rate Inputs'!F82 | M41: =IF(OR($P41="Ready",$P41="FY26 provisional",$P41="FY26 secured"),IF($H41<=DATE(2025,7,1),ROUNDUP($K41,-2),IF('Rate Inputs'!$J82="","",ROUNDUP(IF($H41>DATE(2026,6,30),'Rate Inputs'!$J82,'Rate Inputs'!$J82*($H41-DATE(2025,7,1))/365+$K41*(DATE(2026,6,30)-$H41+1)/365),-2))),"") | N41: =IF($P41="Ready",ROUNDUP(IFERROR($K41,0),-2),IF(OR($P41="FY26 provisional",$P41="FY26 secured"),"",0)) | O41: =IF($P41="Ready",IF('Rate Inputs'!$F82="","",ROUNDUP(IFERROR($L41,0),-2)),IF(OR($P41="FY26 provisional",$P41="FY26 secured"),"",0)) | P41: Ready
A42: 2001600008 | B42: {=_xlfn.XLOOKUP(A42,'Site Register'!A:A,'Site Register'!B:E)} | C42: Australia | D42: SA | E42: AU Small Energy | F42: kWh | G42: 3495 | H42: 46204 | I42: 46934 | J42: AUD | K42: ='Rate Inputs'!E83 | L42: ='Rate Inputs'!F83 | M42: =IF(OR($P42="Ready",$P42="FY26 provisional",$P42="FY26 secured"),IF($H42<=DATE(2025,7,1),ROUNDUP($K42,-2),IF('Rate Inputs'!$J83="","",ROUNDUP(IF($H42>DATE(2026,6,30),'Rate Inputs'!$J83,'Rate Inputs'!$J83*($H42-DATE(2025,7,1))/365+$K42*(DATE(2026,6,30)-$H42+1)/365),-2))),"") | N42: =IF($P42="Ready",ROUNDUP(IFERROR($K42,0),-2),IF(OR($P42="FY26 provisional",$P42="FY26 secured"),"",0)) | O42: =IF($P42="Ready",IF('Rate Inputs'!$F83="","",ROUNDUP(IFERROR($L42,0),-2)),IF(OR($P42="FY26 provisional",$P42="FY26 secured"),"",0)) | P42: Ready
A43: 2001676115 | B43: {=_xlfn.XLOOKUP(A43,'Site Register'!A:A,'Site Register'!B:E)} | C43: Australia | D43: SA | E43: AU Small Energy | F43: kWh | G43: 28791 | H43: 46204 | I43: 46934 | J43: AUD | K43: ='Rate Inputs'!E84 | L43: ='Rate Inputs'!F84 | M43: =IF(OR($P43="Ready",$P43="FY26 provisional",$P43="FY26 secured"),IF($H43<=DATE(2025,7,1),ROUNDUP($K43,-2),IF('Rate Inputs'!$J84="","",ROUNDUP(IF($H43>DATE(2026,6,30),'Rate Inputs'!$J84,'Rate Inputs'!$J84*($H43-DATE(2025,7,1))/365+$K43*(DATE(2026,6,30)-$H43+1)/365),-2))),"") | N43: =IF($P43="Ready",ROUNDUP(IFERROR($K43,0),-2),IF(OR($P43="FY26 provisional",$P43="FY26 secured"),"",0)) | O43: =IF($P43="Ready",IF('Rate Inputs'!$F84="","",ROUNDUP(IFERROR($L43,0),-2)),IF(OR($P43="FY26 provisional",$P43="FY26 secured"),"",0)) | P43: Ready
A44: 2002190876 | B44: {=_xlfn.XLOOKUP(A44,'Site Register'!A:A,'Site Register'!B:E)} | C44: Australia | D44: SA | E44: AU Small Energy | F44: kWh | G44: 29818 | H44: 46204 | I44: 46934 | J44: AUD | K44: ='Rate Inputs'!E85 | L44: ='Rate Inputs'!F85 | M44: =IF(OR($P44="Ready",$P44="FY26 provisional",$P44="FY26 secured"),IF($H44<=DATE(2025,7,1),ROUNDUP($K44,-2),IF('Rate Inputs'!$J85="","",ROUNDUP(IF($H44>DATE(2026,6,30),'Rate Inputs'!$J85,'Rate Inputs'!$J85*($H44-DATE(2025,7,1))/365+$K44*(DATE(2026,6,30)-$H44+1)/365),-2))),"") | N44: =IF($P44="Ready",ROUNDUP(IFERROR($K44,0),-2),IF(OR($P44="FY26 provisional",$P44="FY26 secured"),"",0)) | O44: =IF($P44="Ready",IF('Rate Inputs'!$F85="","",ROUNDUP(IFERROR($L44,0),-2)),IF(OR($P44="FY26 provisional",$P44="FY26 secured"),"",0)) | P44: Ready
A45: 2002601115 | B45: {=_xlfn.XLOOKUP(A45,'Site Register'!A:A,'Site Register'!B:E)} | C45: Australia | D45: SA | E45: AU Small Energy | F45: kWh | G45: 4380 | H45: 46204 | I45: 46934 | J45: AUD | K45: ='Rate Inputs'!E87 | L45: ='Rate Inputs'!F87 | M45: =IF(OR($P45="Ready",$P45="FY26 provisional",$P45="FY26 secured"),IF($H45<=DATE(2025,7,1),ROUNDUP($K45,-2),IF('Rate Inputs'!$J87="","",ROUNDUP(IF($H45>DATE(2026,6,30),'Rate Inputs'!$J87,'Rate Inputs'!$J87*($H45-DATE(2025,7,1))/365+$K45*(DATE(2026,6,30)-$H45+1)/365),-2))),"") | N45: =IF($P45="Ready",ROUNDUP(IFERROR($K45,0),-2),IF(OR($P45="FY26 provisional",$P45="FY26 secured"),"",0)) | O45: =IF($P45="Ready",IF('Rate Inputs'!$F87="","",ROUNDUP(IFERROR($L45,0),-2)),IF(OR($P45="FY26 provisional",$P45="FY26 secured"),"",0)) | P45: Ready
A46: 6001295311 | B46: {=_xlfn.XLOOKUP(A46,'Site Register'!A:A,'Site Register'!B:E)} | C46: Australia | D46: VIC | E46: AU Small Energy | F46: kWh | G46: 22391 | H46: 46204 | I46: 46934 | J46: AUD | K46: ='Rate Inputs'!E93 | L46: ='Rate Inputs'!F93 | M46: =IF(OR($P46="Ready",$P46="FY26 provisional",$P46="FY26 secured"),IF($H46<=DATE(2025,7,1),ROUNDUP($K46,-2),IF('Rate Inputs'!$J93="","",ROUNDUP(IF($H46>DATE(2026,6,30),'Rate Inputs'!$J93,'Rate Inputs'!$J93*($H46-DATE(2025,7,1))/365+$K46*(DATE(2026,6,30)-$H46+1)/365),-2))),"") | N46: =IF($P46="Ready",ROUNDUP(IFERROR($K46,0),-2),IF(OR($P46="FY26 provisional",$P46="FY26 secured"),"",0)) | O46: =IF($P46="Ready",IF('Rate Inputs'!$F93="","",ROUNDUP(IFERROR($L46,0),-2)),IF(OR($P46="FY26 provisional",$P46="FY26 secured"),"",0)) | P46: Ready
A47: 6001399332 | B47: {=_xlfn.XLOOKUP(A47,'Site Register'!A:A,'Site Register'!B:E)} | C47: Australia | D47: VIC | E47: AU Small Energy | F47: kWh | G47: 58945 | H47: 46204 | I47: 46934 | J47: AUD | K47: ='Rate Inputs'!E95 | L47: ='Rate Inputs'!F95 | M47: =IF(OR($P47="Ready",$P47="FY26 provisional",$P47="FY26 secured"),IF($H47<=DATE(2025,7,1),ROUNDUP($K47,-2),IF('Rate Inputs'!$J95="","",ROUNDUP(IF($H47>DATE(2026,6,30),'Rate Inputs'!$J95,'Rate Inputs'!$J95*($H47-DATE(2025,7,1))/365+$K47*(DATE(2026,6,30)-$H47+1)/365),-2))),"") | N47: =IF($P47="Ready",ROUNDUP(IFERROR($K47,0),-2),IF(OR($P47="FY26 provisional",$P47="FY26 secured"),"",0)) | O47: =IF($P47="Ready",IF('Rate Inputs'!$F95="","",ROUNDUP(IFERROR($L47,0),-2)),IF(OR($P47="FY26 provisional",$P47="FY26 secured"),"",0)) | P47: Ready
A48: 6103034554 | B48: {=_xlfn.XLOOKUP(A48,'Site Register'!A:A,'Site Register'!B:E)} | C48: Australia | D48: VIC | E48: AU Small Energy | F48: kWh | G48: 30794 | H48: 46204 | I48: 46934 | J48: AUD | K48: ='Rate Inputs'!E96 | L48: ='Rate Inputs'!F96 | M48: =IF(OR($P48="Ready",$P48="FY26 provisional",$P48="FY26 secured"),IF($H48<=DATE(2025,7,1),ROUNDUP($K48,-2),IF('Rate Inputs'!$J96="","",ROUNDUP(IF($H48>DATE(2026,6,30),'Rate Inputs'!$J96,'Rate Inputs'!$J96*($H48-DATE(2025,7,1))/365+$K48*(DATE(2026,6,30)-$H48+1)/365),-2))),"") | N48: =IF($P48="Ready",ROUNDUP(IFERROR($K48,0),-2),IF(OR($P48="FY26 provisional",$P48="FY26 secured"),"",0)) | O48: =IF($P48="Ready",IF('Rate Inputs'!$F96="","",ROUNDUP(IFERROR($L48,0),-2)),IF(OR($P48="FY26 provisional",$P48="FY26 secured"),"",0)) | P48: Ready
A49: 6103034564 | B49: {=_xlfn.XLOOKUP(A49,'Site Register'!A:A,'Site Register'!B:E)} | C49: Australia | D49: VIC | E49: AU Small Energy | F49: kWh | G49: 37745 | H49: 46204 | I49: 46934 | J49: AUD | K49: ='Rate Inputs'!E97 | L49: ='Rate Inputs'!F97 | M49: =IF(OR($P49="Ready",$P49="FY26 provisional",$P49="FY26 secured"),IF($H49<=DATE(2025,7,1),ROUNDUP($K49,-2),IF('Rate Inputs'!$J97="","",ROUNDUP(IF($H49>DATE(2026,6,30),'Rate Inputs'!$J97,'Rate Inputs'!$J97*($H49-DATE(2025,7,1))/365+$K49*(DATE(2026,6,30)-$H49+1)/365),-2))),"") | N49: =IF($P49="Ready",ROUNDUP(IFERROR($K49,0),-2),IF(OR($P49="FY26 provisional",$P49="FY26 secured"),"",0)) | O49: =IF($P49="Ready",IF('Rate Inputs'!$F97="","",ROUNDUP(IFERROR($L49,0),-2)),IF(OR($P49="FY26 provisional",$P49="FY26 secured"),"",0)) | P49: Ready
A50: 6103034565 | B50: {=_xlfn.XLOOKUP(A50,'Site Register'!A:A,'Site Register'!B:E)} | C50: Australia | D50: VIC | E50: AU Small Energy | F50: kWh | G50: 56975 | H50: 46204 | I50: 46934 | J50: AUD | K50: ='Rate Inputs'!E98 | L50: ='Rate Inputs'!F98 | M50: =IF(OR($P50="Ready",$P50="FY26 provisional",$P50="FY26 secured"),IF($H50<=DATE(2025,7,1),ROUNDUP($K50,-2),IF('Rate Inputs'!$J98="","",ROUNDUP(IF($H50>DATE(2026,6,30),'Rate Inputs'!$J98,'Rate Inputs'!$J98*($H50-DATE(2025,7,1))/365+$K50*(DATE(2026,6,30)-$H50+1)/365),-2))),"") | N50: =IF($P50="Ready",ROUNDUP(IFERROR($K50,0),-2),IF(OR($P50="FY26 provisional",$P50="FY26 secured"),"",0)) | O50: =IF($P50="Ready",IF('Rate Inputs'!$F98="","",ROUNDUP(IFERROR($L50,0),-2)),IF(OR($P50="FY26 provisional",$P50="FY26 secured"),"",0)) | P50: Ready
A51: 6103066712 | B51: {=_xlfn.XLOOKUP(A51,'Site Register'!A:A,'Site Register'!B:E)} | C51: Australia | D51: VIC | E51: AU Small Energy | F51: kWh | G51: 376 | H51: 46204 | I51: 46934 | J51: AUD | K51: ='Rate Inputs'!E99 | L51: ='Rate Inputs'!F99 | M51: =IF(OR($P51="Ready",$P51="FY26 provisional",$P51="FY26 secured"),IF($H51<=DATE(2025,7,1),ROUNDUP($K51,-2),IF('Rate Inputs'!$J99="","",ROUNDUP(IF($H51>DATE(2026,6,30),'Rate Inputs'!$J99,'Rate Inputs'!$J99*($H51-DATE(2025,7,1))/365+$K51*(DATE(2026,6,30)-$H51+1)/365),-2))),"") | N51: =IF($P51="Ready",ROUNDUP(IFERROR($K51,0),-2),IF(OR($P51="FY26 provisional",$P51="FY26 secured"),"",0)) | O51: =IF($P51="Ready",IF('Rate Inputs'!$F99="","",ROUNDUP(IFERROR($L51,0),-2)),IF(OR($P51="FY26 provisional",$P51="FY26 secured"),"",0)) | P51: Ready
A52: 6203155353 | B52: {=_xlfn.XLOOKUP(A52,'Site Register'!A:A,'Site Register'!B:E)} | C52: Australia | D52: VIC | E52: AU Small Energy | F52: kWh | G52: 27942 | H52: 46204 | I52: 46934 | J52: AUD | K52: ='Rate Inputs'!E100 | L52: ='Rate Inputs'!F100 | M52: =IF(OR($P52="Ready",$P52="FY26 provisional",$P52="FY26 secured"),IF($H52<=DATE(2025,7,1),ROUNDUP($K52,-2),IF('Rate Inputs'!$J100="","",ROUNDUP(IF($H52>DATE(2026,6,30),'Rate Inputs'!$J100,'Rate Inputs'!$J100*($H52-DATE(2025,7,1))/365+$K52*(DATE(2026,6,30)-$H52+1)/365),-2))),"") | N52: =IF($P52="Ready",ROUNDUP(IFERROR($K52,0),-2),IF(OR($P52="FY26 provisional",$P52="FY26 secured"),"",0)) | O52: =IF($P52="Ready",IF('Rate Inputs'!$F100="","",ROUNDUP(IFERROR($L52,0),-2)),IF(OR($P52="FY26 provisional",$P52="FY26 secured"),"",0)) | P52: Ready
A53: 6203245874 | B53: {=_xlfn.XLOOKUP(A53,'Site Register'!A:A,'Site Register'!B:E)} | C53: Australia | D53: VIC | E53: AU Small Energy | F53: kWh | G53: 11909 | H53: 46204 | I53: 46934 | J53: AUD | K53: ='Rate Inputs'!E101 | L53: ='Rate Inputs'!F101 | M53: =IF(OR($P53="Ready",$P53="FY26 provisional",$P53="FY26 secured"),IF($H53<=DATE(2025,7,1),ROUNDUP($K53,-2),IF('Rate Inputs'!$J101="","",ROUNDUP(IF($H53>DATE(2026,6,30),'Rate Inputs'!$J101,'Rate Inputs'!$J101*($H53-DATE(2025,7,1))/365+$K53*(DATE(2026,6,30)-$H53+1)/365),-2))),"") | N53: =IF($P53="Ready",ROUNDUP(IFERROR($K53,0),-2),IF(OR($P53="FY26 provisional",$P53="FY26 secured"),"",0)) | O53: =IF($P53="Ready",IF('Rate Inputs'!$F101="","",ROUNDUP(IFERROR($L53,0),-2)),IF(OR($P53="FY26 provisional",$P53="FY26 secured"),"",0)) | P53: Ready
A54: 6203409239 | B54: {=_xlfn.XLOOKUP(A54,'Site Register'!A:A,'Site Register'!B:E)} | C54: Australia | D54: VIC | E54: AU Small Energy | F54: kWh | G54: 3824 | H54: 46204 | I54: 46934 | J54: AUD | K54: ='Rate Inputs'!E102 | L54: ='Rate Inputs'!F102 | M54: =IF(OR($P54="Ready",$P54="FY26 provisional",$P54="FY26 secured"),IF($H54<=DATE(2025,7,1),ROUNDUP($K54,-2),IF('Rate Inputs'!$J102="","",ROUNDUP(IF($H54>DATE(2026,6,30),'Rate Inputs'!$J102,'Rate Inputs'!$J102*($H54-DATE(2025,7,1))/365+$K54*(DATE(2026,6,30)-$H54+1)/365),-2))),"") | N54: =IF($P54="Ready",ROUNDUP(IFERROR($K54,0),-2),IF(OR($P54="FY26 provisional",$P54="FY26 secured"),"",0)) | O54: =IF($P54="Ready",IF('Rate Inputs'!$F102="","",ROUNDUP(IFERROR($L54,0),-2)),IF(OR($P54="FY26 provisional",$P54="FY26 secured"),"",0)) | P54: Ready
A55: 6203409240 | B55: {=_xlfn.XLOOKUP(A55,'Site Register'!A:A,'Site Register'!B:E)} | C55: Australia | D55: VIC | E55: AU Small Energy | F55: kWh | G55: 21695 | H55: 46204 | I55: 46934 | J55: AUD | K55: ='Rate Inputs'!E103 | L55: ='Rate Inputs'!F103 | M55: =IF(OR($P55="Ready",$P55="FY26 provisional",$P55="FY26 secured"),IF($H55<=DATE(2025,7,1),ROUNDUP($K55,-2),IF('Rate Inputs'!$J103="","",ROUNDUP(IF($H55>DATE(2026,6,30),'Rate Inputs'!$J103,'Rate Inputs'!$J103*($H55-DATE(2025,7,1))/365+$K55*(DATE(2026,6,30)-$H55+1)/365),-2))),"") | N55: =IF($P55="Ready",ROUNDUP(IFERROR($K55,0),-2),IF(OR($P55="FY26 provisional",$P55="FY26 secured"),"",0)) | O55: =IF($P55="Ready",IF('Rate Inputs'!$F103="","",ROUNDUP(IFERROR($L55,0),-2)),IF(OR($P55="FY26 provisional",$P55="FY26 secured"),"",0)) | P55: Ready
A56: 6203424291 | B56: {=_xlfn.XLOOKUP(A56,'Site Register'!A:A,'Site Register'!B:E)} | C56: Australia | D56: VIC | E56: AU Small Energy | F56: kWh | G56: 5946 | H56: 46204 | I56: 46934 | J56: AUD | K56: ='Rate Inputs'!E104 | L56: ='Rate Inputs'!F104 | M56: =IF(OR($P56="Ready",$P56="FY26 provisional",$P56="FY26 secured"),IF($H56<=DATE(2025,7,1),ROUNDUP($K56,-2),IF('Rate Inputs'!$J104="","",ROUNDUP(IF($H56>DATE(2026,6,30),'Rate Inputs'!$J104,'Rate Inputs'!$J104*($H56-DATE(2025,7,1))/365+$K56*(DATE(2026,6,30)-$H56+1)/365),-2))),"") | N56: =IF($P56="Ready",ROUNDUP(IFERROR($K56,0),-2),IF(OR($P56="FY26 provisional",$P56="FY26 secured"),"",0)) | O56: =IF($P56="Ready",IF('Rate Inputs'!$F104="","",ROUNDUP(IFERROR($L56,0),-2)),IF(OR($P56="FY26 provisional",$P56="FY26 secured"),"",0)) | P56: Ready
A57: 6203424292 | B57: {=_xlfn.XLOOKUP(A57,'Site Register'!A:A,'Site Register'!B:E)} | C57: Australia | D57: VIC | E57: AU Small Energy | F57: kWh | G57: 8591 | H57: 46204 | I57: 46934 | J57: AUD | K57: ='Rate Inputs'!E105 | L57: ='Rate Inputs'!F105 | M57: =IF(OR($P57="Ready",$P57="FY26 provisional",$P57="FY26 secured"),IF($H57<=DATE(2025,7,1),ROUNDUP($K57,-2),IF('Rate Inputs'!$J105="","",ROUNDUP(IF($H57>DATE(2026,6,30),'Rate Inputs'!$J105,'Rate Inputs'!$J105*($H57-DATE(2025,7,1))/365+$K57*(DATE(2026,6,30)-$H57+1)/365),-2))),"") | N57: =IF($P57="Ready",ROUNDUP(IFERROR($K57,0),-2),IF(OR($P57="FY26 provisional",$P57="FY26 secured"),"",0)) | O57: =IF($P57="Ready",IF('Rate Inputs'!$F105="","",ROUNDUP(IFERROR($L57,0),-2)),IF(OR($P57="FY26 provisional",$P57="FY26 secured"),"",0)) | P57: Ready
A58: 6203606598 | B58: {=_xlfn.XLOOKUP(A58,'Site Register'!A:A,'Site Register'!B:E)} | C58: Australia | D58: VIC | E58: AU Small Energy | F58: kWh | G58: 33744 | H58: 46204 | I58: 46934 | J58: AUD | K58: ='Rate Inputs'!E106 | L58: ='Rate Inputs'!F106 | M58: =IF(OR($P58="Ready",$P58="FY26 provisional",$P58="FY26 secured"),IF($H58<=DATE(2025,7,1),ROUNDUP($K58,-2),IF('Rate Inputs'!$J106="","",ROUNDUP(IF($H58>DATE(2026,6,30),'Rate Inputs'!$J106,'Rate Inputs'!$J106*($H58-DATE(2025,7,1))/365+$K58*(DATE(2026,6,30)-$H58+1)/365),-2))),"") | N58: =IF($P58="Ready",ROUNDUP(IFERROR($K58,0),-2),IF(OR($P58="FY26 provisional",$P58="FY26 secured"),"",0)) | O58: =IF($P58="Ready",IF('Rate Inputs'!$F106="","",ROUNDUP(IFERROR($L58,0),-2)),IF(OR($P58="FY26 provisional",$P58="FY26 secured"),"",0)) | P58: Ready
... A61: 6203723433 | B61: {=_xlfn.XLOOKUP(A61,'Site Register'!A:A,'Site Register'!B:E)} | C61: Australia | D61: VIC | E61: AU Small Energy | F61: kWh | G61: 1966 | H61: 46204 | I61: 46934 | J61: AUD | K61: ='Rate Inputs'!E109 | L61: ='Rate Inputs'!F109 | M61: =IF(OR($P61="Ready",$P61="FY26 provisional",$P61="FY26 secured"),IF($H61<=DATE(2025,7,1),ROUNDUP($K61,-2),IF('Rate Inputs'!$J109="","",ROUNDUP(IF($H61>DATE(2026,6,30),'Rate Inputs'!$J109,'Rate Inputs'!$J109*($H61-DATE(2025,7,1))/365+$K61*(DATE(2026,6,30)-$H61+1)/365),-2))),"") | N61: =IF($P61="Ready",ROUNDUP(IFERROR($K61,0),-2),IF(OR($P61="FY26 provisional",$P61="FY26 secured"),"",0)) | O61: =IF($P61="Ready",IF('Rate Inputs'!$F109="","",ROUNDUP(IFERROR($L61,0),-2)),IF(OR($P61="FY26 provisional",$P61="FY26 secured"),"",0)) | P61: Ready
A62: 6203834591 | B62: {=_xlfn.XLOOKUP(A62,'Site Register'!A:A,'Site Register'!B:E)} | C62: Australia | D62: VIC | E62: AU Small Energy | F62: kWh | G62: 14148 | H62: 46204 | I62: 46934 | J62: AUD | K62: ='Rate Inputs'!E111 | L62: ='Rate Inputs'!F111 | M62: =IF(OR($P62="Ready",$P62="FY26 provisional",$P62="FY26 secured"),IF($H62<=DATE(2025,7,1),ROUNDUP($K62,-2),IF('Rate Inputs'!$J111="","",ROUNDUP(IF($H62>DATE(2026,6,30),'Rate Inputs'!$J111,'Rate Inputs'!$J111*($H62-DATE(2025,7,1))/365+$K62*(DATE(2026,6,30)-$H62+1)/365),-2))),"") | N62: =IF($P62="Ready",ROUNDUP(IFERROR($K62,0),-2),IF(OR($P62="FY26 provisional",$P62="FY26 secured"),"",0)) | O62: =IF($P62="Ready",IF('Rate Inputs'!$F111="","",ROUNDUP(IFERROR($L62,0),-2)),IF(OR($P62="FY26 provisional",$P62="FY26 secured"),"",0)) | P62: Ready
A63: 6203842158 | B63: {=_xlfn.XLOOKUP(A63,'Site Register'!A:A,'Site Register'!B:E)} | C63: Australia | D63: VIC | E63: AU Small Energy | F63: kWh | G63: 6286 | H63: 46204 | I63: 46934 | J63: AUD | K63: ='Rate Inputs'!E112 | L63: ='Rate Inputs'!F112 | M63: =IF(OR($P63="Ready",$P63="FY26 provisional",$P63="FY26 secured"),IF($H63<=DATE(2025,7,1),ROUNDUP($K63,-2),IF('Rate Inputs'!$J112="","",ROUNDUP(IF($H63>DATE(2026,6,30),'Rate Inputs'!$J112,'Rate Inputs'!$J112*($H63-DATE(2025,7,1))/365+$K63*(DATE(2026,6,30)-$H63+1)/365),-2))),"") | N63: =IF($P63="Ready",ROUNDUP(IFERROR($K63,0),-2),IF(OR($P63="FY26 provisional",$P63="FY26 secured"),"",0)) | O63: =IF($P63="Ready",IF('Rate Inputs'!$F112="","",ROUNDUP(IFERROR($L63,0),-2)),IF(OR($P63="FY26 provisional",$P63="FY26 secured"),"",0)) | P63: Ready
A64: 6305487004 | B64: {=_xlfn.XLOOKUP(A64,'Site Register'!A:A,'Site Register'!B:E)} | C64: Australia | D64: VIC | E64: AU Small Energy | F64: kWh | G64: 11315 | H64: 46204 | I64: 46934 | J64: AUD | K64: ='Rate Inputs'!E114 | L64: ='Rate Inputs'!F114 | M64: =IF(OR($P64="Ready",$P64="FY26 provisional",$P64="FY26 secured"),IF($H64<=DATE(2025,7,1),ROUNDUP($K64,-2),IF('Rate Inputs'!$J114="","",ROUNDUP(IF($H64>DATE(2026,6,30),'Rate Inputs'!$J114,'Rate Inputs'!$J114*($H64-DATE(2025,7,1))/365+$K64*(DATE(2026,6,30)-$H64+1)/365),-2))),"") | N64: =IF($P64="Ready",ROUNDUP(IFERROR($K64,0),-2),IF(OR($P64="FY26 provisional",$P64="FY26 secured"),"",0)) | O64: =IF($P64="Ready",IF('Rate Inputs'!$F114="","",ROUNDUP(IFERROR($L64,0),-2)),IF(OR($P64="FY26 provisional",$P64="FY26 secured"),"",0)) | P64: Ready
A65: 6305812613 | B65: {=_xlfn.XLOOKUP(A65,'Site Register'!A:A,'Site Register'!B:E)} | C65: Australia | D65: VIC | E65: AU Small Energy | F65: kWh | G65: 33004 | H65: 46204 | I65: 46934 | J65: AUD | K65: ='Rate Inputs'!E115 | L65: ='Rate Inputs'!F115 | M65: =IF(OR($P65="Ready",$P65="FY26 provisional",$P65="FY26 secured"),IF($H65<=DATE(2025,7,1),ROUNDUP($K65,-2),IF('Rate Inputs'!$J115="","",ROUNDUP(IF($H65>DATE(2026,6,30),'Rate Inputs'!$J115,'Rate Inputs'!$J115*($H65-DATE(2025,7,1))/365+$K65*(DATE(2026,6,30)-$H65+1)/365),-2))),"") | N65: =IF($P65="Ready",ROUNDUP(IFERROR($K65,0),-2),IF(OR($P65="FY26 provisional",$P65="FY26 secured"),"",0)) | O65: =IF($P65="Ready",IF('Rate Inputs'!$F115="","",ROUNDUP(IFERROR($L65,0),-2)),IF(OR($P65="FY26 provisional",$P65="FY26 secured"),"",0)) | P65: Ready
A66: 6305983844 | B66: {=_xlfn.XLOOKUP(A66,'Site Register'!A:A,'Site Register'!B:E)} | C66: Australia | D66: VIC | E66: AU Small Energy | F66: kWh | G66: 18825 | H66: 46204 | I66: 46934 | J66: AUD | K66: ='Rate Inputs'!E118 | L66: ='Rate Inputs'!F118 | M66: =IF(OR($P66="Ready",$P66="FY26 provisional",$P66="FY26 secured"),IF($H66<=DATE(2025,7,1),ROUNDUP($K66,-2),IF('Rate Inputs'!$J118="","",ROUNDUP(IF($H66>DATE(2026,6,30),'Rate Inputs'!$J118,'Rate Inputs'!$J118*($H66-DATE(2025,7,1))/365+$K66*(DATE(2026,6,30)-$H66+1)/365),-2))),"") | N66: =IF($P66="Ready",ROUNDUP(IFERROR($K66,0),-2),IF(OR($P66="FY26 provisional",$P66="FY26 secured"),"",0)) | O66: =IF($P66="Ready",IF('Rate Inputs'!$F118="","",ROUNDUP(IFERROR($L66,0),-2)),IF(OR($P66="FY26 provisional",$P66="FY26 secured"),"",0)) | P66: Ready
A67: 6407387461 | B67: {=_xlfn.XLOOKUP(A67,'Site Register'!A:A,'Site Register'!B:E)} | C67: Australia | D67: VIC | E67: AU Small Energy | F67: kWh | G67: 25187 | H67: 46204 | I67: 46934 | J67: AUD | K67: ='Rate Inputs'!E121 | L67: ='Rate Inputs'!F121 | M67: =IF(OR($P67="Ready",$P67="FY26 provisional",$P67="FY26 secured"),IF($H67<=DATE(2025,7,1),ROUNDUP($K67,-2),IF('Rate Inputs'!$J121="","",ROUNDUP(IF($H67>DATE(2026,6,30),'Rate Inputs'!$J121,'Rate Inputs'!$J121*($H67-DATE(2025,7,1))/365+$K67*(DATE(2026,6,30)-$H67+1)/365),-2))),"") | N67: =IF($P67="Ready",ROUNDUP(IFERROR($K67,0),-2),IF(OR($P67="FY26 provisional",$P67="FY26 secured"),"",0)) | O67: =IF($P67="Ready",IF('Rate Inputs'!$F121="","",ROUNDUP(IFERROR($L67,0),-2)),IF(OR($P67="FY26 provisional",$P67="FY26 secured"),"",0)) | P67: Ready
A68: 6407695648 | B68: {=_xlfn.XLOOKUP(A68,'Site Register'!A:A,'Site Register'!B:E)} | C68: Australia | D68: VIC | E68: AU Small Energy | F68: kWh | G68: 13969 | H68: 46204 | I68: 46934 | J68: AUD | K68: ='Rate Inputs'!E122 | L68: ='Rate Inputs'!F122 | M68: =IF(OR($P68="Ready",$P68="FY26 provisional",$P68="FY26 secured"),IF($H68<=DATE(2025,7,1),ROUNDUP($K68,-2),IF('Rate Inputs'!$J122="","",ROUNDUP(IF($H68>DATE(2026,6,30),'Rate Inputs'!$J122,'Rate Inputs'!$J122*($H68-DATE(2025,7,1))/365+$K68*(DATE(2026,6,30)-$H68+1)/365),-2))),"") | N68: =IF($P68="Ready",ROUNDUP(IFERROR($K68,0),-2),IF(OR($P68="FY26 provisional",$P68="FY26 secured"),"",0)) | O68: =IF($P68="Ready",IF('Rate Inputs'!$F122="","",ROUNDUP(IFERROR($L68,0),-2)),IF(OR($P68="FY26 provisional",$P68="FY26 secured"),"",0)) | P68: Ready
A69: 6408293833 | B69: {=_xlfn.XLOOKUP(A69,'Site Register'!A:A,'Site Register'!B:E)} | C69: Australia | D69: VIC | E69: AU Small Energy | F69: kWh | G69: 13140 | H69: 46204 | I69: 46934 | J69: AUD | K69: ='Rate Inputs'!E124 | L69: ='Rate Inputs'!F124 | M69: =IF(OR($P69="Ready",$P69="FY26 provisional",$P69="FY26 secured"),IF($H69<=DATE(2025,7,1),ROUNDUP($K69,-2),IF('Rate Inputs'!$J124="","",ROUNDUP(IF($H69>DATE(2026,6,30),'Rate Inputs'!$J124,'Rate Inputs'!$J124*($H69-DATE(2025,7,1))/365+$K69*(DATE(2026,6,30)-$H69+1)/365),-2))),"") | N69: =IF($P69="Ready",ROUNDUP(IFERROR($K69,0),-2),IF(OR($P69="FY26 provisional",$P69="FY26 secured"),"",0)) | O69: =IF($P69="Ready",IF('Rate Inputs'!$F124="","",ROUNDUP(IFERROR($L69,0),-2)),IF(OR($P69="FY26 provisional",$P69="FY26 secured"),"",0)) | P69: Ready
A70: 5240431343 | B70: {=_xlfn.XLOOKUP(A70,'Site Register'!A:A,'Site Register'!B:E)} | C70: Australia | D70: NSW | E70: AU Small Energy | F70: MJ | G70: 1000 | H70: 46204 | I70: 46934 | J70: AUD | K70: ='Rate Inputs'!E135 | L70: ='Rate Inputs'!F135 | M70: =IF(OR($P70="Ready",$P70="FY26 provisional",$P70="FY26 secured"),IF($H70<=DATE(2025,7,1),ROUNDUP($K70,-2),IF('Rate Inputs'!$J135="","",ROUNDUP(IF($H70>DATE(2026,6,30),'Rate Inputs'!$J135,'Rate Inputs'!$J135*($H70-DATE(2025,7,1))/365+$K70*(DATE(2026,6,30)-$H70+1)/365),-2))),"") | N70: =IF($P70="Ready",ROUNDUP(IFERROR($K70,0),-2),IF(OR($P70="FY26 provisional",$P70="FY26 secured"),"",0)) | O70: =IF($P70="Ready",IF('Rate Inputs'!$F135="","",ROUNDUP(IFERROR($L70,0),-2)),IF(OR($P70="FY26 provisional",$P70="FY26 secured"),"",0)) | P70: Ready
A71: 5243917108 | B71: {=_xlfn.XLOOKUP(A71,'Site Register'!A:A,'Site Register'!B:E)} | C71: Australia | D71: NSW | E71: AU Small Energy | F71: MJ | G71: 1000 | H71: 46204 | I71: 46934 | J71: AUD | K71: ='Rate Inputs'!E137 | L71: ='Rate Inputs'!F137 | M71: =IF(OR($P71="Ready",$P71="FY26 provisional",$P71="FY26 secured"),IF($H71<=DATE(2025,7,1),ROUNDUP($K71,-2),IF('Rate Inputs'!$J137="","",ROUNDUP(IF($H71>DATE(2026,6,30),'Rate Inputs'!$J137,'Rate Inputs'!$J137*($H71-DATE(2025,7,1))/365+$K71*(DATE(2026,6,30)-$H71+1)/365),-2))),"") | N71: =IF($P71="Ready",ROUNDUP(IFERROR($K71,0),-2),IF(OR($P71="FY26 provisional",$P71="FY26 secured"),"",0)) | O71: =IF($P71="Ready",IF('Rate Inputs'!$F137="","",ROUNDUP(IFERROR($L71,0),-2)),IF(OR($P71="FY26 provisional",$P71="FY26 secured"),"",0)) | P71: Ready
A72: 5246209066 | B72: {=_xlfn.XLOOKUP(A72,'Site Register'!A:A,'Site Register'!B:E)} | C72: Australia | D72: NSW | E72: AU Small Energy | F72: MJ | G72: 1000 | H72: 46204 | I72: 46934 | J72: AUD | K72: ='Rate Inputs'!E138 | L72: ='Rate Inputs'!F138 | M72: =IF(OR($P72="Ready",$P72="FY26 provisional",$P72="FY26 secured"),IF($H72<=DATE(2025,7,1),ROUNDUP($K72,-2),IF('Rate Inputs'!$J138="","",ROUNDUP(IF($H72>DATE(2026,6,30),'Rate Inputs'!$J138,'Rate Inputs'!$J138*($H72-DATE(2025,7,1))/365+$K72*(DATE(2026,6,30)-$H72+1)/365),-2))),"") | N72: =IF($P72="Ready",ROUNDUP(IFERROR($K72,0),-2),IF(OR($P72="FY26 provisional",$P72="FY26 secured"),"",0)) | O72: =IF($P72="Ready",IF('Rate Inputs'!$F138="","",ROUNDUP(IFERROR($L72,0),-2)),IF(OR($P72="FY26 provisional",$P72="FY26 secured"),"",0)) | P72: Ready
A73: 5247058378 | B73: {=_xlfn.XLOOKUP(A73,'Site Register'!A:A,'Site Register'!B:E)} | C73: Australia | D73: NSW | E73: AU Small Energy | F73: MJ | G73: 1000 | H73: 46204 | I73: 46934 | J73: AUD | K73: ='Rate Inputs'!E139 | L73: ='Rate Inputs'!F139 | M73: =IF(OR($P73="Ready",$P73="FY26 provisional",$P73="FY26 secured"),IF($H73<=DATE(2025,7,1),ROUNDUP($K73,-2),IF('Rate Inputs'!$J139="","",ROUNDUP(IF($H73>DATE(2026,6,30),'Rate Inputs'!$J139,'Rate Inputs'!$J139*($H73-DATE(2025,7,1))/365+$K73*(DATE(2026,6,30)-$H73+1)/365),-2))),"") | N73: =IF($P73="Ready",ROUNDUP(IFERROR($K73,0),-2),IF(OR($P73="FY26 provisional",$P73="FY26 secured"),"",0)) | O73: =IF($P73="Ready",IF('Rate Inputs'!$F139="","",ROUNDUP(IFERROR($L73,0),-2)),IF(OR($P73="FY26 provisional",$P73="FY26 secured"),"",0)) | P73: Ready
A74: 5247063334 | B74: {=_xlfn.XLOOKUP(A74,'Site Register'!A:A,'Site Register'!B:E)} | C74: Australia | D74: NSW | E74: AU Small Energy | F74: MJ | G74: 1000 | H74: 46204 | I74: 46934 | J74: AUD | K74: ='Rate Inputs'!E140 | L74: ='Rate Inputs'!F140 | M74: =IF(OR($P74="Ready",$P74="FY26 provisional",$P74="FY26 secured"),IF($H74<=DATE(2025,7,1),ROUNDUP($K74,-2),IF('Rate Inputs'!$J140="","",ROUNDUP(IF($H74>DATE(2026,6,30),'Rate Inputs'!$J140,'Rate Inputs'!$J140*($H74-DATE(2025,7,1))/365+$K74*(DATE(2026,6,30)-$H74+1)/365),-2))),"") | N74: =IF($P74="Ready",ROUNDUP(IFERROR($K74,0),-2),IF(OR($P74="FY26 provisional",$P74="FY26 secured"),"",0)) | O74: =IF($P74="Ready",IF('Rate Inputs'!$F140="","",ROUNDUP(IFERROR($L74,0),-2)),IF(OR($P74="FY26 provisional",$P74="FY26 secured"),"",0)) | P74: Ready
A75: 5247072812 | B75: {=_xlfn.XLOOKUP(A75,'Site Register'!A:A,'Site Register'!B:E)} | C75: Australia | D75: NSW | E75: AU Small Energy | F75: MJ | G75: 1000 | H75: 46204 | I75: 46934 | J75: AUD | K75: ='Rate Inputs'!E142 | L75: ='Rate Inputs'!F142 | M75: =IF(OR($P75="Ready",$P75="FY26 provisional",$P75="FY26 secured"),IF($H75<=DATE(2025,7,1),ROUNDUP($K75,-2),IF('Rate Inputs'!$J142="","",ROUNDUP(IF($H75>DATE(2026,6,30),'Rate Inputs'!$J142,'Rate Inputs'!$J142*($H75-DATE(2025,7,1))/365+$K75*(DATE(2026,6,30)-$H75+1)/365),-2))),"") | N75: =IF($P75="Ready",ROUNDUP(IFERROR($K75,0),-2),IF(OR($P75="FY26 provisional",$P75="FY26 secured"),"",0)) | O75: =IF($P75="Ready",IF('Rate Inputs'!$F142="","",ROUNDUP(IFERROR($L75,0),-2)),IF(OR($P75="FY26 provisional",$P75="FY26 secured"),"",0)) | P75: Ready
A76: 5247072833 | B76: {=_xlfn.XLOOKUP(A76,'Site Register'!A:A,'Site Register'!B:E)} | C76: Australia | D76: NSW | E76: AU Small Energy | F76: MJ | G76: 1000 | H76: 46204 | I76: 46934 | J76: AUD | K76: ='Rate Inputs'!E143 | L76: ='Rate Inputs'!F143 | M76: =IF(OR($P76="Ready",$P76="FY26 provisional",$P76="FY26 secured"),IF($H76<=DATE(2025,7,1),ROUNDUP($K76,-2),IF('Rate Inputs'!$J143="","",ROUNDUP(IF($H76>DATE(2026,6,30),'Rate Inputs'!$J143,'Rate Inputs'!$J143*($H76-DATE(2025,7,1))/365+$K76*(DATE(2026,6,30)-$H76+1)/365),-2))),"") | N76: =IF($P76="Ready",ROUNDUP(IFERROR($K76,0),-2),IF(OR($P76="FY26 provisional",$P76="FY26 secured"),"",0)) | O76: =IF($P76="Ready",IF('Rate Inputs'!$F143="","",ROUNDUP(IFERROR($L76,0),-2)),IF(OR($P76="FY26 provisional",$P76="FY26 secured"),"",0)) | P76: Ready
A77: 5247074005 | B77: {=_xlfn.XLOOKUP(A77,'Site Register'!A:A,'Site Register'!B:E)} | C77: Australia | D77: NSW | E77: AU Small Energy | F77: MJ | G77: 1000 | H77: 46204 | I77: 46934 | J77: AUD | K77: ='Rate Inputs'!E144 | L77: ='Rate Inputs'!F144 | M77: =IF(OR($P77="Ready",$P77="FY26 provisional",$P77="FY26 secured"),IF($H77<=DATE(2025,7,1),ROUNDUP($K77,-2),IF('Rate Inputs'!$J144="","",ROUNDUP(IF($H77>DATE(2026,6,30),'Rate Inputs'!$J144,'Rate Inputs'!$J144*($H77-DATE(2025,7,1))/365+$K77*(DATE(2026,6,30)-$H77+1)/365),-2))),"") | N77: =IF($P77="Ready",ROUNDUP(IFERROR($K77,0),-2),IF(OR($P77="FY26 provisional",$P77="FY26 secured"),"",0)) | O77: =IF($P77="Ready",IF('Rate Inputs'!$F144="","",ROUNDUP(IFERROR($L77,0),-2)),IF(OR($P77="FY26 provisional",$P77="FY26 secured"),"",0)) | P77: Ready
A78: 5247082981 | B78: {=_xlfn.XLOOKUP(A78,'Site Register'!A:A,'Site Register'!B:E)} | C78: Australia | D78: NSW | E78: AU Small Energy | F78: MJ | G78: 1000 | H78: 46204 | I78: 46934 | J78: AUD | K78: ='Rate Inputs'!E145 | L78: ='Rate Inputs'!F145 | M78: =IF(OR($P78="Ready",$P78="FY26 provisional",$P78="FY26 secured"),IF($H78<=DATE(2025,7,1),ROUNDUP($K78,-2),IF('Rate Inputs'!$J145="","",ROUNDUP(IF($H78>DATE(2026,6,30),'Rate Inputs'!$J145,'Rate Inputs'!$J145*($H78-DATE(2025,7,1))/365+$K78*(DATE(2026,6,30)-$H78+1)/365),-2))),"") | N78: =IF($P78="Ready",ROUNDUP(IFERROR($K78,0),-2),IF(OR($P78="FY26 provisional",$P78="FY26 secured"),"",0)) | O78: =IF($P78="Ready",IF('Rate Inputs'!$F145="","",ROUNDUP(IFERROR($L78,0),-2)),IF(OR($P78="FY26 provisional",$P78="FY26 secured"),"",0)) | P78: Ready
A79: 5247083098 | B79: {=_xlfn.XLOOKUP(A79,'Site Register'!A:A,'Site Register'!B:E)} | C79: Australia | D79: NSW | E79: AU Small Energy | F79: MJ | G79: 1000 | H79: 46204 | I79: 46934 | J79: AUD | K79: ='Rate Inputs'!E146 | L79: ='Rate Inputs'!F146 | M79: =IF(OR($P79="Ready",$P79="FY26 provisional",$P79="FY26 secured"),IF($H79<=DATE(2025,7,1),ROUNDUP($K79,-2),IF('Rate Inputs'!$J146="","",ROUNDUP(IF($H79>DATE(2026,6,30),'Rate Inputs'!$J146,'Rate Inputs'!$J146*($H79-DATE(2025,7,1))/365+$K79*(DATE(2026,6,30)-$H79+1)/365),-2))),"") | N79: =IF($P79="Ready",ROUNDUP(IFERROR($K79,0),-2),IF(OR($P79="FY26 provisional",$P79="FY26 secured"),"",0)) | O79: =IF($P79="Ready",IF('Rate Inputs'!$F146="","",ROUNDUP(IFERROR($L79,0),-2)),IF(OR($P79="FY26 provisional",$P79="FY26 secured"),"",0)) | P79: Ready
A80: 5270000035 | B80: {=_xlfn.XLOOKUP(A80,'Site Register'!A:A,'Site Register'!B:E)} | C80: Australia | D80: NSW | E80: AU Small Energy | F80: MJ | G80: 0 | H80: 46204 | I80: 46934 | J80: AUD | K80: ='Rate Inputs'!E149 | L80: ='Rate Inputs'!F149 | M80: =IF(OR($P80="Ready",$P80="FY26 provisional",$P80="FY26 secured"),IF($H80<=DATE(2025,7,1),ROUNDUP($K80,-2),IF('Rate Inputs'!$J149="","",ROUNDUP(IF($H80>DATE(2026,6,30),'Rate Inputs'!$J149,'Rate Inputs'!$J149*($H80-DATE(2025,7,1))/365+$K80*(DATE(2026,6,30)-$H80+1)/365),-2))),"") | N80: =IF($P80="Ready",ROUNDUP(IFERROR($K80,0),-2),IF(OR($P80="FY26 provisional",$P80="FY26 secured"),"",0)) | O80: =IF($P80="Ready",IF('Rate Inputs'!$F149="","",ROUNDUP(IFERROR($L80,0),-2)),IF(OR($P80="FY26 provisional",$P80="FY26 secured"),"",0)) | P80: Ready
A81: 5410075384 | B81: {=_xlfn.XLOOKUP(A81,'Site Register'!A:A,'Site Register'!B:E)} | C81: Australia | D81: QLD | E81: AU Small Energy | F81: MJ | G81: 27439 | H81: 46204 | I81: 46934 | J81: AUD | K81: ='Rate Inputs'!E150 | L81: ='Rate Inputs'!F150 | M81: =IF(OR($P81="Ready",$P81="FY26 provisional",$P81="FY26 secured"),IF($H81<=DATE(2025,7,1),ROUNDUP($K81,-2),IF('Rate Inputs'!$J150="","",ROUNDUP(IF($H81>DATE(2026,6,30),'Rate Inputs'!$J150,'Rate Inputs'!$J150*($H81-DATE(2025,7,1))/365+$K81*(DATE(2026,6,30)-$H81+1)/365),-2))),"") | N81: =IF($P81="Ready",ROUNDUP(IFERROR($K81,0),-2),IF(OR($P81="FY26 provisional",$P81="FY26 secured"),"",0)) | O81: =IF($P81="Ready",IF('Rate Inputs'!$F150="","",ROUNDUP(IFERROR($L81,0),-2)),IF(OR($P81="FY26 provisional",$P81="FY26 secured"),"",0)) | P81: Ready
A82: 5410078053 | B82: {=_xlfn.XLOOKUP(A82,'Site Register'!A:A,'Site Register'!B:E)} | C82: Australia | D82: QLD | E82: AU Small Energy | F82: MJ | G82: 153318 | H82: 46204 | I82: 46934 | J82: AUD | K82: ='Rate Inputs'!E151 | L82: ='Rate Inputs'!F151 | M82: =IF(OR($P82="Ready",$P82="FY26 provisional",$P82="FY26 secured"),IF($H82<=DATE(2025,7,1),ROUNDUP($K82,-2),IF('Rate Inputs'!$J151="","",ROUNDUP(IF($H82>DATE(2026,6,30),'Rate Inputs'!$J151,'Rate Inputs'!$J151*($H82-DATE(2025,7,1))/365+$K82*(DATE(2026,6,30)-$H82+1)/365),-2))),"") | N82: =IF($P82="Ready",ROUNDUP(IFERROR($K82,0),-2),IF(OR($P82="FY26 provisional",$P82="FY26 secured"),"",0)) | O82: =IF($P82="Ready",IF('Rate Inputs'!$F151="","",ROUNDUP(IFERROR($L82,0),-2)),IF(OR($P82="FY26 provisional",$P82="FY26 secured"),"",0)) | P82: Ready
A83: 5410086500 | B83: {=_xlfn.XLOOKUP(A83,'Site Register'!A:A,'Site Register'!B:E)} | C83: Australia | D83: QLD | E83: AU Small Energy | F83: MJ | G83: 504905 | H83: 46204 | I83: 46934 | J83: AUD | K83: ='Rate Inputs'!E152 | L83: ='Rate Inputs'!F152 | M83: =IF(OR($P83="Ready",$P83="FY26 provisional",$P83="FY26 secured"),IF($H83<=DATE(2025,7,1),ROUNDUP($K83,-2),IF('Rate Inputs'!$J152="","",ROUNDUP(IF($H83>DATE(2026,6,30),'Rate Inputs'!$J152,'Rate Inputs'!$J152*($H83-DATE(2025,7,1))/365+$K83*(DATE(2026,6,30)-$H83+1)/365),-2))),"") | N83: =IF($P83="Ready",ROUNDUP(IFERROR($K83,0),-2),IF(OR($P83="FY26 provisional",$P83="FY26 secured"),"",0)) | O83: =IF($P83="Ready",IF('Rate Inputs'!$F152="","",ROUNDUP(IFERROR($L83,0),-2)),IF(OR($P83="FY26 provisional",$P83="FY26 secured"),"",0)) | P83: Ready
A84: 5420000032 | B84: {=_xlfn.XLOOKUP(A84,'Site Register'!A:A,'Site Register'!B:E)} | C84: Australia | D84: QLD | E84: AU Small Energy | F84: MJ | G84: 888078 | H84: 46204 | I84: 46934 | J84: AUD | K84: ='Rate Inputs'!E153 | L84: ='Rate Inputs'!F153 | M84: =IF(OR($P84="Ready",$P84="FY26 provisional",$P84="FY26 secured"),IF($H84<=DATE(2025,7,1),ROUNDUP($K84,-2),IF('Rate Inputs'!$J153="","",ROUNDUP(IF($H84>DATE(2026,6,30),'Rate Inputs'!$J153,'Rate Inputs'!$J153*($H84-DATE(2025,7,1))/365+$K84*(DATE(2026,6,30)-$H84+1)/365),-2))),"") | N84: =IF($P84="Ready",ROUNDUP(IFERROR($K84,0),-2),IF(OR($P84="FY26 provisional",$P84="FY26 secured"),"",0)) | O84: =IF($P84="Ready",IF('Rate Inputs'!$F153="","",ROUNDUP(IFERROR($L84,0),-2)),IF(OR($P84="FY26 provisional",$P84="FY26 secured"),"",0)) | P84: Ready
A85: 5510484999 | B85: {=_xlfn.XLOOKUP(A85,'Site Register'!A:A,'Site Register'!B:E)} | C85: Australia | D85: SA | E85: AU Small Energy | F85: MJ | G85: 766606 | H85: 46204 | I85: 46934 | J85: AUD | K85: ='Rate Inputs'!E155 | L85: ='Rate Inputs'!F155 | M85: =IF(OR($P85="Ready",$P85="FY26 provisional",$P85="FY26 secured"),IF($H85<=DATE(2025,7,1),ROUNDUP($K85,-2),IF('Rate Inputs'!$J155="","",ROUNDUP(IF($H85>DATE(2026,6,30),'Rate Inputs'!$J155,'Rate Inputs'!$J155*($H85-DATE(2025,7,1))/365+$K85*(DATE(2026,6,30)-$H85+1)/365),-2))),"") | N85: =IF($P85="Ready",ROUNDUP(IFERROR($K85,0),-2),IF(OR($P85="FY26 provisional",$P85="FY26 secured"),"",0)) | O85: =IF($P85="Ready",IF('Rate Inputs'!$F155="","",ROUNDUP(IFERROR($L85,0),-2)),IF(OR($P85="FY26 provisional",$P85="FY26 secured"),"",0)) | P85: Ready
A86: 5321918308 | B86: {=_xlfn.XLOOKUP(A86,'Site Register'!A:A,'Site Register'!B:E)} | C86: Australia | D86: VIC | E86: AU Small Energy | F86: MJ | G86: 0 | H86: 46204 | I86: 46934 | J86: AUD | K86: ='Rate Inputs'!E160 | L86: ='Rate Inputs'!F160 | M86: =IF(OR($P86="Ready",$P86="FY26 provisional",$P86="FY26 secured"),IF($H86<=DATE(2025,7,1),ROUNDUP($K86,-2),IF('Rate Inputs'!$J160="","",ROUNDUP(IF($H86>DATE(2026,6,30),'Rate Inputs'!$J160,'Rate Inputs'!$J160*($H86-DATE(2025,7,1))/365+$K86*(DATE(2026,6,30)-$H86+1)/365),-2))),"") | N86: =IF($P86="Ready",ROUNDUP(IFERROR($K86,0),-2),IF(OR($P86="FY26 provisional",$P86="FY26 secured"),"",0)) | O86: =IF($P86="Ready",IF('Rate Inputs'!$F160="","",ROUNDUP(IFERROR($L86,0),-2)),IF(OR($P86="FY26 provisional",$P86="FY26 secured"),"",0)) | P86: Ready
A87: 7001184714 | B87: {=_xlfn.XLOOKUP(A87,'Site Register'!A:A,'Site Register'!B:E)} | C87: Australia | D87: ACT | E87: AU Large Electricity | F87: kWh | G87: 928827.68 | H87: 46204 | I87: 46934 | J87: AUD | K87: ='Rate Inputs'!E3 | L87: ='Rate Inputs'!F3 | M87: =IF(OR($P87="Ready",$P87="FY26 provisional",$P87="FY26 secured"),IF($H87<=DATE(2025,7,1),ROUNDUP($K87,-2),IF('Rate Inputs'!$J3="","",ROUNDUP(IF($H87>DATE(2026,6,30),'Rate Inputs'!$J3,'Rate Inputs'!$J3*($H87-DATE(2025,7,1))/365+$K87*(DATE(2026,6,30)-$H87+1)/365),-2))),"") | N87: =IF($P87="Ready",ROUNDUP(IFERROR($K87,0),-2),IF(OR($P87="FY26 provisional",$P87="FY26 secured"),"",0)) | O87: =IF($P87="Ready",IF('Rate Inputs'!$F3="","",ROUNDUP(IFERROR($L87,0),-2)),IF(OR($P87="FY26 provisional",$P87="FY26 secured"),"",0)) | P87: Ready
A88: 4001127731 | B88: {=_xlfn.XLOOKUP(A88,'Site Register'!A:A,'Site Register'!B:E)} | C88: Australia | D88: NSW | E88: AU Large Electricity | F88: kWh | G88: 44278.31 | H88: 46204 | I88: 46934 | J88: AUD | K88: ='Rate Inputs'!E5 | L88: ='Rate Inputs'!F5 | M88: =IF(OR($P88="Ready",$P88="FY26 provisional",$P88="FY26 secured"),IF($H88<=DATE(2025,7,1),ROUNDUP($K88,-2),IF('Rate Inputs'!$J5="","",ROUNDUP(IF($H88>DATE(2026,6,30),'Rate Inputs'!$J5,'Rate Inputs'!$J5*($H88-DATE(2025,7,1))/365+$K88*(DATE(2026,6,30)-$H88+1)/365),-2))),"") | N88: =IF($P88="Ready",ROUNDUP(IFERROR($K88,0),-2),IF(OR($P88="FY26 provisional",$P88="FY26 secured"),"",0)) | O88: =IF($P88="Ready",IF('Rate Inputs'!$F5="","",ROUNDUP(IFERROR($L88,0),-2)),IF(OR($P88="FY26 provisional",$P88="FY26 secured"),"",0)) | P88: Ready
A89: 4001158058 | B89: {=_xlfn.XLOOKUP(A89,'Site Register'!A:A,'Site Register'!B:E)} | C89: Australia | D89: NSW | E89: AU Large Electricity | F89: kWh | G89: 0 | H89: 46204 | I89: 46934 | J89: AUD | K89: ='Rate Inputs'!E7 | L89: ='Rate Inputs'!F7 | M89: =IF(OR($P89="Ready",$P89="FY26 provisional",$P89="FY26 secured"),IF($H89<=DATE(2025,7,1),ROUNDUP($K89,-2),IF('Rate Inputs'!$J7="","",ROUNDUP(IF($H89>DATE(2026,6,30),'Rate Inputs'!$J7,'Rate Inputs'!$J7*($H89-DATE(2025,7,1))/365+$K89*(DATE(2026,6,30)-$H89+1)/365),-2))),"") | N89: =IF($P89="Ready",ROUNDUP(IFERROR($K89,0),-2),IF(OR($P89="FY26 provisional",$P89="FY26 secured"),"",0)) | O89: =IF($P89="Ready",IF('Rate Inputs'!$F7="","",ROUNDUP(IFERROR($L89,0),-2)),IF(OR($P89="FY26 provisional",$P89="FY26 secured"),"",0)) | P89: Review required
A90: 4001198085 | B90: {=_xlfn.XLOOKUP(A90,'Site Register'!A:A,'Site Register'!B:E)} | C90: Australia | D90: NSW | E90: AU Large Electricity | F90: kWh | G90: 399092.86 | H90: 46204 | I90: 46934 | J90: AUD | K90: ='Rate Inputs'!E9 | L90: ='Rate Inputs'!F9 | M90: =IF(OR($P90="Ready",$P90="FY26 provisional",$P90="FY26 secured"),IF($H90<=DATE(2025,7,1),ROUNDUP($K90,-2),IF('Rate Inputs'!$J9="","",ROUNDUP(IF($H90>DATE(2026,6,30),'Rate Inputs'!$J9,'Rate Inputs'!$J9*($H90-DATE(2025,7,1))/365+$K90*(DATE(2026,6,30)-$H90+1)/365),-2))),"") | N90: =IF($P90="Ready",ROUNDUP(IFERROR($K90,0),-2),IF(OR($P90="FY26 provisional",$P90="FY26 secured"),"",0)) | O90: =IF($P90="Ready",IF('Rate Inputs'!$F9="","",ROUNDUP(IFERROR($L90,0),-2)),IF(OR($P90="FY26 provisional",$P90="FY26 secured"),"",0)) | P90: Ready
A91: 4001200751 | B91: {=_xlfn.XLOOKUP(A91,'Site Register'!A:A,'Site Register'!B:E)} | C91: Australia | D91: NSW | E91: AU Large Electricity | F91: kWh | G91: 10268532 | H91: 46204 | I91: 46934 | J91: AUD | K91: ='Rate Inputs'!E10 | L91: ='Rate Inputs'!F10 | M91: =IF(OR($P91="Ready",$P91="FY26 provisional",$P91="FY26 secured"),IF($H91<=DATE(2025,7,1),ROUNDUP($K91,-2),IF('Rate Inputs'!$J10="","",ROUNDUP(IF($H91>DATE(2026,6,30),'Rate Inputs'!$J10,'Rate Inputs'!$J10*($H91-DATE(2025,7,1))/365+$K91*(DATE(2026,6,30)-$H91+1)/365),-2))),"") | N91: =IF($P91="Ready",ROUNDUP(IFERROR($K91,0),-2),IF(OR($P91="FY26 provisional",$P91="FY26 secured"),"",0)) | O91: =IF($P91="Ready",IF('Rate Inputs'!$F10="","",ROUNDUP(IFERROR($L91,0),-2)),IF(OR($P91="FY26 provisional",$P91="FY26 secured"),"",0)) | P91: Ready
A92: 4001287259 | B92: {=_xlfn.XLOOKUP(A92,'Site Register'!A:A,'Site Register'!B:E)} | C92: Australia | D92: NSW | E92: AU Large Electricity | F92: kWh | G92: 171810.51 | H92: 46204 | I92: 46934 | J92: AUD | K92: ='Rate Inputs'!E13 | L92: ='Rate Inputs'!F13 | M92: =IF(OR($P92="Ready",$P92="FY26 provisional",$P92="FY26 secured"),IF($H92<=DATE(2025,7,1),ROUNDUP($K92,-2),IF('Rate Inputs'!$J13="","",ROUNDUP(IF($H92>DATE(2026,6,30),'Rate Inputs'!$J13,'Rate Inputs'!$J13*($H92-DATE(2025,7,1))/365+$K92*(DATE(2026,6,30)-$H92+1)/365),-2))),"") | N92: =IF($P92="Ready",ROUNDUP(IFERROR($K92,0),-2),IF(OR($P92="FY26 provisional",$P92="FY26 secured"),"",0)) | O92: =IF($P92="Ready",IF('Rate Inputs'!$F13="","",ROUNDUP(IFERROR($L92,0),-2)),IF(OR($P92="FY26 provisional",$P92="FY26 secured"),"",0)) | P92: Ready
A93: 4103689689 | B93: {=_xlfn.XLOOKUP(A93,'Site Register'!A:A,'Site Register'!B:E)} | C93: Australia | D93: NSW | E93: AU Large Electricity | F93: kWh | G93: 143552.12 | H93: 46204 | I93: 46934 | J93: AUD | K93: ='Rate Inputs'!E15 | L93: ='Rate Inputs'!F15 | M93: =IF(OR($P93="Ready",$P93="FY26 provisional",$P93="FY26 secured"),IF($H93<=DATE(2025,7,1),ROUNDUP($K93,-2),IF('Rate Inputs'!$J15="","",ROUNDUP(IF($H93>DATE(2026,6,30),'Rate Inputs'!$J15,'Rate Inputs'!$J15*($H93-DATE(2025,7,1))/365+$K93*(DATE(2026,6,30)-$H93+1)/365),-2))),"") | N93: =IF($P93="Ready",ROUNDUP(IFERROR($K93,0),-2),IF(OR($P93="FY26 provisional",$P93="FY26 secured"),"",0)) | O93: =IF($P93="Ready",IF('Rate Inputs'!$F15="","",ROUNDUP(IFERROR($L93,0),-2)),IF(OR($P93="FY26 provisional",$P93="FY26 secured"),"",0)) | P93: Ready
A94: 4103705443 | B94: {=_xlfn.XLOOKUP(A94,'Site Register'!A:A,'Site Register'!B:E)} | C94: Australia | D94: NSW | E94: AU Large Electricity | F94: kWh | G94: 106397.96 | H94: 46204 | I94: 46934 | J94: AUD | K94: ='Rate Inputs'!E16 | L94: ='Rate Inputs'!F16 | M94: =IF(OR($P94="Ready",$P94="FY26 provisional",$P94="FY26 secured"),IF($H94<=DATE(2025,7,1),ROUNDUP($K94,-2),IF('Rate Inputs'!$J16="","",ROUNDUP(IF($H94>DATE(2026,6,30),'Rate Inputs'!$J16,'Rate Inputs'!$J16*($H94-DATE(2025,7,1))/365+$K94*(DATE(2026,6,30)-$H94+1)/365),-2))),"") | N94: =IF($P94="Ready",ROUNDUP(IFERROR($K94,0),-2),IF(OR($P94="FY26 provisional",$P94="FY26 secured"),"",0)) | O94: =IF($P94="Ready",IF('Rate Inputs'!$F16="","",ROUNDUP(IFERROR($L94,0),-2)),IF(OR($P94="FY26 provisional",$P94="FY26 secured"),"",0)) | P94: Ready
A95: 4103711576 | B95: {=_xlfn.XLOOKUP(A95,'Site Register'!A:A,'Site Register'!B:E)} | C95: Australia | D95: NSW | E95: AU Large Electricity | F95: kWh | G95: 2405011.6 | H95: 46204 | I95: 46934 | J95: AUD | K95: ='Rate Inputs'!E17 | L95: ='Rate Inputs'!F17 | M95: =IF(OR($P95="Ready",$P95="FY26 provisional",$P95="FY26 secured"),IF($H95<=DATE(2025,7,1),ROUNDUP($K95,-2),IF('Rate Inputs'!$J17="","",ROUNDUP(IF($H95>DATE(2026,6,30),'Rate Inputs'!$J17,'Rate Inputs'!$J17*($H95-DATE(2025,7,1))/365+$K95*(DATE(2026,6,30)-$H95+1)/365),-2))),"") | N95: =IF($P95="Ready",ROUNDUP(IFERROR($K95,0),-2),IF(OR($P95="FY26 provisional",$P95="FY26 secured"),"",0)) | O95: =IF($P95="Ready",IF('Rate Inputs'!$F17="","",ROUNDUP(IFERROR($L95,0),-2)),IF(OR($P95="FY26 provisional",$P95="FY26 secured"),"",0)) | P95: Ready
A96: 4103713125 | B96: {=_xlfn.XLOOKUP(A96,'Site Register'!A:A,'Site Register'!B:E)} | C96: Australia | D96: NSW | E96: AU Large Electricity | F96: kWh | G96: 1251891.6 | H96: 46204 | I96: 46934 | J96: AUD | K96: ='Rate Inputs'!E18 | L96: ='Rate Inputs'!F18 | M96: =IF(OR($P96="Ready",$P96="FY26 provisional",$P96="FY26 secured"),IF($H96<=DATE(2025,7,1),ROUNDUP($K96,-2),IF('Rate Inputs'!$J18="","",ROUNDUP(IF($H96>DATE(2026,6,30),'Rate Inputs'!$J18,'Rate Inputs'!$J18*($H96-DATE(2025,7,1))/365+$K96*(DATE(2026,6,30)-$H96+1)/365),-2))),"") | N96: =IF($P96="Ready",ROUNDUP(IFERROR($K96,0),-2),IF(OR($P96="FY26 provisional",$P96="FY26 secured"),"",0)) | O96: =IF($P96="Ready",IF('Rate Inputs'!$F18="","",ROUNDUP(IFERROR($L96,0),-2)),IF(OR($P96="FY26 provisional",$P96="FY26 secured"),"",0)) | P96: Ready
A97: 4103737079 | B97: {=_xlfn.XLOOKUP(A97,'Site Register'!A:A,'Site Register'!B:E)} | C97: Australia | D97: NSW | E97: AU Large Electricity | F97: kWh | G97: 19241.4 | H97: 46204 | I97: 46934 | J97: AUD | K97: ='Rate Inputs'!E19 | L97: ='Rate Inputs'!F19 | M97: =IF(OR($P97="Ready",$P97="FY26 provisional",$P97="FY26 secured"),IF($H97<=DATE(2025,7,1),ROUNDUP($K97,-2),IF('Rate Inputs'!$J19="","",ROUNDUP(IF($H97>DATE(2026,6,30),'Rate Inputs'!$J19,'Rate Inputs'!$J19*($H97-DATE(2025,7,1))/365+$K97*(DATE(2026,6,30)-$H97+1)/365),-2))),"") | N97: =IF($P97="Ready",ROUNDUP(IFERROR($K97,0),-2),IF(OR($P97="FY26 provisional",$P97="FY26 secured"),"",0)) | O97: =IF($P97="Ready",IF('Rate Inputs'!$F19="","",ROUNDUP(IFERROR($L97,0),-2)),IF(OR($P97="FY26 provisional",$P97="FY26 secured"),"",0)) | P97: Ready
A98: 4103737729 | B98: {=_xlfn.XLOOKUP(A98,'Site Register'!A:A,'Site Register'!B:E)} | C98: Australia | D98: NSW | E98: AU Large Electricity | F98: kWh | G98: 13618.63 | H98: 46204 | I98: 46934 | J98: AUD | K98: ='Rate Inputs'!E20 | L98: ='Rate Inputs'!F20 | M98: =IF(OR($P98="Ready",$P98="FY26 provisional",$P98="FY26 secured"),IF($H98<=DATE(2025,7,1),ROUNDUP($K98,-2),IF('Rate Inputs'!$J20="","",ROUNDUP(IF($H98>DATE(2026,6,30),'Rate Inputs'!$J20,'Rate Inputs'!$J20*($H98-DATE(2025,7,1))/365+$K98*(DATE(2026,6,30)-$H98+1)/365),-2))),"") | N98: =IF($P98="Ready",ROUNDUP(IFERROR($K98,0),-2),IF(OR($P98="FY26 provisional",$P98="FY26 secured"),"",0)) | O98: =IF($P98="Ready",IF('Rate Inputs'!$F20="","",ROUNDUP(IFERROR($L98,0),-2)),IF(OR($P98="FY26 provisional",$P98="FY26 secured"),"",0)) | P98: Ready
A99: 4103742938 | B99: {=_xlfn.XLOOKUP(A99,'Site Register'!A:A,'Site Register'!B:E)} | C99: Australia | D99: NSW | E99: AU Large Electricity | F99: kWh | G99: 105623.45 | H99: 46204 | I99: 46934 | J99: AUD | K99: ='Rate Inputs'!E21 | L99: ='Rate Inputs'!F21 | M99: =IF(OR($P99="Ready",$P99="FY26 provisional",$P99="FY26 secured"),IF($H99<=DATE(2025,7,1),ROUNDUP($K99,-2),IF('Rate Inputs'!$J21="","",ROUNDUP(IF($H99>DATE(2026,6,30),'Rate Inputs'!$J21,'Rate Inputs'!$J21*($H99-DATE(2025,7,1))/365+$K99*(DATE(2026,6,30)-$H99+1)/365),-2))),"") | N99: =IF($P99="Ready",ROUNDUP(IFERROR($K99,0),-2),IF(OR($P99="FY26 provisional",$P99="FY26 secured"),"",0)) | O99: =IF($P99="Ready",IF('Rate Inputs'!$F21="","",ROUNDUP(IFERROR($L99,0),-2)),IF(OR($P99="FY26 provisional",$P99="FY26 secured"),"",0)) | P99: Ready
A100: 4103742939 | B100: {=_xlfn.XLOOKUP(A100,'Site Register'!A:A,'Site Register'!B:E)} | C100: Australia | D100: NSW | E100: AU Large Electricity | F100: kWh | G100: 81857.8 | H100: 46204 | I100: 46934 | J100: AUD | K100: ='Rate Inputs'!E22 | L100: ='Rate Inputs'!F22 | M100: =IF(OR($P100="Ready",$P100="FY26 provisional",$P100="FY26 secured"),IF($H100<=DATE(2025,7,1),ROUNDUP($K100,-2),IF('Rate Inputs'!$J22="","",ROUNDUP(IF($H100>DATE(2026,6,30),'Rate Inputs'!$J22,'Rate Inputs'!$J22*($H100-DATE(2025,7,1))/365+$K100*(DATE(2026,6,30)-$H100+1)/365),-2))),"") | N100: =IF($P100="Ready",ROUNDUP(IFERROR($K100,0),-2),IF(OR($P100="FY26 provisional",$P100="FY26 secured"),"",0)) | O100: =IF($P100="Ready",IF('Rate Inputs'!$F22="","",ROUNDUP(IFERROR($L100,0),-2)),IF(OR($P100="FY26 provisional",$P100="FY26 secured"),"",0)) | P100: Ready
A101: 4103742940 | B101: {=_xlfn.XLOOKUP(A101,'Site Register'!A:A,'Site Register'!B:E)} | C101: Australia | D101: NSW | E101: AU Large Electricity | F101: kWh | G101: 90701.86 | H101: 46204 | I101: 46934 | J101: AUD | K101: ='Rate Inputs'!E23 | L101: ='Rate Inputs'!F23 | M101: =IF(OR($P101="Ready",$P101="FY26 provisional",$P101="FY26 secured"),IF($H101<=DATE(2025,7,1),ROUNDUP($K101,-2),IF('Rate Inputs'!$J23="","",ROUNDUP(IF($H101>DATE(2026,6,30),'Rate Inputs'!$J23,'Rate Inputs'!$J23*($H101-DATE(2025,7,1))/365+$K101*(DATE(2026,6,30)-$H101+1)/365),-2))),"") | N101: =IF($P101="Ready",ROUNDUP(IFERROR($K101,0),-2),IF(OR($P101="FY26 provisional",$P101="FY26 secured"),"",0)) | O101: =IF($P101="Ready",IF('Rate Inputs'!$F23="","",ROUNDUP(IFERROR($L101,0),-2)),IF(OR($P101="FY26 provisional",$P101="FY26 secured"),"",0)) | P101: Ready
A102: 4103759848 | B102: {=_xlfn.XLOOKUP(A102,'Site Register'!A:A,'Site Register'!B:E)} | C102: Australia | D102: NSW | E102: AU Large Electricity | F102: kWh | G102: 102767.91 | H102: 46204 | I102: 46934 | J102: AUD | K102: ='Rate Inputs'!E24 | L102: ='Rate Inputs'!F24 | M102: =IF(OR($P102="Ready",$P102="FY26 provisional",$P102="FY26 secured"),IF($H102<=DATE(2025,7,1),ROUNDUP($K102,-2),IF('Rate Inputs'!$J24="","",ROUNDUP(IF($H102>DATE(2026,6,30),'Rate Inputs'!$J24,'Rate Inputs'!$J24*($H102-DATE(2025,7,1))/365+$K102*(DATE(2026,6,30)-$H102+1)/365),-2))),"") | N102: =IF($P102="Ready",ROUNDUP(IFERROR($K102,0),-2),IF(OR($P102="FY26 provisional",$P102="FY26 secured"),"",0)) | O102: =IF($P102="Ready",IF('Rate Inputs'!$F24="","",ROUNDUP(IFERROR($L102,0),-2)),IF(OR($P102="FY26 provisional",$P102="FY26 secured"),"",0)) | P102: Ready
...

Sheet Rate Inputs
A1: Budget Inputs – formula links to raw schedules and source analysis
A2: Connection ID | B2: Contracted Retailer | C2: Units | D2: Annual Consumption | E2: Annual Spend Input (current term) | F2: Renewal / FY28 Annual Input | G2: FY27 Blended Rate (audit only) | H2: FY28 Blended Rate (audit only) | I2: Budget Status | J2: Current Annual Spend (reference) | K2: Source Annual Total (fallback) | L2: Renewal Source Total (fallback)
A3: 7001184714 | B3: =_xlfn.XLOOKUP(A3,'Budget FY26-28'!A:A,'Site Register'!M:M) | C3: kWh | D3: 928827.68 | E3: =SUMIFS('Rates & Source Data'!$AO$33:$AO$100,'Rates & Source Data'!$A$33:$A$100,$A3) | F3: =SUMIFS('Rates & Source Data'!$AR$33:$AR$100,'Rates & Source Data'!$A$33:$A$100,$A3) | G3: 0.11532858 | H3: 0.1137053 | I3: Ready | J3: 238460.94 | K3: 107120.38 | L3: 105612.63
A4: 4001050448 | B4: =_xlfn.XLOOKUP(A4,'Budget FY26-28'!A:A,'Site Register'!M:M) | C4: kWh | D4: 28354 | E4: =IFERROR(IF(SUMIFS('Rates & Source Data'!$BM$106:$BM$156,'Rates & Source Data'!$C$106:$C$156,$A4,'Rates & Source Data'!$A$106:$A$156,$B4)<>0,SUMIFS('Rates & Source Data'!$BM$106:$BM$156,'Rates & Source Data'!$C$106:$C$156,$A4,'Rates & Source Data'!$A$106:$A$156,$B4),$K4),$K4) | F4: =E4 | G4: 0.31082427 | H4: 0.31082427 | I4: Ready | J4: 11190.412 | K4: 8813.1113 | L4: 8813.1113
A5: 4001127731 | B5: =_xlfn.XLOOKUP(A5,'Budget FY26-28'!A:A,'Site Register'!M:M) | C5: kWh | D5: 44278.31 | E5: =SUMIFS('Rates & Source Data'!$AO$33:$AO$100,'Rates & Source Data'!$A$33:$A$100,$A5) | F5: =SUMIFS('Rates & Source Data'!$AR$33:$AR$100,'Rates & Source Data'!$A$33:$A$100,$A5) | G5: 0.12105105 | H5: 0.11998768 | I5: Ready | J5: 22410.436 | K5: 5359.936 | L5: 5312.8518
A6: 4001128707 | B6: =_xlfn.XLOOKUP(A6,'Budget FY26-28'!A:A,'Site Register'!M:M) | C6: kWh | D6: 0 | E6: =IFERROR(IF(SUMIFS('Rates & Source Data'!$BM$106:$BM$156,'Rates & Source Data'!$C$106:$C$156,$A6,'Rates & Source Data'!$A$106:$A$156,$B6)<>0,SUMIFS('Rates & Source Data'!$BM$106:$BM$156,'Rates & Source Data'!$C$106:$C$156,$A6,'Rates & Source Data'!$A$106:$A$156,$B6),$K6),$K6) | F6: =E6 | I6: Review required | J6: 543.485 | K6: 1009.5243 | L6: 1009.5243
A7: 4001158058 | B7: =_xlfn.XLOOKUP(A7,'Budget FY26-28'!A:A,'Site Register'!M:M) | C7: kWh | D7: 0 | E7: =SUMIFS('Rates & Source Data'!$AO$33:$AO$100,'Rates & Source Data'!$A$33:$A$100,$A7) | F7: =SUMIFS('Rates & Source Data'!$AR$33:$AR$100,'Rates & Source Data'!$A$33:$A$100,$A7) | I7: Review required | J7: 991 | K7: 550 | L7: 550
A8: 4001174306 | B8: =_xlfn.XLOOKUP(A8,'Budget FY26-28'!A:A,'Site Register'!M:M) | C8: kWh | D8: 254401 | E8: =IFERROR(IF(SUMIFS('Rates & Source Data'!$BM$106:$BM$156,'Rates & Source Data'!$C$106:$C$156,$A8,'Rates & Source Data'!$A$106:$A$156,$B8)<>0,SUMIFS('Rates & Source Data'!$BM$106:$BM$156,'Rates & Source Data'!$C$106:$C$156,$A8,'Rates & Source Data'!$A$106:$A$156,$B8),$K8),$K8) | F8: =E8 | G8: 0.2791949 | H8: 0.2791949 | I8: Ready | J8: 96071.06 | K8: 71027.462 | L8: 71027.462
A9: 4001198085 | B9: =_xlfn.XLOOKUP(A9,'Budget FY26-28'!A:A,'Site Register'!M:M) | C9: kWh | D9: 399092.86 | E9: =SUMIFS('Rates & Source Data'!$AO$33:$AO$100,'Rates & Source Data'!$A$33:$A$100,$A9) | F9: =SUMIFS('Rates & Source Data'!$AR$33:$AR$100,'Rates & Source Data'!$A$33:$A$100,$A9) | G9: 0.11563507 | H9: 0.11363655 | I9: Ready | J9: 130890.78 | K9: 46149.13 | L9: 45351.536
A10: 4001200751 | B10: =_xlfn.XLOOKUP(A10,'Budget FY26-28'!A:A,'Site Register'!M:M) | C10: kWh | D10: 10268532 | E10: =SUMIFS('Rates & Source Data'!$AO$33:$AO$100,'Rates & Source Data'!$A$33:$A$100,$A10) | F10: =SUMIFS('Rates & Source Data'!$AR$33:$AR$100,'Rates & Source Data'!$A$33:$A$100,$A10) | G10: 0.10544056 | H10: 0.10449211 | I10: Ready | J10: 2157078.1 | K10: 1082719.8 | L10: 1072980.6
A11: 4001231357 | B11: =_xlfn.XLOOKUP(A11,'Budget FY26-28'!A:A,'Site Register'!M:M) | C11: kWh | D11: 30776 | E11: =IFERROR(IF(SUMIFS('Rates & Source Data'!$BM$106:$BM$156,'Rates & Source Data'!$C$106:$C$156,$A11,'Rates & Source Data'!$A$106:$A$156,$B11)<>0,SUMIFS('Rates & Source Data'!$BM$106:$BM$156,'Rates & Source Data'!$C$106:$C$156,$A11,'Rates & Source Data'!$A$106:$A$156,$B11),$K11),$K11) | F11: =E11 | G11: 0.4041785 | H11: 0.4041785 | I11: Ready | J11: 10863.702 | K11: 12438.998 | L11: 12438.998
A12: 4001277522 | B12: =_xlfn.XLOOKUP(A12,'Budget FY26-28'!A:A,'Site Register'!M:M) | C12: kWh | D12: 9299 | E12: =IFERROR(IF(SUMIFS('Rates & Source Data'!$BM$106:$BM$156,'Rates & Source Data'!$C$106:$C$156,$A12,'Rates & Source Data'!$A$106:$A$156,$B12)<>0,SUMIFS('Rates & Source Data'!$BM$106:$BM$156,'Rates & Source Data'!$C$106:$C$156,$A12,'Rates & Source Data'!$A$106:$A$156,$B12),$K12),$K12) | F12: =E12 | G12: 0.38376721 | H12: 0.38376721 | I12: Ready | J12: 4035.2595 | K12: 3568.6513 | L12: 3568.6513
A13: 4001287259 | B13: =_xlfn.XLOOKUP(A13,'Budget FY26-28'!A:A,'Site Register'!M:M) | C13: kWh | D13: 171810.51 | E13: =SUMIFS('Rates & Source Data'!$AO$33:$AO$100,'Rates & Source Data'!$A$33:$A$100,$A13) | F13: =SUMIFS('Rates & Source Data'!$AR$33:$AR$100,'Rates & Source Data'!$A$33:$A$100,$A13) | G13: 0.111167 | H13: 0.11028304 | I13: Ready | J13: 45112.975 | K13: 19099.659 | L13: 18947.786
A14: 4103512903 | B14: =_xlfn.XLOOKUP(A14,'Budget FY26-28'!A:A,'Site Register'!M:M) | C14: kWh | D14: 15039 | E14: =IFERROR(IF(SUMIFS('Rates & Source Data'!$BM$106:$BM$156,'Rates & Source Data'!$C$106:$C$156,$A14,'Rates & Source Data'!$A$106:$A$156,$B14)<>0,SUMIFS('Rates & Source Data'!$BM$106:$BM$156,'Rates & Source Data'!$C$106:$C$156,$A14,'Rates & Source Data'!$A$106:$A$156,$B14),$K14),$K14) | F14: =E14 | G14: 0.25343406 | H14: 0.25343406 | I14: Ready | J14: 6147.8927 | K14: 3811.3948 | L14: 3811.3948
A15: 4103689689 | B15: =_xlfn.XLOOKUP(A15,'Budget FY26-28'!A:A,'Site Register'!M:M) | C15: kWh | D15: 143552.12 | E15: =SUMIFS('Rates & Source Data'!$AO$33:$AO$100,'Rates & Source Data'!$A$33:$A$100,$A15) | F15: =SUMIFS('Rates & Source Data'!$AR$33:$AR$100,'Rates & Source Data'!$A$33:$A$100,$A15) | G15: 0.1133316 | H15: 0.11169924 | I15: Ready | J15: 40468.996 | K15: 16268.991 | L15: 16034.662
A16: 4103705443 | B16: =_xlfn.XLOOKUP(A16,'Budget FY26-28'!A:A,'Site Register'!M:M) | C16: kWh | D16: 106397.96 | E16: =SUMIFS('Rates & Source Data'!$AO$33:$AO$100,'Rates & Source Data'!$A$33:$A$100,$A16) | F16: =SUMIFS('Rates & Source Data'!$AR$33:$AR$100,'Rates & Source Data'!$A$33:$A$100,$A16) | G16: 0.11416328 | H16: 0.11223166 | I16: Ready | J16: 29888.748 | K16: 12146.74 | L16: 11941.22
A17: 4103711576 | B17: =_xlfn.XLOOKUP(A17,'Budget FY26-28'!A:A,'Site Register'!M:M) | C17: kWh | D17: 2405011.6 | E17: =SUMIFS('Rates & Source Data'!$AO$33:$AO$100,'Rates & Source Data'!$A$33:$A$100,$A17) | F17: =SUMIFS('Rates & Source Data'!$AR$33:$AR$100,'Rates & Source Data'!$A$33:$A$100,$A17) | G17: 0.1083436 | H17: 0.10731269 | I17: Ready | J17: 469889.74 | K17: 260567.61 | L17: 258088.25
A18: 4103713125 | B18: =_xlfn.XLOOKUP(A18,'Budget FY26-28'!A:A,'Site Register'!M:M) | C18: kWh | D18: 1251891.6 | E18: =SUMIFS('Rates & Source Data'!$AO$33:$AO$100,'Rates & Source Data'!$A$33:$A$100,$A18) | F18: =SUMIFS('Rates & Source Data'!$AR$33:$AR$100,'Rates & Source Data'!$A$33:$A$100,$A18) | G18: 0.10856071 | H18: 0.10754959 | I18: Ready | J18: 287020.45 | K18: 135906.24 | L18: 134640.42
A19: 4103737079 | B19: =_xlfn.XLOOKUP(A19,'Budget FY26-28'!A:A,'Site Register'!M:M) | C19: kWh | D19: 19241.4 | E19: =SUMIFS('Rates & Source Data'!$AO$33:$AO$100,'Rates & Source Data'!$A$33:$A$100,$A19) | F19: =SUMIFS('Rates & Source Data'!$AR$33:$AR$100,'Rates & Source Data'!$A$33:$A$100,$A19) | G19: 0.13724908 | H19: 0.13629366 | I19: Ready | J19: 10765.562 | K19: 2640.8644 | L19: 2622.4809
A20: 4103737729 | B20: =_xlfn.XLOOKUP(A20,'Budget FY26-28'!A:A,'Site Register'!M:M) | C20: kWh | D20: 13618.63 | E20: =SUMIFS('Rates & Source Data'!$AO$33:$AO$100,'Rates & Source Data'!$A$33:$A$100,$A20) | F20: =SUMIFS('Rates & Source Data'!$AR$33:$AR$100,'Rates & Source Data'!$A$33:$A$100,$A20) | G20: 0.15028575 | H20: 0.14911445 | I20: Ready | J20: 4135.7821 | K20: 2046.686 | L20: 2030.7346
A21: 4103742938 | B21: =_xlfn.XLOOKUP(A21,'Budget FY26-28'!A:A,'Site Register'!M:M) | C21: kWh | D21: 105623.45 | E21: =SUMIFS('Rates & Source Data'!$AO$33:$AO$100,'Rates & Source Data'!$A$33:$A$100,$A21) | F21: =SUMIFS('Rates & Source Data'!$AR$33:$AR$100,'Rates & Source Data'!$A$33:$A$100,$A21) | G21: 0.11371029 | H21: 0.11225956 | I21: Ready | J21: 51698.741 | K21: 12010.473 | L21: 11857.242
A22: 4103742939 | B22: =_xlfn.XLOOKUP(A22,'Budget FY26-28'!A:A,'Site Register'!M:M) | C22: kWh | D22: 81857.8 | E22: =SUMIFS('Rates & Source Data'!$AO$33:$AO$100,'Rates & Source Data'!$A$33:$A$100,$A22) | F22: =SUMIFS('Rates & Source Data'!$AR$33:$AR$100,'Rates & Source Data'!$A$33:$A$100,$A22) | G22: 0.11541036 | H22: 0.11453611 | I22: Ready | J22: 39496.387 | K22: 9447.2378 | L22: 9375.6742
A23: 4103742940 | B23: =_xlfn.XLOOKUP(A23,'Budget FY26-28'!A:A,'Site Register'!M:M) | C23: kWh | D23: 90701.86 | E23: =SUMIFS('Rates & Source Data'!$AO$33:$AO$100,'Rates & Source Data'!$A$33:$A$100,$A23) | F23: =SUMIFS('Rates & Source Data'!$AR$33:$AR$100,'Rates & Source Data'!$A$33:$A$100,$A23) | G23: 0.11448239 | H23: 0.1127728 | I23: Ready | J23: 45158.303 | K23: 10383.766 | L23: 10228.703
A24: 4103759848 | B24: =_xlfn.XLOOKUP(A24,'Budget FY26-28'!A:A,'Site Register'!M:M) | C24: kWh | D24: 102767.91 | E24: =SUMIFS('Rates & Source Data'!$AO$33:$AO$100,'Rates & Source Data'!$A$33:$A$100,$A24) | F24: =SUMIFS('Rates & Source Data'!$AR$33:$AR$100,'Rates & Source Data'!$A$33:$A$100,$A24) | G24: 0.11634754 | H24: 0.11468759 | I24: Ready | J24: 25065.346 | K24: 11956.793 | L24: 11786.204
A25: 4103759849 | B25: =_xlfn.XLOOKUP(A25,'Budget FY26-28'!A:A,'Site Register'!M:M) | C25: kWh | D25: 94304.33 | E25: =SUMIFS('Rates & Source Data'!$AO$33:$AO$100,'Rates & Source Data'!$A$33:$A$100,$A25) | F25: =SUMIFS('Rates & Source Data'!$AR$33:$AR$100,'Rates & Source Data'!$A$33:$A$100,$A25) | G25: 0.11422131 | H25: 0.11242157 | I25: Ready | J25: 47056.114 | K25: 10771.564 | L25: 10601.841
A26: 4103766552 | B26: =_xlfn.XLOOKUP(A26,'Budget FY26-28'!A:A,'Site Register'!M:M) | C26: kWh | D26: 224019.81 | E26: =SUMIFS('Rates & Source Data'!$AO$33:$AO$100,'Rates & Source Data'!$A$33:$A$100,$A26) | F26: =SUMIFS('Rates & Source Data'!$AR$33:$AR$100,'Rates & Source Data'!$A$33:$A$100,$A26) | G26: 0.11244843 | H26: 0.11080043 | I26: Ready | J26: 59982.959 | K26: 25190.676 | L26: 24821.492
... A32: 4104030101 | B32: =_xlfn.XLOOKUP(A32,'Budget FY26-28'!A:A,'Site Register'!M:M) | C32: kWh | D32: 687204.96 | E32: =SUMIFS('Rates & Source Data'!$AO$33:$AO$100,'Rates & Source Data'!$A$33:$A$100,$A32) | F32: =SUMIFS('Rates & Source Data'!$AR$33:$AR$100,'Rates & Source Data'!$A$33:$A$100,$A32) | G32: 0.10987742 | H32: 0.1089323 | I32: Ready | J32: 173885.28 | K32: 75508.307 | L32: 74858.818
A33: 4104037195 | B33: =_xlfn.XLOOKUP(A33,'Budget FY26-28'!A:A,'Site Register'!M:M) | C33: kWh | D33: 2938 | E33: =IFERROR(IF(SUMIFS('Rates & Source Data'!$BM$106:$BM$156,'Rates & Source Data'!$C$106:$C$156,$A33,'Rates & Source Data'!$A$106:$A$156,$B33)<>0,SUMIFS('Rates & Source Data'!$BM$106:$BM$156,'Rates & Source Data'!$C$106:$C$156,$A33,'Rates & Source Data'!$A$106:$A$156,$B33),$K33),$K33) | F33: =E33 | G33: 0.45948541 | H33: 0.45948541 | I33: Ready | J33: 1952.5169 | K33: 1349.9681 | L33: 1349.9681
A34: 4204072845 | B34: =_xlfn.XLOOKUP(A34,'Budget FY26-28'!A:A,'Site Register'!M:M) | C34: kWh | D34: 377879.64 | E34: =SUMIFS('Rates & Source Data'!$AO$33:$AO$100,'Rates & Source Data'!$A$33:$A$100,$A34) | F34: =SUMIFS('Rates & Source Data'!$AR$33:$AR$100,'Rates & Source Data'!$A$33:$A$100,$A34) | G34: 0.11208158 | H34: 0.11112396 | I34: Ready | J34: 133353.88 | K34: 42353.346 | L34: 41991.481
A35: 4204234430 | B35: =_xlfn.XLOOKUP(A35,'Budget FY26-28'!A:A,'Site Register'!M:M) | C35: kWh | D35: 16709 | E35: =IFERROR(IF(SUMIFS('Rates & Source Data'!$BM$106:$BM$156,'Rates & Source Data'!$C$106:$C$156,$A35,'Rates & Source Data'!$A$106:$A$156,$B35)<>0,SUMIFS('Rates & Source Data'!$BM$106:$BM$156,'Rates & Source Data'!$C$106:$C$156,$A35,'Rates & Source Data'!$A$106:$A$156,$B35),$K35),$K35) | F35: =E35 | G35: 0.36876043 | H35: 0.36876043 | I35: Ready | J35: 6244.0996 | K35: 6161.618 | L35: 6161.618
A36: 4310027807 | B36: =_xlfn.XLOOKUP(A36,'Budget FY26-28'!A:A,'Site Register'!M:M) | C36: kWh | D36: 65379 | E36: =IFERROR(IF(SUMIFS('Rates & Source Data'!$BM$106:$BM$156,'Rates & Source Data'!$C$106:$C$156,$A36,'Rates & Source Data'!$A$106:$A$156,$B36)<>0,SUMIFS('Rates & Source Data'!$BM$106:$BM$156,'Rates & Source Data'!$C$106:$C$156,$A36,'Rates & Source Data'!$A$106:$A$156,$B36),$K36),$K36) | F36: =E36 | G36: 0.24465015 | H36: 0.24465015 | I36: Ready | J36: 27601.381 | K36: 15994.982 | L36: 15994.982
A37: 4310934278 | B37: =_xlfn.XLOOKUP(A37,'Budget FY26-28'!A:A,'Site Register'!M:M) | C37: kWh | D37: 210805.16 | E37: =SUMIFS('Rates & Source Data'!$AO$33:$AO$100,'Rates & Source Data'!$A$33:$A$100,$A37) | F37: =SUMIFS('Rates & Source Data'!$AR$33:$AR$100,'Rates & Source Data'!$A$33:$A$100,$A37) | G37: 0.11450416 | H37: 0.11283111 | I37: Ready | J37: 53110.244 | K37: 24138.067 | L37: 23785.38
A38: 4310938258 | B38: =_xlfn.XLOOKUP(A38,'Budget FY26-28'!A:A,'Site Register'!M:M) | C38: kWh | D38: 147736.15 | E38: =SUMIFS('Rates & Source Data'!$AO$33:$AO$100,'Rates & Source Data'!$A$33:$A$100,$A38) | F38: =SUMIFS('Rates & Source Data'!$AR$33:$AR$100,'Rates & Source Data'!$A$33:$A$100,$A38) | G38: 0.11544924 | H38: 0.11325957 | I38: Ready | J38: 39610.504 | K38: 17056.026 | L38: 16732.532
A39: 4310955386 | B39: =_xlfn.XLOOKUP(A39,'Budget FY26-28'!A:A,'Site Register'!M:M) | C39: kWh | D39: 110678.1 | E39: =SUMIFS('Rates & Source Data'!$AO$33:$AO$100,'Rates & Source Data'!$A$33:$A$100,$A39) | F39: =SUMIFS('Rates & Source Data'!$AR$33:$AR$100,'Rates & Source Data'!$A$33:$A$100,$A39) | G39: 0.11563405 | H39: 0.11383267 | I39: Ready | J39: 28894.897 | K39: 12798.157 | L39: 12598.783
A40: 4310957406 | B40: =_xlfn.XLOOKUP(A40,'Budget FY26-28'!A:A,'Site Register'!M:M) | C40: kWh | D40: 26836.14 | E40: =SUMIFS('Rates & Source Data'!$AO$33:$AO$100,'Rates & Source Data'!$A$33:$A$100,$A40) | F40: =SUMIFS('Rates & Source Data'!$AR$33:$AR$100,'Rates & Source Data'!$A$33:$A$100,$A40) | G40: 0.12888916 | H40: 0.1271056 | I40: Ready | J40: 14736.432 | K40: 3458.8876 | L40: 3411.0236
A41: 4310984436 | B41: =_xlfn.XLOOKUP(A41,'Budget FY26-28'!A:A,'Site Register'!M:M) | C41: kWh | D41: 238859.85 | E41: =SUMIFS('Rates & Source Data'!$AO$33:$AO$100,'Rates & Source Data'!$A$33:$A$100,$A41) | F41: =SUMIFS('Rates & Source Data'!$AR$33:$AR$100,'Rates & Source Data'!$A$33:$A$100,$A41) | G41: 0.11402274 | H41: 0.11218719 | I41: Ready | J41: 63794.021 | K41: 27235.456 | L41: 26797.016
A42: 4311006154 | B42: =_xlfn.XLOOKUP(A42,'Budget FY26-28'!A:A,'Site Register'!M:M) | C42: kWh | D42: 141294.49 | E42: =SUMIFS('Rates & Source Data'!$AO$33:$AO$100,'Rates & Source Data'!$A$33:$A$100,$A42) | F42: =SUMIFS('Rates & Source Data'!$AR$33:$AR$100,'Rates & Source Data'!$A$33:$A$100,$A42) | G42: 0.1147264 | H42: 0.11247869 | I42: Ready | J42: 38147.555 | K42: 16210.208 | L42: 15892.619
A43: 4311006155 | B43: =_xlfn.XLOOKUP(A43,'Budget FY26-28'!A:A,'Site Register'!M:M) | C43: kWh | D43: 125233.95 | E43: =SUMIFS('Rates & Source Data'!$AO$33:$AO$100,'Rates & Source Data'!$A$33:$A$100,$A43) | F43: =SUMIFS('Rates & Source Data'!$AR$33:$AR$100,'Rates & Source Data'!$A$33:$A$100,$A43) | G43: 0.11607027 | H43: 0.11410718 | I43: Ready | J43: 33924.466 | K43: 14535.938 | L43: 14290.092
A44: 4311006315 | B44: =_xlfn.XLOOKUP(A44,'Budget FY26-28'!A:A,'Site Register'!M:M) | C44: kWh | D44: 631132.89 | E44: =SUMIFS('Rates & Source Data'!$AO$33:$AO$100,'Rates & Source Data'!$A$33:$A$100,$A44) | F44: =SUMIFS('Rates & Source Data'!$AR$33:$AR$100,'Rates & Source Data'!$A$33:$A$100,$A44) | G44: 0.11296606 | H44: 0.11190386 | I44: Ready | J44: 139059.12 | K44: 71296.594 | L44: 70626.208
A45: 4311396021 | B45: =_xlfn.XLOOKUP(A45,'Budget FY26-28'!A:A,'Site Register'!M:M) | C45: kWh | D45: 1537139 | E45: =SUMIFS('Rates & Source Data'!$AO$33:$AO$100,'Rates & Source Data'!$A$33:$A$100,$A45) | F45: =SUMIFS('Rates & Source Data'!$AR$33:$AR$100,'Rates & Source Data'!$A$33:$A$100,$A45) | G45: 0.112447 | H45: 0.11136821 | I45: Ready | J45: 364715.68 | K45: 172846.66 | L45: 171188.41
A46: 4311396022 | B46: =_xlfn.XLOOKUP(A46,'Budget FY26-28'!A:A,'Site Register'!M:M) | C46: kWh | D46: 553695.01 | E46: =SUMIFS('Rates & Source Data'!$AO$33:$AO$100,'Rates & Source Data'!$A$33:$A$100,$A46) | F46: =SUMIFS('Rates & Source Data'!$AR$33:$AR$100,'Rates & Source Data'!$A$33:$A$100,$A46) | G46: 0.11304851 | H46: 0.11186558 | I46: Ready | J46: 135558.08 | K46: 62594.394 | L46: 61939.414
A47: 4311422527 | B47: =_xlfn.XLOOKUP(A47,'Budget FY26-28'!A:A,'Site Register'!M:M) | C47: kWh | D47: 33060 | E47: =IFERROR(IF(SUMIFS('Rates & Source Data'!$BM$106:$BM$156,'Rates & Source Data'!$C$106:$C$156,$A47,'Rates & Source Data'!$A$106:$A$156,$B47)<>0,SUMIFS('Rates & Source Data'!$BM$106:$BM$156,'Rates & Source Data'!$C$106:$C$156,$A47,'Rates & Source Data'!$A$106:$A$156,$B47),$K47),$K47) | F47: =E47 | G47: 0.25373452 | H47: 0.25373452 | I47: Ready | J47: 10152.655 | K47: 8388.4633 | L47: 8388.4633
A48: 4407159044 | B48: =_xlfn.XLOOKUP(A48,'Budget FY26-28'!A:A,'Site Register'!M:M) | C48: kWh | D48: 33872 | E48: =IFERROR(IF(SUMIFS('Rates & Source Data'!$BM$106:$BM$156,'Rates & Source Data'!$C$106:$C$156,$A48,'Rates & Source Data'!$A$106:$A$156,$B48)<>0,SUMIFS('Rates & Source Data'!$BM$106:$BM$156,'Rates & Source Data'!$C$106:$C$156,$A48,'Rates & Source Data'!$A$106:$A$156,$B48),$K48),$K48) | F48: =E48 | G48: 0.30502529 | H48: 0.30502529 | I48: Ready | J48: 13262.421 | K48: 10331.817 | L48: 10331.817
A49: 4407159054 | B49: =_xlfn.XLOOKUP(A49,'Budget FY26-28'!A:A,'Site Register'!M:M) | C49: kWh | D49: 379736.79 | E49: =SUMIFS('Rates & Source Data'!$AO$33:$AO$100,'Rates & Source Data'!$A$33:$A$100,$A49) | F49: =SUMIFS('Rates & Source Data'!$AR$33:$AR$100,'Rates & Source Data'!$A$33:$A$100,$A49) | G49: 0.10825401 | H49: 0.10747762 | I49: Ready | J49: 90063.388 | K49: 41108.031 | L49: 40813.205
A50: NAAA00AC25 | B50: =_xlfn.XLOOKUP(A50,'Budget FY26-28'!A:A,'Site Register'!M:M) | C50: kWh | D50: 468259.76 | E50: =SUMIFS('Rates & Source Data'!$AO$33:$AO$100,'Rates & Source Data'!$A$33:$A$100,$A50) | F50: =SUMIFS('Rates & Source Data'!$AR$33:$AR$100,'Rates & Source Data'!$A$33:$A$100,$A50) | G50: 0.11573418 | H50: 0.11466244 | I50: Ready | J50: 166086.31 | K50: 54193.659 | L50: 53691.809
A51: 2500033707 | B51: =_xlfn.XLOOKUP(A51,'Budget FY26-28'!A:A,'Site Register'!M:M) | C51: kWh | D51: 0 | I51: Review required
A52: 2500044629 | B52: =_xlfn.XLOOKUP(A52,'Budget FY26-28'!A:A,'Site Register'!M:M) | C52: kWh | D52: 0 | I52: Review required
A53: 2500054287 | B53: =_xlfn.XLOOKUP(A53,'Budget FY26-28'!A:A,'Site Register'!M:M) | C53: kWh | D53: 2347683.9 | E53: =SUMIFS('Rates & Source Data'!$M$1489:$M$1489,'Rates & Source Data'!$A$1489:$A$1489,$A53) | F53: ="" | I53: Ready | J53: =SUMIFS('Rates & Source Data'!$B$1494:$B$1494,'Rates & Source Data'!$A$1494:$A$1494,$A53) | K53: 783031.27
A54: 3030075637 | B54: =_xlfn.XLOOKUP(A54,'Budget FY26-28'!A:A,'Site Register'!M:M) | C54: kWh | D54: 66273.91 | E54: =SUMIFS('Rates & Source Data'!$AO$33:$AO$100,'Rates & Source Data'!$A$33:$A$100,$A54) | F54: =SUMIFS('Rates & Source Data'!$AR$33:$AR$100,'Rates & Source Data'!$A$33:$A$100,$A54) | G54: 0.095960718 | H54: 0.09733264 | I54: Ready | J54: 14719.753 | K54: 6359.692 | L54: 6450.6146
A55: 3038502933 | B55: =_xlfn.XLOOKUP(A55,'Budget FY26-28'!A:A,'Site Register'!M:M) | C55: kWh | D55: 38380 | E55: =IFERROR(IF(SUMIFS('Rates & Source Data'!$BM$106:$BM$156,'Rates & Source Data'!$C$106:$C$156,$A55,'Rates & Source Data'!$A$106:$A$156,$B55)<>0,SUMIFS('Rates & Source Data'!$BM$106:$BM$156,'Rates & Source Data'!$C$106:$C$156,$A55,'Rates & Source Data'!$A$106:$A$156,$B55),$K55),$K55) | F55: =E55 | G55: 0.2913437 | H55: 0.2913437 | I55: Ready | J55: 11292.443 | K55: 11181.771 | L55: 11181.771
A56: 3039040879 | B56: =_xlfn.XLOOKUP(A56,'Budget FY26-28'!A:A,'Site Register'!M:M) | C56: kWh | D56: 70195 | E56: =IFERROR(IF(SUMIFS('Rates & Source Data'!$BM$106:$BM$156,'Rates & Source Data'!$C$106:$C$156,$A56,'Rates & Source Data'!$A$106:$A$156,$B56)<>0,SUMIFS('Rates & Source Data'!$BM$106:$BM$156,'Rates & Source Data'!$C$106:$C$156,$A56,'Rates & Source Data'!$A$106:$A$156,$B56),$K56),$K56) | F56: =E56 | G56: 0.28310897 | H56: 0.28310897 | I56: Ready | J56: 20653.283 | K56: 19872.834 | L56: 19872.834
A57: 3041781236 | B57: =_xlfn.XLOOKUP(A57,'Budget FY26-28'!A:A,'Site Register'!M:M) | C57: kWh | D57: 53331 | E57: =IFERROR(IF(SUMIFS('Rates & Source Data'!$BM$106:$BM$156,'Rates & Source Data'!$C$106:$C$156,$A57,'Rates & Source Data'!$A$106:$A$156,$B57)<>0,SUMIFS('Rates & Source Data'!$BM$106:$BM$156,'Rates & Source Data'!$C$106:$C$156,$A57,'Rates & Source Data'!$A$106:$A$156,$B57),$K57),$K57) | F57: =E57 | G57: 0.28625022 | H57: 0.28625022 | I57: Ready | J57: 15057.049 | K57: 15266.011 | L57: 15266.011
A58: 3051770385 | B58: =_xlfn.XLOOKUP(A58,'Budget FY26-28'!A:A,'Site Register'!M:M) | C58: kWh | D58: 208479.48 | E58: =SUMIFS('Rates & Source Data'!$AO$33:$AO$100,'Rates & Source Data'!$A$33:$A$100,$A58) | F58: =SUMIFS('Rates & Source Data'!$AR$33:$AR$100,'Rates & Source Data'!$A$33:$A$100,$A58) | G58: 0.089630752 | H58: 0.090991473 | I58: Ready | J58: 54065.651 | K58: 18686.172 | L58: 18969.855
A59: 3053253239 | B59: =_xlfn.XLOOKUP(A59,'Budget FY26-28'!A:A,'Site Register'!M:M) | C59: kWh | D59: 6208798 | E59: =SUMIFS('Rates & Source Data'!$AO$33:$AO$100,'Rates & Source Data'!$A$33:$A$100,$A59) | F59: =SUMIFS('Rates & Source Data'!$AR$33:$AR$100,'Rates & Source Data'!$A$33:$A$100,$A59) | G59: 0.087300343 | H59: 0.088932898 | I59: Ready | J59: =IF(COUNTIF('Rates & Source Data'!$A$1737:$A$1738,$A59)=0,"",SUMIFS('Rates & Source Data'!$B$1737:$B$1738,'Rates & Source Data'!$A$1737:$A$1738,$A59)) | K59: 542030.2 | L59: 552166.4
A60: 3116382269 | B60: =_xlfn.XLOOKUP(A60,'Budget FY26-28'!A:A,'Site Register'!M:M) | C60: kWh | D60: 8005232.9 | E60: =SUMIFS('Rates & Source Data'!$AO$33:$AO$100,'Rates & Source Data'!$A$33:$A$100,$A60) | F60: =SUMIFS('Rates & Source Data'!$AR$33:$AR$100,'Rates & Source Data'!$A$33:$A$100,$A60) | G60: 0.082521535 | H60: 0.083812613 | I60: Ready | J60: 1183999.4 | K60: 660604.11 | L60: 670939.49
A61: 3116600011 | B61: =_xlfn.XLOOKUP(A61,'Budget FY26-28'!A:A,'Site Register'!M:M) | C61: kWh | D61: 49553.7 | E61: =SUMIFS('Rates & Source Data'!$AO$33:$AO$100,'Rates & Source Data'!$A$33:$A$100,$A61) | F61: =SUMIFS('Rates & Source Data'!$AR$33:$AR$100,'Rates & Source Data'!$A$33:$A$100,$A61) | G61: 0.09626225 | H61: 0.097596548 | I61: Ready | J61: 10546.729 | K61: 4770.1507 | L61: 4836.2701
A62: 3117134943 | B62: =_xlfn.XLOOKUP(A62,'Budget FY26-28'!A:A,'Site Register'!M:M) | C62: kWh | D62: 189990.46 | E62: =SUMIFS('Rates & Source Data'!$AO$33:$AO$100,'Rates & Source Data'!$A$33:$A$100,$A62) | F62: =SUMIFS('Rates & Source Data'!$AR$33:$AR$100,'Rates & Source Data'!$A$33:$A$100,$A62) | G62: 0.087796002 | H62: 0.089125914 | I62: Ready | J62: 36988.786 | K62: 16680.403 | L62: 16933.073
A63: 3120014382 | B63: =_xlfn.XLOOKUP(A63,'Budget FY26-28'!A:A,'Site Register'!M:M) | C63: kWh | D63: 344623.5 | E63: =SUMIFS('Rates & Source Data'!$AO$33:$AO$100,'Rates & Source Data'!$A$33:$A$100,$A63) | F63: =SUMIFS('Rates & Source Data'!$AR$33:$AR$100,'Rates & Source Data'!$A$33:$A$100,$A63) | G63: 0.086742239 | H63: 0.088075517 | I63: Ready | J63: 61767.8 | K63: 29893.414 | L63: 30352.893
A64: 3120070486 | B64: =_xlfn.XLOOKUP(A64,'Budget FY26-28'!A:A,'Site Register'!M:M) | C64: kWh | D64: 260263.44 | E64: =SUMIFS('Rates & Source Data'!$AO$33:$AO$100,'Rates & Source Data'!$A$33:$A$100,$A64) | F64: =SUMIFS('Rates & Source Data'!$AR$33:$AR$100,'Rates & Source Data'!$A$33:$A$100,$A64) | G64: 0.086513366 | H64: 0.087834894 | I64: Ready | J64: 45989.983 | K64: 22516.266 | L64: 22860.212
A65: 3120103988 | B65: =_xlfn.XLOOKUP(A65,'Budget FY26-28'!A:A,'Site Register'!M:M) | C65: kWh | D65: 747633.8 | E65: =SUMIFS('Rates & Source Data'!$AO$33:$AO$100,'Rates & Source Data'!$A$33:$A$100,$A65) | F65: =SUMIFS('Rates & Source Data'!$AR$33:$AR$100,'Rates & Source Data'!$A$33:$A$100,$A65) | G65: 0.086635649 | H65: 0.087981541 | I65: Ready | J65: 166792.17 | K65: 64771.74 | L65: 65777.974
A66: 3120129028 | B66: =_xlfn.XLOOKUP(A66,'Budget FY26-28'!A:A,'Site Register'!M:M) | C66: kWh | D66: 207140.7 | E66: =SUMIFS('Rates & Source Data'!$AO$33:$AO$100,'Rates & Source Data'!$A$33:$A$100,$A66) | F66: =SUMIFS('Rates & Source Data'!$AR$33:$AR$100,'Rates & Source Data'!$A$33:$A$100,$A66) | G66: 0.085706485 | H66: 0.087005439 | I66: Ready | J66: 37050.024 | K66: 17753.301 | L66: 18022.368
A67: 3120143385 | B67: =_xlfn.XLOOKUP(A67,'Budget FY26-28'!A:A,'Site Register'!M:M) | C67: kWh | D67: 225934.41 | E67: =SUMIFS('Rates & Source Data'!$AO$33:$AO$100,'Rates & Source Data'!$A$33:$A$100,$A67) | F67: =SUMIFS('Rates & Source Data'!$AR$33:$AR$100,'Rates & Source Data'!$A$33:$A$100,$A67) | G67: 0.08833433 | H67: 0.089680222 | I67: Ready | J67: 37482.059 | K67: 19957.765 | L67: 20261.848
A68: 3120725958 | B68: =_xlfn.XLOOKUP(A68,'Budget FY26-28'!A:A,'Site Register'!M:M) | C68: kWh | D68: 1047801.8 | E68: =SUMIFS('Rates & Source Data'!$AO$33:$AO$100,'Rates & Source Data'!$A$33:$A$100,$A68) | F68: =SUMIFS('Rates & Source Data'!$AR$33:$AR$100,'Rates & Source Data'!$A$33:$A$100,$A68) | G68: 0.084986692 | H68: 0.086309252 | I68: Ready | J68: 205270.21 | K68: 89049.213 | L68: 90434.994
A69: QB05383854 | B69: =_xlfn.XLOOKUP(A69,'Budget FY26-28'!A:A,'Site Register'!M:M) | C69: kWh | D69: 876582.28 | E69: =SUMIFS('Rates & Source Data'!$AO$33:$AO$100,'Rates & Source Data'!$A$33:$A$100,$A69) | F69: =SUMIFS('Rates & Source Data'!$AR$33:$AR$100,'Rates & Source Data'!$A$33:$A$100,$A69) | G69: 0.085066098 | H69: 0.086388271 | I69: Ready | J69: 184560.8 | K69: 74567.434 | L69: 75726.427
A70: QB06081428 | B70: =_xlfn.XLOOKUP(A70,'Budget FY26-28'!A:A,'Site Register'!M:M) | C70: kWh | D70: 1044289.8 | E70: =SUMIFS('Rates & Source Data'!$AO$33:$AO$100,'Rates & Source Data'!$A$33:$A$100,$A70) | F70: =SUMIFS('Rates & Source Data'!$AR$33:$AR$100,'Rates & Source Data'!$A$33:$A$100,$A70) | G70: 0.085527993 | H70: 0.086859582 | I70: Ready | J70: 180958.93 | K70: 89316.014 | L70: 90706.579
A71: QB06082220 | B71: =_xlfn.XLOOKUP(A71,'Budget FY26-28'!A:A,'Site Register'!M:M) | C71: kWh | D71: 80526.6 | E71: =SUMIFS('Rates & Source Data'!$AO$33:$AO$100,'Rates & Source Data'!$A$33:$A$100,$A71) | F71: =SUMIFS('Rates & Source Data'!$AR$33:$AR$100,'Rates & Source Data'!$A$33:$A$100,$A71) | G71: 0.09183136 | H71: 0.093162949 | I71: Ready | J71: 16557.949 | K71: 7394.8672 | L71: 7502.0956
A72: QB07736452 | B72: =_xlfn.XLOOKUP(A72,'Budget FY26-28'!A:A,'Site Register'!M:M) | C72: kWh | D72: 24596 | E72: =IFERROR(IF(SUMIFS('Rates & Source Data'!$BM$106:$BM$156,'Rates & Source Data'!$C$106:$C$156,$A72,'Rates & Source Data'!$A$106:$A$156,$B72)<>0,SUMIFS('Rates & Source Data'!$BM$106:$BM$156,'Rates & Source Data'!$C$106:$C$156,$A72,'Rates & Source Data'!$A$106:$A$156,$B72),$K72),$K72) | F72: =E72 | G72: 0.31140059 | H72: 0.31140059 | I72: Ready | J72: 6996.117 | K72: 7659.2088 | L72: 7659.2088
A73: QB13869604 | B73: =_xlfn.XLOOKUP(A73,'Budget FY26-28'!A:A,'Site Register'!M:M) | C73: kWh | D73: 16289 | E73: =IFERROR(IF(SUMIFS('Rates & Source Data'!$BM$106:$BM$156,'Rates & Source Data'!$C$106:$C$156,$A73,'Rates & Source Data'!$A$106:$A$156,$B73)<>0,SUMIFS('Rates & Source Data'!$BM$106:$BM$156,'Rates & Source Data'!$C$106:$C$156,$A73,'Rates & Source Data'!$A$106:$A$156,$B73),$K73),$K73) | F73: =E73 | G73: 0.25940277 | H73: 0.25940277 | I73: Ready | J73: 5043.2176 | K73: 4225.4117 | L73: 4225.4117
A74: QGGG000010 | B74: =_xlfn.XLOOKUP(A74,'Budget FY26-28'!A:A,'Site Register'!M:M) | C74: kWh | D74: 3994276.9 | E74: =SUMIFS('Rates & Source Data'!$AO$33:$AO$100,'Rates & Source Data'!$A$33:$A$100,$A74) | F74: =SUMIFS('Rates & Source Data'!$AR$33:$AR$100,'Rates & Source Data'!$A$33:$A$100,$A74) | G74: 0.081051308 | H74: 0.082317091 | I74: Ready | J74: 712199.51 | K74: 323741.37 | L74: 328797.25
A75: QGGG000320 | B75: =_xlfn.XLOOKUP(A75,'Budget FY26-28'!A:A,'Site Register'!M:M) | C75: kWh | D75: 165144.29 | E75: =SUMIFS('Rates & Source Data'!$AO$33:$AO$100,'Rates & Source Data'!$A$33:$A$100,$A75) | F75: =SUMIFS('Rates & Source Data'!$AR$33:$AR$100,'Rates & Source Data'!$A$33:$A$100,$A75) | G75: 0.090468156 | H75: 0.091831307 | I75: Ready | J75: 62434.925 | K75: 14940.299 | L75: 15165.416
A76: 2001130961 | B76: =_xlfn.XLOOKUP(A76,'Budget FY26-28'!A:A,'Site Register'!M:M) | C76: kWh | D76: 22458 | E76: =IFERROR(IF(SUMIFS('Rates & Source Data'!$BM$106:$BM$156,'Rates & Source Data'!$C$106:$C$156,$A76,'Rates & Source Data'!$A$106:$A$156,$B76)<>0,SUMIFS('Rates & Source Data'!$BM$106:$BM$156,'Rates & Source Data'!$C$106:$C$156,$A76,'Rates & Source Data'!$A$106:$A$156,$B76),$K76),$K76) | F76: =E76 | G76: 0.38329891 | H76: 0.38329891 | I76: Ready | J76: 10480.737 | K76: 8608.1269 | L76: 8608.1269
A77: 2001160686 | B77: =_xlfn.XLOOKUP(A77,'Budget FY26-28'!A:A,'Site Register'!M:M) | C77: kWh | D77: 36782 | E77: =IFERROR(IF(SUMIFS('Rates & Source Data'!$BM$106:$BM$156,'Rates & Source Data'!$C$106:$C$156,$A77,'Rates & Source Data'!$A$106:$A$156,$B77)<>0,SUMIFS('Rates & Source Data'!$BM$106:$BM$156,'Rates & Source Data'!$C$106:$C$156,$A77,'Rates & Source Data'!$A$106:$A$156,$B77),$K77),$K77) | F77: =E77 | G77: 0.35982858 | H77: 0.35982858 | I77: Ready | J77: 14486.184 | K77: 13235.215 | L77: 13235.215
A78: 2001160742 | B78: =_xlfn.XLOOKUP(A78,'Budget FY26-28'!A:A,'Site Register'!M:M) | C78: kWh | D78: 119987.46 | E78: =SUMIFS('Rates & Source Data'!$AO$33:$AO$100,'Rates & Source Data'!$A$33:$A$100,$A78) | F78: =SUMIFS('Rates & Source Data'!$AR$33:$AR$100,'Rates & Source Data'!$A$33:$A$100,$A78) | G78: 0.11199246 | H78: 0.11033336 | I78: Ready | J78: 39177.998 | K78: 13437.69 | L78: 13238.62
A79: 2001223248 | B79: =_xlfn.XLOOKUP(A79,'Budget FY26-28'!A:A,'Site Register'!M:M) | C79: kWh | D79: 5840 | E79: =IFERROR(IF(SUMIFS('Rates & Source Data'!$BM$106:$BM$156,'Rates & Source Data'!$C$106:$C$156,$A79,'Rates & Source Data'!$A$106:$A$156,$B79)<>0,SUMIFS('Rates & Source Data'!$BM$106:$BM$156,'Rates & Source Data'!$C$106:$C$156,$A79,'Rates & Source Data'!$A$106:$A$156,$B79),$K79),$K79) | F79: =E79 | G79: 0.44727863 | H79: 0.44727863 | I79: Ready | J79: 3099.3537 | K79: 2612.1072 | L79: 2612.1072
A80: 2001341166 | B80: =_xlfn.XLOOKUP(A80,'Budget FY26-28'!A:A,'Site Register'!M:M) | C80: kWh | D80: 3902 | E80: =IFERROR(IF(SUMIFS('Rates & Source Data'!$BM$106:$BM$156,'Rates & Source Data'!$C$106:$C$156,$A80,'Rates & Source Data'!$A$106:$A$156,$B80)<>0,SUMIFS('Rates & Source Data'!$BM$106:$BM$156,'Rates & Source Data'!$C$106:$C$156,$A80,'Rates & Source Data'!$A$106:$A$156,$B80),$K80),$K80) | F80: =E80 | G80: 0.4761728 | H80: 0.4761728 | I80: Ready | J80: 1834.3545 | K80: 1858.0263 | L80: 1858.0263
A81: 2001341167 | B81: =_xlfn.XLOOKUP(A81,'Budget FY26-28'!A:A,'Site Register'!M:M) | C81: kWh | D81: 21166 | E81: =IFERROR(IF(SUMIFS('Rates & Source Data'!$BM$106:$BM$156,'Rates & Source Data'!$C$106:$C$156,$A81,'Rates & Source Data'!$A$106:$A$156,$B81)<>0,SUMIFS('Rates & Source Data'!$BM$106:$BM$156,'Rates & Source Data'!$C$106:$C$156,$A81,'Rates & Source Data'!$A$106:$A$156,$B81),$K81),$K81) | F81: =E81 | G81: 0.35815421 | H81: 0.35815421 | I81: Ready | J81: 8477.3346 | K81: 7580.692 | L81: 7580.692
A82: 2001515449 | B82: =_xlfn.XLOOKUP(A82,'Budget FY26-28'!A:A,'Site Register'!M:M) | C82: kWh | D82: 10660 | E82: =IFERROR(IF(SUMIFS('Rates & Source Data'!$BM$106:$BM$156,'Rates & Source Data'!$C$106:$C$156,$A82,'Rates & Source Data'!$A$106:$A$156,$B82)<>0,SUMIFS('Rates & Source Data'!$BM$106:$BM$156,'Rates & Source Data'!$C$106:$C$156,$A82,'Rates & Source Data'!$A$106:$A$156,$B82),$K82),$K82) | F82: =E82 | G82: 0.38166618 | H82: 0.38166618 | I82: Ready | J82: 4434.7518 | K82: 4068.5614 | L82: 4068.5614
A83: 2001600008 | B83: =_xlfn.XLOOKUP(A83,'Budget FY26-28'!A:A,'Site Register'!M:M) | C83: kWh | D83: 3495 | E83: =IFERROR(IF(SUMIFS('Rates & Source Data'!$BM$106:$BM$156,'Rates & Source Data'!$C$106:$C$156,$A83,'Rates & Source Data'!$A$106:$A$156,$B83)<>0,SUMIFS('Rates & Source Data'!$BM$106:$BM$156,'Rates & Source Data'!$C$106:$C$156,$A83,'Rates & Source Data'!$A$106:$A$156,$B83),$K83),$K83) | F83: =E83 | G83: 0.47877515 | H83: 0.47877515 | I83: Ready | J83: 1677.7458 | K83: 1673.3191 | L83: 1673.3191
A84: 2001676115 | B84: =_xlfn.XLOOKUP(A84,'Budget FY26-28'!A:A,'Site Register'!M:M) | C84: kWh | D84: 28791 | E84: =IFERROR(IF(SUMIFS('Rates & Source Data'!$BM$106:$BM$156,'Rates & Source Data'!$C$106:$C$156,$A84,'Rates & Source Data'!$A$106:$A$156,$B84)<>0,SUMIFS('Rates & Source Data'!$BM$106:$BM$156,'Rates & Source Data'!$C$106:$C$156,$A84,'Rates & Source Data'!$A$106:$A$156,$B84),$K84),$K84) | F84: =E84 | G84: 0.35183603 | H84: 0.35183603 | I84: Ready | J84: 11411.343 | K84: 10129.711 | L84: 10129.711
A85: 2002190876 | B85: =_xlfn.XLOOKUP(A85,'Budget FY26-28'!A:A,'Site Register'!M:M) | C85: kWh | D85: 29818 | E85: =IFERROR(IF(SUMIFS('Rates & Source Data'!$BM$106:$BM$156,'Rates & Source Data'!$C$106:$C$156,$A85,'Rates & Source Data'!$A$106:$A$156,$B85)<>0,SUMIFS('Rates & Source Data'!$BM$106:$BM$156,'Rates & Source Data'!$C$106:$C$156,$A85,'Rates & Source Data'!$A$106:$A$156,$B85),$K85),$K85) | F85: =E85 | G85: 0.35123197 | H85: 0.35123197 | I85: Ready | J85: 11806.52 | K85: 10473.035 | L85: 10473.035
A86: 2002254877 | B86: =_xlfn.XLOOKUP(A86,'Budget FY26-28'!A:A,'Site Register'!M:M) | C86: kWh | D86: 1255064.1 | E86: =SUMIFS('Rates & Source Data'!$AO$33:$AO$100,'Rates & Source Data'!$A$33:$A$100,$A86) | F86: =SUMIFS('Rates & Source Data'!$AR$33:$AR$100,'Rates & Source Data'!$A$33:$A$100,$A86) | G86: 0.10428676 | H86: 0.10584378 | I86: Ready | J86: 340403.09 | K86: 130886.56 | L86: 132840.72
A87: 2002601115 | B87: =_xlfn.XLOOKUP(A87,'Budget FY26-28'!A:A,'Site Register'!M:M) | C87: kWh | D87: 4380 | E87: =IFERROR(IF(SUMIFS('Rates & Source Data'!$BM$106:$BM$156,'Rates & Source Data'!$C$106:$C$156,$A87,'Rates & Source Data'!$A$106:$A$156,$B87)<>0,SUMIFS('Rates & Source Data'!$BM$106:$BM$156,'Rates & Source Data'!$C$106:$C$156,$A87,'Rates & Source Data'!$A$106:$A$156,$B87),$K87),$K87) | F87: =E87 | G87: 0.47609993 | H87: 0.47609993 | I87: Ready | J87: 2450.8509 | K87: 2085.3177 | L87: 2085.3177
A88: SAAAAAB023 | B88: =_xlfn.XLOOKUP(A88,'Budget FY26-28'!A:A,'Site Register'!M:M) | C88: kWh | D88: 384392.53 | E88: =SUMIFS('Rates & Source Data'!$AO$33:$AO$100,'Rates & Source Data'!$A$33:$A$100,$A88) | F88: =SUMIFS('Rates & Source Data'!$AR$33:$AR$100,'Rates & Source Data'!$A$33:$A$100,$A88) | G88: 0.10559136 | H88: 0.10617379 | I88: Ready | J88: 106375.2 | K88: 40588.53 | L88: 40812.411
A89: SAAAAAC481 | B89: =_xlfn.XLOOKUP(A89,'Budget FY26-28'!A:A,'Site Register'!M:M) | C89: kWh | D89: 154241.09 | E89: =SUMIFS('Rates & Source Data'!$AO$33:$AO$100,'Rates & Source Data'!$A$33:$A$100,$A89) | F89: =SUMIFS('Rates & Source Data'!$AR$33:$AR$100,'Rates & Source Data'!$A$33:$A$100,$A89) | G89: 0.10704111 | H89: 0.10895567 | I89: Ready | J89: 43312.128 | K89: 16510.137 | L89: 16805.441
A90: 8000002117 | B90: =_xlfn.XLOOKUP(A90,'Budget FY26-28'!A:A,'Site Register'!M:M) | C90: kWh | D90: 448303.49 | E90: =$D90*SUMIFS('Rates & Source Data'!$B$1466:$B$1468,'Rates & Source Data'!$A$1466:$A$1468,$A90) | F90: =$D90*SUMIFS('Rates & Source Data'!$C$1466:$C$1468,'Rates & Source Data'!$A$1466:$A$1468,$A90) | I90: Ready | J90: =IF(COUNTIF('Rates & Source Data'!$A$1730:$A$1732,$A90)=0,"",SUMIFS('Rates & Source Data'!$B$1730:$B$1732,'Rates & Source Data'!$A$1730:$A$1732,$A90)) | K90: 129331.17 | L90: 129103.31
A91: 8000002963 | B91: =_xlfn.XLOOKUP(A91,'Budget FY26-28'!A:A,'Site Register'!M:M) | C91: kWh | D91: 122988.74 | E91: =$D91*SUMIFS('Rates & Source Data'!$B$1466:$B$1468,'Rates & Source Data'!$A$1466:$A$1468,$A91) | F91: =$D91*SUMIFS('Rates & Source Data'!$C$1466:$C$1468,'Rates & Source Data'!$A$1466:$A$1468,$A91) | I91: Ready | J91: =IF(COUNTIF('Rates & Source Data'!$A$1730:$A$1732,$A91)=0,"",SUMIFS('Rates & Source Data'!$B$1730:$B$1732,'Rates & Source Data'!$A$1730:$A$1732,$A91)) | K91: 35481.05 | L91: 35418.538
A92: 8000326927 | B92: =_xlfn.XLOOKUP(A92,'Budget FY26-28'!A:A,'Site Register'!M:M) | C92: kWh | D92: 489994.03 | E92: =$D92*SUMIFS('Rates & Source Data'!$B$1466:$B$1468,'Rates & Source Data'!$A$1466:$A$1468,$A92) | F92: =$D92*SUMIFS('Rates & Source Data'!$C$1466:$C$1468,'Rates & Source Data'!$A$1466:$A$1468,$A92) | I92: Ready | J92: =IF(COUNTIF('Rates & Source Data'!$A$1730:$A$1732,$A92)=0,"",SUMIFS('Rates & Source Data'!$B$1730:$B$1732,'Rates & Source Data'!$A$1730:$A$1732,$A92)) | K92: 141358.49 | L92: 141109.43
A93: 6001295311 | B93: =_xlfn.XLOOKUP(A93,'Budget FY26-28'!A:A,'Site Register'!M:M) | C93: kWh | D93: 22391 | E93: =IFERROR(IF(SUMIFS('Rates & Source Data'!$BM$106:$BM$156,'Rates & Source Data'!$C$106:$C$156,$A93,'Rates & Source Data'!$A$106:$A$156,$B93)<>0,SUMIFS('Rates & Source Data'!$BM$106:$BM$156,'Rates & Source Data'!$C$106:$C$156,$A93,'Rates & Source Data'!$A$106:$A$156,$B93),$K93),$K93) | F93: =E93 | G93: 0.23094236 | H93: 0.23094236 | I93: Ready | J93: 6801.7058 | K93: 5171.0304 | L93: 5171.0304
A94: 6001311036 | B94: =_xlfn.XLOOKUP(A94,'Budget FY26-28'!A:A,'Site Register'!M:M) | C94: kWh | D94: 1016001.5 | E94: =SUMIFS('Rates & Source Data'!$AO$33:$AO$100,'Rates & Source Data'!$A$33:$A$100,$A94) | F94: =SUMIFS('Rates & Source Data'!$AR$33:$AR$100,'Rates & Source Data'!$A$33:$A$100,$A94) | G94: 0.095106607 | H94: 0.096098457 | I94: Ready | J94: 208427.11 | K94: 96628.456 | L94: 97636.177
A95: 6001399332 | B95: =_xlfn.XLOOKUP(A95,'Budget FY26-28'!A:A,'Site Register'!M:M) | C95: kWh | D95: 58945 | E95: =IFERROR(IF(SUMIFS('Rates & Source Data'!$BM$106:$BM$156,'Rates & Source Data'!$C$106:$C$156,$A95,'Rates & Source Data'!$A$106:$A$156,$B95)<>0,SUMIFS('Rates & Source Data'!$BM$106:$BM$156,'Rates & Source Data'!$C$106:$C$156,$A95,'Rates & Source Data'!$A$106:$A$156,$B95),$K95),$K95) | F95: =E95 | G95: 0.23038058 | H95: 0.23038058 | I95: Ready | J95: 17944.258 | K95: 13579.783 | L95: 13579.783
A96: 6103034554 | B96: =_xlfn.XLOOKUP(A96,'Budget FY26-28'!A:A,'Site Register'!M:M) | C96: kWh | D96: 30794 | E96: =IFERROR(IF(SUMIFS('Rates & Source Data'!$BM$106:$BM$156,'Rates & Source Data'!$C$106:$C$156,$A96,'Rates & Source Data'!$A$106:$A$156,$B96)<>0,SUMIFS('Rates & Source Data'!$BM$106:$BM$156,'Rates & Source Data'!$C$106:$C$156,$A96,'Rates & Source Data'!$A$106:$A$156,$B96),$K96),$K96) | F96: =E96 | G96: 0.20534219 | H96: 0.20534219 | I96: Ready | J96: 8186.0456 | K96: 6323.3073 | L96: 6323.3073
A97: 6103034564 | B97: =_xlfn.XLOOKUP(A97,'Budget FY26-28'!A:A,'Site Register'!M:M) | C97: kWh | D97: 37745 | E97: =IFERROR(IF(SUMIFS('Rates & Source Data'!$BM$106:$BM$156,'Rates & Source Data'!$C$106:$C$156,$A97,'Rates & Source Data'!$A$106:$A$156,$B97)<>0,SUMIFS('Rates & Source Data'!$BM$106:$BM$156,'Rates & Source Data'!$C$106:$C$156,$A97,'Rates & Source Data'!$A$106:$A$156,$B97),$K97),$K97) | F97: =E97 | G97: 0.20277519 | H97: 0.20277519 | I97: Ready | J97: 9921.7868 | K97: 7653.7495 | L97: 7653.7495
A98: 6103034565 | B98: =_xlfn.XLOOKUP(A98,'Budget FY26-28'!A:A,'Site Register'!M:M) | C98: kWh | D98: 56975 | E98: =IFERROR(IF(SUMIFS('Rates & Source Data'!$BM$106:$BM$156,'Rates & Source Data'!$C$106:$C$156,$A98,'Rates & Source Data'!$A$106:$A$156,$B98)<>0,SUMIFS('Rates & Source Data'!$BM$106:$BM$156,'Rates & Source Data'!$C$106:$C$156,$A98,'Rates & Source Data'!$A$106:$A$156,$B98),$K98),$K98) | F98: =E98 | G98: 0.19893689 | H98: 0.19893689 | I98: Ready | J98: 14723.729 | K98: 11334.429 | L98: 11334.429
A99: 6103066712 | B99: =_xlfn.XLOOKUP(A99,'Budget FY26-28'!A:A,'Site Register'!M:M) | C99: kWh | D99: 376 | E99: =IFERROR(IF(SUMIFS('Rates & Source Data'!$BM$106:$BM$156,'Rates & Source Data'!$C$106:$C$156,$A99,'Rates & Source Data'!$A$106:$A$156,$B99)<>0,SUMIFS('Rates & Source Data'!$BM$106:$BM$156,'Rates & Source Data'!$C$106:$C$156,$A99,'Rates & Source Data'!$A$106:$A$156,$B99),$K99),$K99) | F99: =E99 | G99: 1.3330075 | H99: 1.3330075 | I99: Ready | J99: 590.33645 | K99: 501.21081 | L99: 501.21081
A100: 6203155353 | B100: =_xlfn.XLOOKUP(A100,'Budget FY26-28'!A:A,'Site Register'!M:M) | C100: kWh | D100: 27942 | E100: =IFERROR(IF(SUMIFS('Rates & Source Data'!$BM$106:$BM$156,'Rates & Source Data'!$C$106:$C$156,$A100,'Rates & Source Data'!$A$106:$A$156,$B100)<>0,SUMIFS('Rates & Source Data'!$BM$106:$BM$156,'Rates & Source Data'!$C$106:$C$156,$A100,'Rates & Source Data'!$A$106:$A$156,$B100),$K100),$K100) | F100: =E100 | G100: 0.22854948 | H100: 0.22854948 | I100: Ready | J100: 8233.8658 | K100: 6386.1295 | L100: 6386.1295
A101: 6203245874 | B101: =_xlfn.XLOOKUP(A101,'Budget FY26-28'!A:A,'Site Register'!M:M) | C101: kWh | D101: 11909 | E101: =IFERROR(IF(SUMIFS('Rates & Source Data'!$BM$106:$BM$156,'Rates & Source Data'!$C$106:$C$156,$A101,'Rates & Source Data'!$A$106:$A$156,$B101)<>0,SUMIFS('Rates & Source Data'!$BM$106:$BM$156,'Rates & Source Data'!$C$106:$C$156,$A101,'Rates & Source Data'!$A$106:$A$156,$B101),$K101),$K101) | F101: =E101 | G101: 0.25162154 | H101: 0.25162154 | I101: Ready | J101: 3822.4275 | K101: 2996.5609 | L101: 2996.5609
